[
  {
    "id": "laptop_001",
    "text": "Dell XPS 15 9520 - Dell\nGiá: 45,000,000 VND\nMô tả: Laptop cao cấp Dell XPS 15 với màn hình 4K tuyệt đẹp, hiệu năng mạnh mẽ cho công việc sáng tạo và lập trình. Thiết kế nhôm nguyên khối sang trọng, bàn phím thoải mái và touchpad rộng rãi.\nThông số kỹ thuật:\n- cpu: Intel Core i7-12700H (14 cores, up to 4.7GHz)\n- ram: 16GB DDR5 4800MHz\n- storage: 512GB PCIe NVMe SSD\n- gpu: NVIDIA GeForce RTX 3050 Ti 4GB\n- display: 15.6 inch 4K+ (3456x2160) OLED, 400 nits, 100% DCI-P3\n- battery: 86Wh, up to 13 hours\n- weight: 1.96kg\n- os: Windows 11 Pro\n- ports: 2x Thunderbolt 4, 1x USB-C 3.2, SD card reader, 3.5mm audio\nFeatures: Màn hình OLED 4K, Thunderbolt 4, Windows Hello (vân tay + IR camera), Killer Wi-Fi 6E, Bàn phím có đèn nền, Loa stereo được tinh chỉnh bởi Waves MaxxAudio\nPros: Màn hình OLED xuất sắc với màu sắc chính xác, Hiệu năng mạnh mẽ cho đa tác vụ, Thiết kế cao cấp, sang trọng, Thời lượng pin tốt cho laptop 4K, Bàn phím và touchpad chất lượng cao\nCons: Giá cao, Có thể nóng khi chạy tác vụ nặng, Webcam vẫn ở vị trí dưới màn hình, Nâng cấp RAM và SSD khó khăn\nUse_Cases: Lập trình và phát triển phần mềm, Thiết kế đồ họa và chỉnh sửa video, Công việc văn phòng cao cấp, Content creation, Machine learning và data science\nĐánh giá: 4.6/5 từ 342 người dùng",
    "metadata": {
      "type": "product",
      "category": "laptop",
      "subcategory": "ultrabook",
      "brand": "Dell",
      "name": "Dell XPS 15 9520",
      "price": 45000000,
      "rating": 4.6,
      "in_stock": true,
      "id": "laptop_001",
      "currency": "VND",
      "features": [
        "Màn hình OLED 4K",
        "Thunderbolt 4",
        "Windows Hello (vân tay + IR camera)",
        "Killer Wi-Fi 6E",
        "Bàn phím có đèn nền",
        "Loa stereo được tinh chỉnh bởi Waves MaxxAudio"
      ],
      "pros": [
        "Màn hình OLED xuất sắc với màu sắc chính xác",
        "Hiệu năng mạnh mẽ cho đa tác vụ",
        "Thiết kế cao cấp, sang trọng",
        "Thời lượng pin tốt cho laptop 4K",
        "Bàn phím và touchpad chất lượng cao"
      ],
      "cons": [
        "Giá cao",
        "Có thể nóng khi chạy tác vụ nặng",
        "Webcam vẫn ở vị trí dưới màn hình",
        "Nâng cấp RAM và SSD khó khăn"
      ],
      "use_cases": [
        "Lập trình và phát triển phần mềm",
        "Thiết kế đồ họa và chỉnh sửa video",
        "Công việc văn phòng cao cấp",
        "Content creation",
        "Machine learning và data science"
      ],
      "review_count": 342,
      "warranty": "12 tháng",
      "tags": [
        "premium",
        "4k-display",
        "content-creation",
        "programming",
        "ultrabook"
      ]
    }
  },
  {
    "id": "laptop_002",
    "text": "MacBook Air M2 13 inch - Apple\nGiá: 32,000,000 VND\nMô tả: MacBook Air M2 mỏng nhẹ với chip Apple M2 mạnh mẽ, thời lượng pin cực kỳ ấn tượng lên đến 18 giờ. Thiết kế mới với màn hình Liquid Retina và MagSafe trở lại.\nThông số kỹ thuật:\n- cpu: Apple M2 (8-core CPU: 4 performance + 4 efficiency)\n- ram: 8GB unified memory\n- storage: 256GB SSD\n- gpu: 8-core GPU\n- display: 13.6 inch Liquid Retina (2560x1664), 500 nits, P3 color\n- battery: 52.6Wh, up to 18 hours\n- weight: 1.24kg\n- os: macOS Ventura\n- ports: 2x Thunderbolt/USB 4, MagSafe 3, 3.5mm audio\nFeatures: Chip Apple M2 tiết kiệm điện, Màn hình Liquid Retina, MagSafe charging, Touch ID, Fanless design (không quạt, hoàn toàn yên tĩnh), 1080p FaceTime HD camera, Spatial audio với 4 loa\nPros: Thời lượng pin xuất sắc (18 giờ), Hiệu năng mạnh với M2, Hoàn toàn yên tĩnh (không quạt), Màn hình sáng và sắc nét, Mỏng nhẹ, dễ mang theo, Khởi động và xử lý cực nhanh\nCons: RAM chỉ 8GB, không nâng cấp được, Giá cao so với cấu hình, Ít cổng kết nối, SSD dung lượng thấp ở bản base\nUse_Cases: Lập trình web và mobile (iOS), Công việc văn phòng, Học tập và nghiên cứu, Content creation nhẹ, Di chuyển nhiều\nĐánh giá: 4.8/5 từ 567 người dùng",
    "metadata": {
      "type": "product",
      "category": "laptop",
      "subcategory": "ultrabook",
      "brand": "Apple",
      "name": "MacBook Air M2 13 inch",
      "price": 32000000,
      "rating": 4.8,
      "in_stock": true,
      "id": "laptop_002",
      "currency": "VND",
      "features": [
        "Chip Apple M2 tiết kiệm điện",
        "Màn hình Liquid Retina",
        "MagSafe charging",
        "Touch ID",
        "Fanless design (không quạt, hoàn toàn yên tĩnh)",
        "1080p FaceTime HD camera",
        "Spatial audio với 4 loa"
      ],
      "pros": [
        "Thời lượng pin xuất sắc (18 giờ)",
        "Hiệu năng mạnh với M2",
        "Hoàn toàn yên tĩnh (không quạt)",
        "Màn hình sáng và sắc nét",
        "Mỏng nhẹ, dễ mang theo",
        "Khởi động và xử lý cực nhanh"
      ],
      "cons": [
        "RAM chỉ 8GB, không nâng cấp được",
        "Giá cao so với cấu hình",
        "Ít cổng kết nối",
        "SSD dung lượng thấp ở bản base"
      ],
      "use_cases": [
        "Lập trình web và mobile (iOS)",
        "Công việc văn phòng",
        "Học tập và nghiên cứu",
        "Content creation nhẹ",
        "Di chuyển nhiều"
      ],
      "review_count": 567,
      "warranty": "12 tháng",
      "tags": [
        "ultraportable",
        "long-battery",
        "silent",
        "macos",
        "m2-chip"
      ]
    }
  },
  {
    "id": "laptop_003",
    "text": "ASUS ROG Strix G15 - ASUS\nGiá: 35,000,000 VND\nMô tả: Laptop gaming mạnh mẽ với AMD Ryzen 7 và RTX 3060, màn hình 300Hz cho trải nghiệm gaming mượt mà. Hệ thống tản nhiệt ROG Intelligent Cooling giữ máy mát mẻ ngay cả khi chơi game nặng.\nThông số kỹ thuật:\n- cpu: AMD Ryzen 7 6800H (8 cores, up to 4.7GHz)\n- ram: 16GB DDR5 4800MHz (2x8GB)\n- storage: 1TB PCIe 4.0 NVMe SSD\n- gpu: NVIDIA GeForce RTX 3060 6GB GDDR6\n- display: 15.6 inch FHD (1920x1080) 300Hz, 3ms, 100% sRGB\n- battery: 90Wh, up to 8 hours\n- weight: 2.3kg\n- os: Windows 11 Home\n- ports: 3x USB 3.2 Type-A, 1x USB-C (DP 1.4), HDMI 2.0b, RJ45, 3.5mm audio\nFeatures: Màn hình 300Hz cho gaming, RGB keyboard 4-zone, ROG Intelligent Cooling, Dolby Atmos audio, Wi-Fi 6E, MUX Switch cho hiệu năng GPU tối đa, Aura Sync lighting\nPros: Hiệu năng gaming mạnh mẽ, Màn hình 300Hz cực mượt, Tản nhiệt hiệu quả, Nâng cấp RAM và SSD dễ dàng, Giá tốt cho cấu hình\nCons: Nặng và cồng kềnh, Pin yếu khi gaming, Ồn khi chạy tác vụ nặng, Thiết kế gaming có thể không phù hợp văn phòng\nUse_Cases: Gaming AAA titles, Game development, 3D rendering và modeling, Video editing nặng, Streaming game\nĐánh giá: 4.5/5 từ 423 người dùng",
    "metadata": {
      "type": "product",
      "category": "laptop",
      "subcategory": "gaming",
      "brand": "ASUS",
      "name": "ASUS ROG Strix G15",
      "price": 35000000,
      "rating": 4.5,
      "in_stock": true,
      "id": "laptop_003",
      "currency": "VND",
      "features": [
        "Màn hình 300Hz cho gaming",
        "RGB keyboard 4-zone",
        "ROG Intelligent Cooling",
        "Dolby Atmos audio",
        "Wi-Fi 6E",
        "MUX Switch cho hiệu năng GPU tối đa",
        "Aura Sync lighting"
      ],
      "pros": [
        "Hiệu năng gaming mạnh mẽ",
        "Màn hình 300Hz cực mượt",
        "Tản nhiệt hiệu quả",
        "Nâng cấp RAM và SSD dễ dàng",
        "Giá tốt cho cấu hình"
      ],
      "cons": [
        "Nặng và cồng kềnh",
        "Pin yếu khi gaming",
        "Ồn khi chạy tác vụ nặng",
        "Thiết kế gaming có thể không phù hợp văn phòng"
      ],
      "use_cases": [
        "Gaming AAA titles",
        "Game development",
        "3D rendering và modeling",
        "Video editing nặng",
        "Streaming game"
      ],
      "review_count": 423,
      "warranty": "24 tháng",
      "tags": [
        "gaming",
        "high-refresh",
        "rtx3060",
        "amd-ryzen",
        "rgb"
      ]
    }
  },
  {
    "id": "laptop_004",
    "text": "Lenovo ThinkPad X1 Carbon Gen 10 - Lenovo\nGiá: 42,000,000 VND\nMô tả: Laptop doanh nhân cao cấp với độ bền chuẩn quân đội MIL-STD-810H, bàn phím ThinkPad huyền thoại và bảo mật cấp doanh nghiệp. Mỏng nhẹ chỉ 1.12kg nhưng cực kỳ bền bỉ.\nThông số kỹ thuật:\n- cpu: Intel Core i7-1260P (12 cores, up to 4.7GHz)\n- ram: 16GB LPDDR5 5200MHz\n- storage: 512GB PCIe Gen 4 SSD\n- gpu: Intel Iris Xe Graphics\n- display: 14 inch WUXGA (1920x1200) IPS, 400 nits, 100% sRGB\n- battery: 57Wh, up to 15 hours\n- weight: 1.12kg\n- os: Windows 11 Pro\n- ports: 2x Thunderbolt 4, 2x USB-A 3.2, HDMI 2.0, 3.5mm audio\nFeatures: Bàn phím ThinkPad với TrackPoint, Đạt chuẩn quân đội MIL-STD-810H, IR camera với Windows Hello, Fingerprint reader, ThinkShutter camera privacy, Dolby Atmos speaker system, 4G LTE option\nPros: Cực kỳ nhẹ và di động, Bàn phím tốt nhất thị trường, Độ bền cao, chuẩn quân đội, Bảo mật doanh nghiệp, Pin lâu cho laptop Intel\nCons: Giá cao, Thiết kế truyền thống, ít thay đổi, Màn hình chỉ FHD+, Hiệu năng đồ họa hạn chế\nUse_Cases: Business professionals, Lập trình và phát triển, Công việc văn phòng, Di chuyển thường xuyên, Bảo mật cao\nĐánh giá: 4.7/5 từ 289 người dùng",
    "metadata": {
      "type": "product",
      "category": "laptop",
      "subcategory": "business",
      "brand": "Lenovo",
      "name": "Lenovo ThinkPad X1 Carbon Gen 10",
      "price": 42000000,
      "rating": 4.7,
      "in_stock": true,
      "id": "laptop_004",
      "currency": "VND",
      "features": [
        "Bàn phím ThinkPad với TrackPoint",
        "Đạt chuẩn quân đội MIL-STD-810H",
        "IR camera với Windows Hello",
        "Fingerprint reader",
        "ThinkShutter camera privacy",
        "Dolby Atmos speaker system",
        "4G LTE option"
      ],
      "pros": [
        "Cực kỳ nhẹ và di động",
        "Bàn phím tốt nhất thị trường",
        "Độ bền cao, chuẩn quân đội",
        "Bảo mật doanh nghiệp",
        "Pin lâu cho laptop Intel"
      ],
      "cons": [
        "Giá cao",
        "Thiết kế truyền thống, ít thay đổi",
        "Màn hình chỉ FHD+",
        "Hiệu năng đồ họa hạn chế"
      ],
      "use_cases": [
        "Business professionals",
        "Lập trình và phát triển",
        "Công việc văn phòng",
        "Di chuyển thường xuyên",
        "Bảo mật cao"
      ],
      "review_count": 289,
      "warranty": "36 tháng",
      "tags": [
        "business",
        "ultraportable",
        "durable",
        "thinkpad",
        "security"
      ]
    }
  },
  {
    "id": "laptop_005",
    "text": "HP Pavilion 15 - HP\nGiá: 18,000,000 VND\nMô tả: Laptop phổ thông đa năng với cấu hình tốt trong tầm giá, phù hợp cho sinh viên và công việc văn phòng. Thiết kế hiện đại với viền màn hình mỏng.\nThông số kỹ thuật:\n- cpu: Intel Core i5-1235U (10 cores, up to 4.4GHz)\n- ram: 8GB DDR4 3200MHz\n- storage: 512GB PCIe NVMe SSD\n- gpu: Intel Iris Xe Graphics\n- display: 15.6 inch FHD (1920x1080) IPS, 250 nits\n- battery: 41Wh, up to 8 hours\n- weight: 1.75kg\n- os: Windows 11 Home\n- ports: 1x USB-C, 2x USB-A 3.2, HDMI 2.1, SD card reader, 3.5mm audio\nFeatures: Màn hình IPS Full HD, Bàn phím có đèn nền, Fast Charge (50% trong 45 phút), B&O audio, Wi-Fi 6, Webcam HD với privacy shutter\nPros: Giá phải chăng, Cấu hình tốt cho tầm giá, Thiết kế đẹp, hiện đại, Đầy đủ cổng kết nối, Nâng cấp RAM và SSD dễ dàng\nCons: Màn hình độ sáng thấp, Pin trung bình, Vỏ nhựa, không cao cấp, Loa yếu\nUse_Cases: Sinh viên, Văn phòng cơ bản, Entertainment nhẹ, Học online, Lập trình cơ bản\nĐánh giá: 4.2/5 từ 512 người dùng",
    "metadata": {
      "type": "product",
      "category": "laptop",
      "subcategory": "mainstream",
      "brand": "HP",
      "name": "HP Pavilion 15",
      "price": 18000000,
      "rating": 4.2,
      "in_stock": true,
      "id": "laptop_005",
      "currency": "VND",
      "features": [
        "Màn hình IPS Full HD",
        "Bàn phím có đèn nền",
        "Fast Charge (50% trong 45 phút)",
        "B&O audio",
        "Wi-Fi 6",
        "Webcam HD với privacy shutter"
      ],
      "pros": [
        "Giá phải chăng",
        "Cấu hình tốt cho tầm giá",
        "Thiết kế đẹp, hiện đại",
        "Đầy đủ cổng kết nối",
        "Nâng cấp RAM và SSD dễ dàng"
      ],
      "cons": [
        "Màn hình độ sáng thấp",
        "Pin trung bình",
        "Vỏ nhựa, không cao cấp",
        "Loa yếu"
      ],
      "use_cases": [
        "Sinh viên",
        "Văn phòng cơ bản",
        "Entertainment nhẹ",
        "Học online",
        "Lập trình cơ bản"
      ],
      "review_count": 512,
      "warranty": "12 tháng",
      "tags": [
        "budget-friendly",
        "student",
        "office",
        "mainstream",
        "value"
      ]
    }
  },
  {
    "id": "laptop_006",
    "text": "Lenovo ThinkPad X1 Carbon Gen 11 - Lenovo\nGiá: 42,000,000 VND\nMô tả: Laptop doanh nghiệp cao cấp với thiết kế carbon fiber siêu nhẹ, bảo mật tối đa và độ bền quân đội. Bàn phím TrackPoint huyền thoại và pin dài cho dân văn phòng.\nThông số kỹ thuật:\n- cpu: Intel Core i7-1365U (10 cores, up to 5.2GHz)\n- ram: 16GB LPDDR5 5200MHz\n- storage: 512GB PCIe NVMe SSD\n- gpu: Intel Iris Xe Graphics\n- display: 14 inch 2.8K (2880x1800) IPS, 400 nits, 100% sRGB\n- battery: 57Wh, up to 15 hours\n- weight: 1.12kg\n- os: Windows 11 Pro\n- ports: 2x Thunderbolt 4, 2x USB-A 3.2, HDMI 2.1, 3.5mm audio\nFeatures: Carbon fiber chassis, MIL-STD-810H durability, TrackPoint + TrackPad, ThinkShutter camera privacy, Rapid Charge (80% in 1 hour), Wi-Fi 6E + 5G optional\nPros: Siêu nhẹ chỉ 1.12kg, Bàn phím xuất sắc, Bảo mật doanh nghiệp, Pin dài 15 tiếng, Độ bền quân đội\nCons: GPU tích hợp yếu, Giá cao, Màn hình không OLED, Loa không ấn tượng\nUse_Cases: Doanh nghiệp và tập đoàn, Lập trình và development, Công tác và di chuyển nhiều, Bảo mật cao\nĐánh giá: 4.6/5 từ 234 người dùng",
    "metadata": {
      "type": "product",
      "category": "laptop",
      "subcategory": "business",
      "brand": "Lenovo",
      "name": "Lenovo ThinkPad X1 Carbon Gen 11",
      "price": 42000000,
      "rating": 4.6,
      "in_stock": true,
      "id": "laptop_006",
      "currency": "VND",
      "features": [
        "Carbon fiber chassis",
        "MIL-STD-810H durability",
        "TrackPoint + TrackPad",
        "ThinkShutter camera privacy",
        "Rapid Charge (80% in 1 hour)",
        "Wi-Fi 6E + 5G optional"
      ],
      "pros": [
        "Siêu nhẹ chỉ 1.12kg",
        "Bàn phím xuất sắc",
        "Bảo mật doanh nghiệp",
        "Pin dài 15 tiếng",
        "Độ bền quân đội"
      ],
      "cons": [
        "GPU tích hợp yếu",
        "Giá cao",
        "Màn hình không OLED",
        "Loa không ấn tượng"
      ],
      "use_cases": [
        "Doanh nghiệp và tập đoàn",
        "Lập trình và development",
        "Công tác và di chuyển nhiều",
        "Bảo mật cao"
      ],
      "review_count": 234,
      "warranty": "36 tháng",
      "tags": [
        "business",
        "ultralight",
        "security",
        "premium",
        "thinkpad"
      ]
    }
  },
  {
    "id": "laptop_007",
    "text": "HP Spectre x360 16 - HP\nGiá: 38,000,000 VND\nMô tả: Laptop 2-in-1 cao cấp với màn hình cảm ứng 16 inch, thiết kế gem-cut sang trọng và hiệu năng mạnh mẽ. Xoay 360 độ linh hoạt cho mọi tác vụ.\nThông số kỹ thuật:\n- cpu: Intel Core i7-12700H (14 cores, up to 4.7GHz)\n- ram: 16GB DDR4 3200MHz\n- storage: 1TB PCIe NVMe SSD\n- gpu: Intel Arc A370M 4GB\n- display: 16 inch 3K+ (3072x1920) OLED Touch, 400 nits, 100% DCI-P3\n- battery: 83Wh, up to 12 hours\n- weight: 2.45kg\n- os: Windows 11 Home\n- ports: 2x Thunderbolt 4, 1x USB-A 3.2, MicroSD, 3.5mm audio\nFeatures: 360-degree hinge, OLED touchscreen, HP Pen included, Bang & Olufsen speakers, Privacy camera kill switch, Fast charge 90W\nPros: Màn hình OLED tuyệt đẹp, Thiết kế 2-in-1 linh hoạt, Chất lượng build cao, Loa B&O chất lượng, Bút stylus đi kèm\nCons: Nặng cho laptop 2-in-1, Pin trung bình, Giá cao, Dễ bám vân tay\nUse_Cases: Thiết kế và sáng tạo, Thuyết trình và họp, Giải trí và media, Sinh viên và học tập\nĐánh giá: 4.3/5 từ 189 người dùng",
    "metadata": {
      "type": "product",
      "category": "laptop",
      "subcategory": "convertible",
      "brand": "HP",
      "name": "HP Spectre x360 16",
      "price": 38000000,
      "rating": 4.3,
      "in_stock": true,
      "id": "laptop_007",
      "currency": "VND",
      "features": [
        "360-degree hinge",
        "OLED touchscreen",
        "HP Pen included",
        "Bang & Olufsen speakers",
        "Privacy camera kill switch",
        "Fast charge 90W"
      ],
      "pros": [
        "Màn hình OLED tuyệt đẹp",
        "Thiết kế 2-in-1 linh hoạt",
        "Chất lượng build cao",
        "Loa B&O chất lượng",
        "Bút stylus đi kèm"
      ],
      "cons": [
        "Nặng cho laptop 2-in-1",
        "Pin trung bình",
        "Giá cao",
        "Dễ bám vân tay"
      ],
      "use_cases": [
        "Thiết kế và sáng tạo",
        "Thuyết trình và họp",
        "Giải trí và media",
        "Sinh viên và học tập"
      ],
      "review_count": 189,
      "warranty": "24 tháng",
      "tags": [
        "2-in-1",
        "touchscreen",
        "oled",
        "premium",
        "convertible"
      ]
    }
  },
  {
    "id": "laptop_008",
    "text": "Samsung Legion 13 - Samsung\nGiá: 42,850,233 VND\nMô tả: Laptop gaming Samsung với hiệu năng tốt cho công việc.\nThông số kỹ thuật:\n- cpu: Intel Core i7-13700H\n- ram: 16GB DDR5\n- storage: 512GB NVMe\n- gpu: RTX 4080 12GB\n- display: 16 inch FHD VA\n- battery: 74Wh\n- weight: 1.6kg\n- os: Ubuntu\nFeatures: Vân tay, Thunderbolt, Bluetooth 5.0, Wi-Fi 6\nPros: Thiết kế đẹp, Tản nhiệt tốt, Màn hình chất lượng, Pin trâu\nCons: Loa không hay, Ít cổng kết nối\nUse_Cases: Thiết kế, Video editing, Văn phòng, Lập trình\nĐánh giá: 4.0/5 từ 120 người dùng",
    "metadata": {
      "type": "product",
      "category": "laptop",
      "subcategory": "gaming",
      "brand": "Samsung",
      "name": "Samsung Legion 13",
      "price": 42850233,
      "rating": 4.0,
      "in_stock": true,
      "id": "laptop_008",
      "currency": "VND",
      "features": [
        "Vân tay",
        "Thunderbolt",
        "Bluetooth 5.0",
        "Wi-Fi 6"
      ],
      "pros": [
        "Thiết kế đẹp",
        "Tản nhiệt tốt",
        "Màn hình chất lượng",
        "Pin trâu"
      ],
      "cons": [
        "Loa không hay",
        "Ít cổng kết nối"
      ],
      "use_cases": [
        "Thiết kế",
        "Video editing",
        "Văn phòng",
        "Lập trình"
      ],
      "review_count": 120,
      "warranty": "36 tháng",
      "tags": [
        "gaming",
        "samsung",
        "new"
      ]
    }
  },
  {
    "id": "laptop_009",
    "text": "Alienware ThinkPad X 13 - Alienware\nGiá: 30,390,692 VND\nMô tả: Laptop ultrabook Alienware với hiệu năng mạnh mẽ cho gaming.\nThông số kỹ thuật:\n- cpu: Intel Core i5-1340P\n- ram: 16GB LPDDR5\n- storage: 512GB SSD\n- gpu: AMD Radeon Graphics\n- display: 15.6 inch 4K VA\n- battery: 56Wh\n- weight: 2.1kg\n- os: Ubuntu\nFeatures: Thunderbolt, Bàn phím có đèn nền, Vân tay, Wi-Fi 6\nPros: Thiết kế đẹp, Giá hợp lý, Tản nhiệt tốt, Hiệu năng tốt\nCons: Webcam kém, Loa không hay, Hơi nặng\nUse_Cases: Lập trình, Streaming, Business\nĐánh giá: 4.8/5 từ 391 người dùng",
    "metadata": {
      "type": "product",
      "category": "laptop",
      "subcategory": "ultrabook",
      "brand": "Alienware",
      "name": "Alienware ThinkPad X 13",
      "price": 30390692,
      "rating": 4.8,
      "in_stock": true,
      "id": "laptop_009",
      "currency": "VND",
      "features": [
        "Thunderbolt",
        "Bàn phím có đèn nền",
        "Vân tay",
        "Wi-Fi 6"
      ],
      "pros": [
        "Thiết kế đẹp",
        "Giá hợp lý",
        "Tản nhiệt tốt",
        "Hiệu năng tốt"
      ],
      "cons": [
        "Webcam kém",
        "Loa không hay",
        "Hơi nặng"
      ],
      "use_cases": [
        "Lập trình",
        "Streaming",
        "Business"
      ],
      "review_count": 391,
      "warranty": "36 tháng",
      "tags": [
        "ultrabook",
        "alienware",
        "new"
      ]
    }
  },
  {
    "id": "laptop_010",
    "text": "LG ExpertBook 13 - LG\nGiá: 37,534,372 VND\nMô tả: Laptop business LG với hiệu năng tốt cho gaming.\nThông số kỹ thuật:\n- cpu: Intel Core i7-1365U\n- ram: 32GB DDR4\n- storage: 512GB SSD\n- gpu: Intel Iris Xe\n- display: 15.6 inch FHD IPS\n- battery: 77Wh\n- weight: 1.8kg\n- os: Windows 11 Pro\nFeatures: Vân tay, Bluetooth 5.0, Thunderbolt, Sạc nhanh, HDMI\nPros: Hiệu năng tốt, Thiết kế đẹp, Nâng cấp dễ, Pin trâu, Giá hợp lý\nCons: Hơi nặng, Nóng máy, Ít cổng kết nối, Webcam kém\nUse_Cases: Gaming, Học tập, Business\nĐánh giá: 4.7/5 từ 347 người dùng",
    "metadata": {
      "type": "product",
      "category": "laptop",
      "subcategory": "business",
      "brand": "LG",
      "name": "LG ExpertBook 13",
      "price": 37534372,
      "rating": 4.7,
      "in_stock": true,
      "id": "laptop_010",
      "currency": "VND",
      "features": [
        "Vân tay",
        "Bluetooth 5.0",
        "Thunderbolt",
        "Sạc nhanh",
        "HDMI"
      ],
      "pros": [
        "Hiệu năng tốt",
        "Thiết kế đẹp",
        "Nâng cấp dễ",
        "Pin trâu",
        "Giá hợp lý"
      ],
      "cons": [
        "Hơi nặng",
        "Nóng máy",
        "Ít cổng kết nối",
        "Webcam kém"
      ],
      "use_cases": [
        "Gaming",
        "Học tập",
        "Business"
      ],
      "review_count": 347,
      "warranty": "12 tháng",
      "tags": [
        "business",
        "lg",
        "bestseller"
      ]
    }
  },
  {
    "id": "laptop_011",
    "text": "Acer Nitro 14 - Acer\nGiá: 43,943,675 VND\nMô tả: Laptop gaming Acer với hiệu năng ổn định cho học tập.\nThông số kỹ thuật:\n- cpu: Intel Core i9-13900H\n- ram: 16GB DDR4\n- storage: 512GB NVMe\n- gpu: RTX 4070 8GB\n- display: 15.6 inch 2K IPS\n- battery: 89Wh\n- weight: 2.7kg\n- os: Ubuntu\nFeatures: Wi-Fi 6, Loa stereo, Bàn phím có đèn nền, Bluetooth 5.0, USB-C, Sạc nhanh\nPros: Màn hình chất lượng, Giá hợp lý, Nâng cấp dễ, Tản nhiệt tốt, Bàn phím thoải mái\nCons: Màn hình tối, Ít cổng kết nối, Giá cao\nUse_Cases: Video editing, Gaming\nĐánh giá: 4.6/5 từ 488 người dùng",
    "metadata": {
      "type": "product",
      "category": "laptop",
      "subcategory": "gaming",
      "brand": "Acer",
      "name": "Acer Nitro 14",
      "price": 43943675,
      "rating": 4.6,
      "in_stock": false,
      "id": "laptop_011",
      "currency": "VND",
      "features": [
        "Wi-Fi 6",
        "Loa stereo",
        "Bàn phím có đèn nền",
        "Bluetooth 5.0",
        "USB-C",
        "Sạc nhanh"
      ],
      "pros": [
        "Màn hình chất lượng",
        "Giá hợp lý",
        "Nâng cấp dễ",
        "Tản nhiệt tốt",
        "Bàn phím thoải mái"
      ],
      "cons": [
        "Màn hình tối",
        "Ít cổng kết nối",
        "Giá cao"
      ],
      "use_cases": [
        "Video editing",
        "Gaming"
      ],
      "review_count": 488,
      "warranty": "12 tháng",
      "tags": [
        "gaming",
        "acer",
        "popular"
      ]
    }
  },
  {
    "id": "laptop_012",
    "text": "Lenovo ExpertBook 17 - Lenovo\nGiá: 40,825,605 VND\nMô tả: Laptop business Lenovo với hiệu năng cao cho học tập.\nThông số kỹ thuật:\n- cpu: Intel Core i7-1365U\n- ram: 32GB DDR4\n- storage: 512GB NVMe\n- gpu: AMD Radeon Graphics\n- display: 14 inch 4K OLED\n- battery: 67Wh\n- weight: 1.9kg\n- os: Windows 11 Pro\nFeatures: Webcam HD, Thunderbolt, Bluetooth 5.0\nPros: Nâng cấp dễ, Pin trâu, Thiết kế đẹp, Màn hình chất lượng\nCons: Hơi nặng, Màn hình tối, Webcam kém\nUse_Cases: Văn phòng, Thiết kế, Lập trình, Video editing\nĐánh giá: 3.8/5 từ 166 người dùng",
    "metadata": {
      "type": "product",
      "category": "laptop",
      "subcategory": "business",
      "brand": "Lenovo",
      "name": "Lenovo ExpertBook 17",
      "price": 40825605,
      "rating": 3.8,
      "in_stock": true,
      "id": "laptop_012",
      "currency": "VND",
      "features": [
        "Webcam HD",
        "Thunderbolt",
        "Bluetooth 5.0"
      ],
      "pros": [
        "Nâng cấp dễ",
        "Pin trâu",
        "Thiết kế đẹp",
        "Màn hình chất lượng"
      ],
      "cons": [
        "Hơi nặng",
        "Màn hình tối",
        "Webcam kém"
      ],
      "use_cases": [
        "Văn phòng",
        "Thiết kế",
        "Lập trình",
        "Video editing"
      ],
      "review_count": 166,
      "warranty": "24 tháng",
      "tags": [
        "business",
        "lenovo",
        "bestseller"
      ]
    }
  },
  {
    "id": "laptop_013",
    "text": "Samsung IdeaPad 17 - Samsung\nGiá: 12,643,943 VND\nMô tả: Laptop budget Samsung với hiệu năng ổn định cho sáng tạo.\nThông số kỹ thuật:\n- cpu: Intel Core i5-1235U\n- ram: 8GB DDR4\n- storage: 512GB NVMe\n- gpu: Intel UHD Graphics\n- display: 16 inch FHD OLED\n- battery: 71Wh\n- weight: 2.8kg\n- os: Windows 11 Pro\nFeatures: USB-C, Loa stereo, Webcam HD, Bluetooth 5.0, Vân tay, HDMI\nPros: Giá hợp lý, Pin trâu, Thiết kế đẹp\nCons: Webcam kém, Màn hình tối, Hơi nặng, Ít cổng kết nối\nUse_Cases: Business, Gaming, Học tập\nĐánh giá: 3.6/5 từ 58 người dùng",
    "metadata": {
      "type": "product",
      "category": "laptop",
      "subcategory": "budget",
      "brand": "Samsung",
      "name": "Samsung IdeaPad 17",
      "price": 12643943,
      "rating": 3.6,
      "in_stock": false,
      "id": "laptop_013",
      "currency": "VND",
      "features": [
        "USB-C",
        "Loa stereo",
        "Webcam HD",
        "Bluetooth 5.0",
        "Vân tay",
        "HDMI"
      ],
      "pros": [
        "Giá hợp lý",
        "Pin trâu",
        "Thiết kế đẹp"
      ],
      "cons": [
        "Webcam kém",
        "Màn hình tối",
        "Hơi nặng",
        "Ít cổng kết nối"
      ],
      "use_cases": [
        "Business",
        "Gaming",
        "Học tập"
      ],
      "review_count": 58,
      "warranty": "36 tháng",
      "tags": [
        "budget",
        "samsung",
        "recommended"
      ]
    }
  },
  {
    "id": "laptop_014",
    "text": "Acer Gram 17 - Acer\nGiá: 44,334,835 VND\nMô tả: Laptop ultrabook Acer với hiệu năng ổn định cho công việc.\nThông số kỹ thuật:\n- cpu: Intel Core i5-1340P\n- ram: 8GB LPDDR5\n- storage: 256GB SSD\n- gpu: AMD Radeon Graphics\n- display: 16 inch 4K OLED\n- battery: 46Wh\n- weight: 2.1kg\n- os: Ubuntu\nFeatures: Webcam HD, Thunderbolt, Vân tay, USB-C\nPros: Nâng cấp dễ, Thiết kế đẹp, Tản nhiệt tốt, Giá hợp lý, Pin trâu\nCons: Hơi nặng, Webcam kém\nUse_Cases: Học tập, Streaming, Văn phòng, Thiết kế\nĐánh giá: 4.8/5 từ 43 người dùng",
    "metadata": {
      "type": "product",
      "category": "laptop",
      "subcategory": "ultrabook",
      "brand": "Acer",
      "name": "Acer Gram 17",
      "price": 44334835,
      "rating": 4.8,
      "in_stock": false,
      "id": "laptop_014",
      "currency": "VND",
      "features": [
        "Webcam HD",
        "Thunderbolt",
        "Vân tay",
        "USB-C"
      ],
      "pros": [
        "Nâng cấp dễ",
        "Thiết kế đẹp",
        "Tản nhiệt tốt",
        "Giá hợp lý",
        "Pin trâu"
      ],
      "cons": [
        "Hơi nặng",
        "Webcam kém"
      ],
      "use_cases": [
        "Học tập",
        "Streaming",
        "Văn phòng",
        "Thiết kế"
      ],
      "review_count": 43,
      "warranty": "24 tháng",
      "tags": [
        "ultrabook",
        "acer",
        "recommended"
      ]
    }
  },
  {
    "id": "laptop_015",
    "text": "HP IdeaPad 13 - HP\nGiá: 9,406,766 VND\nMô tả: Laptop budget HP với hiệu năng mạnh mẽ cho học tập.\nThông số kỹ thuật:\n- cpu: Intel Core i5-1235U\n- ram: 8GB DDR4\n- storage: 512GB SSD\n- gpu: AMD Radeon Graphics\n- display: 14 inch FHD OLED\n- battery: 57Wh\n- weight: 2.1kg\n- os: Windows 11 Pro\nFeatures: HDMI, Wi-Fi 6, USB-C\nPros: Nâng cấp dễ, Giá hợp lý, Màn hình chất lượng\nCons: Ít cổng kết nối, Hơi nặng, Webcam kém, Màn hình tối\nUse_Cases: Streaming, Video editing\nĐánh giá: 4.7/5 từ 476 người dùng",
    "metadata": {
      "type": "product",
      "category": "laptop",
      "subcategory": "budget",
      "brand": "HP",
      "name": "HP IdeaPad 13",
      "price": 9406766,
      "rating": 4.7,
      "in_stock": true,
      "id": "laptop_015",
      "currency": "VND",
      "features": [
        "HDMI",
        "Wi-Fi 6",
        "USB-C"
      ],
      "pros": [
        "Nâng cấp dễ",
        "Giá hợp lý",
        "Màn hình chất lượng"
      ],
      "cons": [
        "Ít cổng kết nối",
        "Hơi nặng",
        "Webcam kém",
        "Màn hình tối"
      ],
      "use_cases": [
        "Streaming",
        "Video editing"
      ],
      "review_count": 476,
      "warranty": "36 tháng",
      "tags": [
        "budget",
        "hp",
        "popular"
      ]
    }
  },
  {
    "id": "laptop_016",
    "text": "Alienware Pavilion 17 - Alienware\nGiá: 12,707,737 VND\nMô tả: Laptop budget Alienware với hiệu năng ổn định cho học tập.\nThông số kỹ thuật:\n- cpu: AMD Ryzen 5 5500U\n- ram: 4GB DDR4\n- storage: 256GB SSD\n- gpu: Intel UHD Graphics\n- display: 17.3 inch 2K OLED\n- battery: 50Wh\n- weight: 2.0kg\n- os: Ubuntu\nFeatures: Wi-Fi 6, Bàn phím có đèn nền, Thunderbolt\nPros: Pin trâu, Màn hình chất lượng, Hiệu năng tốt, Nâng cấp dễ\nCons: Giá cao, Nóng máy, Hơi nặng\nUse_Cases: Văn phòng, Gaming, Streaming, Học tập\nĐánh giá: 4.6/5 từ 469 người dùng",
    "metadata": {
      "type": "product",
      "category": "laptop",
      "subcategory": "budget",
      "brand": "Alienware",
      "name": "Alienware Pavilion 17",
      "price": 12707737,
      "rating": 4.6,
      "in_stock": true,
      "id": "laptop_016",
      "currency": "VND",
      "features": [
        "Wi-Fi 6",
        "Bàn phím có đèn nền",
        "Thunderbolt"
      ],
      "pros": [
        "Pin trâu",
        "Màn hình chất lượng",
        "Hiệu năng tốt",
        "Nâng cấp dễ"
      ],
      "cons": [
        "Giá cao",
        "Nóng máy",
        "Hơi nặng"
      ],
      "use_cases": [
        "Văn phòng",
        "Gaming",
        "Streaming",
        "Học tập"
      ],
      "review_count": 469,
      "warranty": "24 tháng",
      "tags": [
        "budget",
        "alienware",
        "popular"
      ]
    }
  },
  {
    "id": "laptop_017",
    "text": "MSI ZenBook 17 - MSI\nGiá: 31,167,961 VND\nMô tả: Laptop ultrabook MSI với hiệu năng ổn định cho học tập.\nThông số kỹ thuật:\n- cpu: Intel Core i5-1340P\n- ram: 16GB LPDDR5\n- storage: 1TB SSD\n- gpu: AMD Radeon Graphics\n- display: 14 inch 2K VA\n- battery: 62Wh\n- weight: 1.6kg\n- os: Ubuntu\nFeatures: Wi-Fi 6, Bàn phím có đèn nền, Loa stereo\nPros: Giá hợp lý, Thiết kế đẹp, Bàn phím thoải mái, Tản nhiệt tốt\nCons: Màn hình tối, Webcam kém\nUse_Cases: Lập trình, Học tập, Business, Video editing\nĐánh giá: 4.1/5 từ 172 người dùng",
    "metadata": {
      "type": "product",
      "category": "laptop",
      "subcategory": "ultrabook",
      "brand": "MSI",
      "name": "MSI ZenBook 17",
      "price": 31167961,
      "rating": 4.1,
      "in_stock": true,
      "id": "laptop_017",
      "currency": "VND",
      "features": [
        "Wi-Fi 6",
        "Bàn phím có đèn nền",
        "Loa stereo"
      ],
      "pros": [
        "Giá hợp lý",
        "Thiết kế đẹp",
        "Bàn phím thoải mái",
        "Tản nhiệt tốt"
      ],
      "cons": [
        "Màn hình tối",
        "Webcam kém"
      ],
      "use_cases": [
        "Lập trình",
        "Học tập",
        "Business",
        "Video editing"
      ],
      "review_count": 172,
      "warranty": "24 tháng",
      "tags": [
        "ultrabook",
        "msi",
        "popular"
      ]
    }
  },
  {
    "id": "laptop_018",
    "text": "Dell ThinkPad 17 - Dell\nGiá: 19,490,428 VND\nMô tả: Laptop business Dell với hiệu năng mạnh mẽ cho gaming.\nThông số kỹ thuật:\n- cpu: Intel Core i5-1335U\n- ram: 16GB DDR4\n- storage: 1TB SSD\n- gpu: AMD Radeon Graphics\n- display: 15.6 inch 2K VA\n- battery: 73Wh\n- weight: 1.9kg\n- os: Windows 11 Pro\nFeatures: Bluetooth 5.0, Webcam HD, Loa stereo, Thunderbolt\nPros: Pin trâu, Tản nhiệt tốt, Nâng cấp dễ\nCons: Pin yếu, Giá cao, Màn hình tối, Webcam kém\nUse_Cases: Streaming, Business, Gaming, Video editing\nĐánh giá: 3.7/5 từ 87 người dùng",
    "metadata": {
      "type": "product",
      "category": "laptop",
      "subcategory": "business",
      "brand": "Dell",
      "name": "Dell ThinkPad 17",
      "price": 19490428,
      "rating": 3.7,
      "in_stock": false,
      "id": "laptop_018",
      "currency": "VND",
      "features": [
        "Bluetooth 5.0",
        "Webcam HD",
        "Loa stereo",
        "Thunderbolt"
      ],
      "pros": [
        "Pin trâu",
        "Tản nhiệt tốt",
        "Nâng cấp dễ"
      ],
      "cons": [
        "Pin yếu",
        "Giá cao",
        "Màn hình tối",
        "Webcam kém"
      ],
      "use_cases": [
        "Streaming",
        "Business",
        "Gaming",
        "Video editing"
      ],
      "review_count": 87,
      "warranty": "24 tháng",
      "tags": [
        "business",
        "dell",
        "recommended"
      ]
    }
  },
  {
    "id": "laptop_019",
    "text": "Acer ExpertBook 17 - Acer\nGiá: 27,838,175 VND\nMô tả: Laptop business Acer với hiệu năng mạnh mẽ cho sáng tạo.\nThông số kỹ thuật:\n- cpu: Intel Core i5-1335U\n- ram: 16GB DDR4\n- storage: 256GB SSD\n- gpu: Intel Iris Xe\n- display: 16 inch 2K OLED\n- battery: 83Wh\n- weight: 1.7kg\n- os: Windows 11 Pro\nFeatures: Bàn phím có đèn nền, Webcam HD, Thunderbolt\nPros: Bàn phím thoải mái, Thiết kế đẹp, Màn hình chất lượng, Pin trâu\nCons: Màn hình tối, Webcam kém, Giá cao, Ít cổng kết nối\nUse_Cases: Gaming, Học tập\nĐánh giá: 3.8/5 từ 10 người dùng",
    "metadata": {
      "type": "product",
      "category": "laptop",
      "subcategory": "business",
      "brand": "Acer",
      "name": "Acer ExpertBook 17",
      "price": 27838175,
      "rating": 3.8,
      "in_stock": false,
      "id": "laptop_019",
      "currency": "VND",
      "features": [
        "Bàn phím có đèn nền",
        "Webcam HD",
        "Thunderbolt"
      ],
      "pros": [
        "Bàn phím thoải mái",
        "Thiết kế đẹp",
        "Màn hình chất lượng",
        "Pin trâu"
      ],
      "cons": [
        "Màn hình tối",
        "Webcam kém",
        "Giá cao",
        "Ít cổng kết nối"
      ],
      "use_cases": [
        "Gaming",
        "Học tập"
      ],
      "review_count": 10,
      "warranty": "12 tháng",
      "tags": [
        "business",
        "acer",
        "popular"
      ]
    }
  },
  {
    "id": "laptop_020",
    "text": "Lenovo Spectre 15 - Lenovo\nGiá: 40,078,807 VND\nMô tả: Laptop ultrabook Lenovo với hiệu năng ổn định cho sáng tạo.\nThông số kỹ thuật:\n- cpu: Intel Core i5-1340P\n- ram: 8GB LPDDR5\n- storage: 512GB SSD\n- gpu: Intel UHD Graphics\n- display: 17.3 inch 2K VA\n- battery: 57Wh\n- weight: 1.6kg\n- os: Windows 11 Home\nFeatures: Thunderbolt, Loa stereo, Wi-Fi 6, Webcam HD, USB-C\nPros: Nâng cấp dễ, Pin trâu, Giá hợp lý, Bàn phím thoải mái, Tản nhiệt tốt\nCons: Màn hình tối, Nóng máy, Ít cổng kết nối\nUse_Cases: Gaming, Thiết kế\nĐánh giá: 4.0/5 từ 58 người dùng",
    "metadata": {
      "type": "product",
      "category": "laptop",
      "subcategory": "ultrabook",
      "brand": "Lenovo",
      "name": "Lenovo Spectre 15",
      "price": 40078807,
      "rating": 4.0,
      "in_stock": true,
      "id": "laptop_020",
      "currency": "VND",
      "features": [
        "Thunderbolt",
        "Loa stereo",
        "Wi-Fi 6",
        "Webcam HD",
        "USB-C"
      ],
      "pros": [
        "Nâng cấp dễ",
        "Pin trâu",
        "Giá hợp lý",
        "Bàn phím thoải mái",
        "Tản nhiệt tốt"
      ],
      "cons": [
        "Màn hình tối",
        "Nóng máy",
        "Ít cổng kết nối"
      ],
      "use_cases": [
        "Gaming",
        "Thiết kế"
      ],
      "review_count": 58,
      "warranty": "12 tháng",
      "tags": [
        "ultrabook",
        "lenovo",
        "popular"
      ]
    }
  },
  {
    "id": "laptop_021",
    "text": "ASUS TUF 16 - ASUS\nGiá: 46,687,942 VND\nMô tả: Laptop gaming ASUS với hiệu năng ổn định cho sáng tạo.\nThông số kỹ thuật:\n- cpu: AMD Ryzen 7 7700H\n- ram: 32GB DDR5\n- storage: 512GB SSD\n- gpu: RTX 4080 12GB\n- display: 14 inch 2K VA\n- battery: 54Wh\n- weight: 1.5kg\n- os: Windows 11 Pro\nFeatures: Wi-Fi 6, Bluetooth 5.0, Loa stereo\nPros: Màn hình chất lượng, Nâng cấp dễ, Pin trâu, Giá hợp lý, Bàn phím thoải mái\nCons: Màn hình tối, Loa không hay, Nóng máy\nUse_Cases: Học tập, Gaming\nĐánh giá: 3.6/5 từ 471 người dùng",
    "metadata": {
      "type": "product",
      "category": "laptop",
      "subcategory": "gaming",
      "brand": "ASUS",
      "name": "ASUS TUF 16",
      "price": 46687942,
      "rating": 3.6,
      "in_stock": true,
      "id": "laptop_021",
      "currency": "VND",
      "features": [
        "Wi-Fi 6",
        "Bluetooth 5.0",
        "Loa stereo"
      ],
      "pros": [
        "Màn hình chất lượng",
        "Nâng cấp dễ",
        "Pin trâu",
        "Giá hợp lý",
        "Bàn phím thoải mái"
      ],
      "cons": [
        "Màn hình tối",
        "Loa không hay",
        "Nóng máy"
      ],
      "use_cases": [
        "Học tập",
        "Gaming"
      ],
      "review_count": 471,
      "warranty": "36 tháng",
      "tags": [
        "gaming",
        "asus",
        "bestseller"
      ]
    }
  },
  {
    "id": "laptop_022",
    "text": "MSI Predator 14 - MSI\nGiá: 57,109,577 VND\nMô tả: Laptop gaming MSI với hiệu năng tốt cho học tập.\nThông số kỹ thuật:\n- cpu: AMD Ryzen 9 7900H\n- ram: 16GB DDR4\n- storage: 512GB SSD\n- gpu: RTX 4060 8GB\n- display: 14 inch 4K VA\n- battery: 48Wh\n- weight: 2.6kg\n- os: Windows 11 Home\nFeatures: USB-C, Sạc nhanh, Bàn phím có đèn nền, Webcam HD\nPros: Nâng cấp dễ, Thiết kế đẹp, Hiệu năng tốt, Tản nhiệt tốt, Giá hợp lý\nCons: Màn hình tối, Ít cổng kết nối, Pin yếu, Nóng máy\nUse_Cases: Lập trình, Văn phòng, Streaming, Video editing\nĐánh giá: 3.8/5 từ 305 người dùng",
    "metadata": {
      "type": "product",
      "category": "laptop",
      "subcategory": "gaming",
      "brand": "MSI",
      "name": "MSI Predator 14",
      "price": 57109577,
      "rating": 3.8,
      "in_stock": true,
      "id": "laptop_022",
      "currency": "VND",
      "features": [
        "USB-C",
        "Sạc nhanh",
        "Bàn phím có đèn nền",
        "Webcam HD"
      ],
      "pros": [
        "Nâng cấp dễ",
        "Thiết kế đẹp",
        "Hiệu năng tốt",
        "Tản nhiệt tốt",
        "Giá hợp lý"
      ],
      "cons": [
        "Màn hình tối",
        "Ít cổng kết nối",
        "Pin yếu",
        "Nóng máy"
      ],
      "use_cases": [
        "Lập trình",
        "Văn phòng",
        "Streaming",
        "Video editing"
      ],
      "review_count": 305,
      "warranty": "12 tháng",
      "tags": [
        "gaming",
        "msi",
        "bestseller"
      ]
    }
  },
  {
    "id": "laptop_023",
    "text": "MSI EliteBook 13 - MSI\nGiá: 33,508,979 VND\nMô tả: Laptop business MSI với hiệu năng tốt cho gaming.\nThông số kỹ thuật:\n- cpu: Intel Core i7-1365U\n- ram: 32GB DDR4\n- storage: 512GB SSD\n- gpu: AMD Radeon Graphics\n- display: 17.3 inch FHD IPS\n- battery: 87Wh\n- weight: 2.4kg\n- os: Windows 11 Pro\nFeatures: Wi-Fi 6, HDMI, USB-C, Sạc nhanh, Bàn phím có đèn nền, Thunderbolt\nPros: Màn hình chất lượng, Bàn phím thoải mái, Pin trâu, Giá hợp lý, Thiết kế đẹp\nCons: Pin yếu, Nóng máy, Hơi nặng\nUse_Cases: Học tập, Lập trình, Gaming\nĐánh giá: 4.3/5 từ 303 người dùng",
    "metadata": {
      "type": "product",
      "category": "laptop",
      "subcategory": "business",
      "brand": "MSI",
      "name": "MSI EliteBook 13",
      "price": 33508979,
      "rating": 4.3,
      "in_stock": false,
      "id": "laptop_023",
      "currency": "VND",
      "features": [
        "Wi-Fi 6",
        "HDMI",
        "USB-C",
        "Sạc nhanh",
        "Bàn phím có đèn nền",
        "Thunderbolt"
      ],
      "pros": [
        "Màn hình chất lượng",
        "Bàn phím thoải mái",
        "Pin trâu",
        "Giá hợp lý",
        "Thiết kế đẹp"
      ],
      "cons": [
        "Pin yếu",
        "Nóng máy",
        "Hơi nặng"
      ],
      "use_cases": [
        "Học tập",
        "Lập trình",
        "Gaming"
      ],
      "review_count": 303,
      "warranty": "36 tháng",
      "tags": [
        "business",
        "msi",
        "recommended"
      ]
    }
  },
  {
    "id": "laptop_024",
    "text": "Alienware ThinkPad 17 - Alienware\nGiá: 23,743,909 VND\nMô tả: Laptop business Alienware với hiệu năng cao cho công việc.\nThông số kỹ thuật:\n- cpu: AMD Ryzen 5 PRO 7530U\n- ram: 16GB DDR4\n- storage: 512GB SSD\n- gpu: Intel Iris Xe\n- display: 15.6 inch 2K IPS\n- battery: 47Wh\n- weight: 1.8kg\n- os: Windows 11 Home\nFeatures: HDMI, Bluetooth 5.0, Sạc nhanh, Bàn phím có đèn nền, Loa stereo\nPros: Nâng cấp dễ, Giá hợp lý, Bàn phím thoải mái, Màn hình chất lượng, Tản nhiệt tốt\nCons: Pin yếu, Nóng máy, Webcam kém, Màn hình tối\nUse_Cases: Lập trình, Video editing\nĐánh giá: 4.4/5 từ 278 người dùng",
    "metadata": {
      "type": "product",
      "category": "laptop",
      "subcategory": "business",
      "brand": "Alienware",
      "name": "Alienware ThinkPad 17",
      "price": 23743909,
      "rating": 4.4,
      "in_stock": false,
      "id": "laptop_024",
      "currency": "VND",
      "features": [
        "HDMI",
        "Bluetooth 5.0",
        "Sạc nhanh",
        "Bàn phím có đèn nền",
        "Loa stereo"
      ],
      "pros": [
        "Nâng cấp dễ",
        "Giá hợp lý",
        "Bàn phím thoải mái",
        "Màn hình chất lượng",
        "Tản nhiệt tốt"
      ],
      "cons": [
        "Pin yếu",
        "Nóng máy",
        "Webcam kém",
        "Màn hình tối"
      ],
      "use_cases": [
        "Lập trình",
        "Video editing"
      ],
      "review_count": 278,
      "warranty": "36 tháng",
      "tags": [
        "business",
        "alienware",
        "bestseller"
      ]
    }
  },
  {
    "id": "laptop_025",
    "text": "ASUS Latitude 16 - ASUS\nGiá: 29,930,372 VND\nMô tả: Laptop business ASUS với hiệu năng cao cho gaming.\nThông số kỹ thuật:\n- cpu: AMD Ryzen 5 PRO 7530U\n- ram: 8GB DDR4\n- storage: 512GB NVMe\n- gpu: Intel Iris Xe\n- display: 17.3 inch 4K VA\n- battery: 73Wh\n- weight: 2.6kg\n- os: Windows 11 Home\nFeatures: Thunderbolt, Vân tay, Bluetooth 5.0, Bàn phím có đèn nền, Sạc nhanh\nPros: Bàn phím thoải mái, Giá hợp lý, Hiệu năng tốt, Pin trâu, Thiết kế đẹp\nCons: Nóng máy, Webcam kém, Ít cổng kết nối\nUse_Cases: Học tập, Streaming\nĐánh giá: 4.1/5 từ 294 người dùng",
    "metadata": {
      "type": "product",
      "category": "laptop",
      "subcategory": "business",
      "brand": "ASUS",
      "name": "ASUS Latitude 16",
      "price": 29930372,
      "rating": 4.1,
      "in_stock": false,
      "id": "laptop_025",
      "currency": "VND",
      "features": [
        "Thunderbolt",
        "Vân tay",
        "Bluetooth 5.0",
        "Bàn phím có đèn nền",
        "Sạc nhanh"
      ],
      "pros": [
        "Bàn phím thoải mái",
        "Giá hợp lý",
        "Hiệu năng tốt",
        "Pin trâu",
        "Thiết kế đẹp"
      ],
      "cons": [
        "Nóng máy",
        "Webcam kém",
        "Ít cổng kết nối"
      ],
      "use_cases": [
        "Học tập",
        "Streaming"
      ],
      "review_count": 294,
      "warranty": "24 tháng",
      "tags": [
        "business",
        "asus",
        "popular"
      ]
    }
  },
  {
    "id": "laptop_026",
    "text": "Lenovo Blade 17 - Lenovo\nGiá: 50,778,475 VND\nMô tả: Laptop gaming Lenovo với hiệu năng tốt cho gaming.\nThông số kỹ thuật:\n- cpu: Intel Core i9-13900H\n- ram: 16GB DDR5\n- storage: 1TB SSD\n- gpu: RX 7600M XT 8GB\n- display: 17.3 inch 2K OLED\n- battery: 55Wh\n- weight: 2.4kg\n- os: Windows 11 Pro\nFeatures: Bàn phím có đèn nền, Loa stereo, Sạc nhanh\nPros: Tản nhiệt tốt, Hiệu năng tốt, Màn hình chất lượng, Bàn phím thoải mái\nCons: Ít cổng kết nối, Loa không hay, Màn hình tối\nUse_Cases: Video editing, Văn phòng\nĐánh giá: 4.6/5 từ 300 người dùng",
    "metadata": {
      "type": "product",
      "category": "laptop",
      "subcategory": "gaming",
      "brand": "Lenovo",
      "name": "Lenovo Blade 17",
      "price": 50778475,
      "rating": 4.6,
      "in_stock": true,
      "id": "laptop_026",
      "currency": "VND",
      "features": [
        "Bàn phím có đèn nền",
        "Loa stereo",
        "Sạc nhanh"
      ],
      "pros": [
        "Tản nhiệt tốt",
        "Hiệu năng tốt",
        "Màn hình chất lượng",
        "Bàn phím thoải mái"
      ],
      "cons": [
        "Ít cổng kết nối",
        "Loa không hay",
        "Màn hình tối"
      ],
      "use_cases": [
        "Video editing",
        "Văn phòng"
      ],
      "review_count": 300,
      "warranty": "24 tháng",
      "tags": [
        "gaming",
        "lenovo",
        "popular"
      ]
    }
  },
  {
    "id": "laptop_027",
    "text": "Razer Predator 17 - Razer\nGiá: 26,089,377 VND\nMô tả: Laptop gaming Razer với hiệu năng ổn định cho gaming.\nThông số kỹ thuật:\n- cpu: Intel Core i9-13900H\n- ram: 16GB DDR5\n- storage: 512GB SSD\n- gpu: RX 7600M XT 8GB\n- display: 15.6 inch 4K VA\n- battery: 75Wh\n- weight: 2.2kg\n- os: Windows 11 Home\nFeatures: Vân tay, HDMI, Sạc nhanh, USB-C\nPros: Hiệu năng tốt, Giá hợp lý, Màn hình chất lượng, Tản nhiệt tốt, Bàn phím thoải mái\nCons: Pin yếu, Nóng máy, Giá cao, Hơi nặng\nUse_Cases: Video editing, Văn phòng, Thiết kế\nĐánh giá: 4.4/5 từ 18 người dùng",
    "metadata": {
      "type": "product",
      "category": "laptop",
      "subcategory": "gaming",
      "brand": "Razer",
      "name": "Razer Predator 17",
      "price": 26089377,
      "rating": 4.4,
      "in_stock": true,
      "id": "laptop_027",
      "currency": "VND",
      "features": [
        "Vân tay",
        "HDMI",
        "Sạc nhanh",
        "USB-C"
      ],
      "pros": [
        "Hiệu năng tốt",
        "Giá hợp lý",
        "Màn hình chất lượng",
        "Tản nhiệt tốt",
        "Bàn phím thoải mái"
      ],
      "cons": [
        "Pin yếu",
        "Nóng máy",
        "Giá cao",
        "Hơi nặng"
      ],
      "use_cases": [
        "Video editing",
        "Văn phòng",
        "Thiết kế"
      ],
      "review_count": 18,
      "warranty": "24 tháng",
      "tags": [
        "gaming",
        "razer",
        "new"
      ]
    }
  },
  {
    "id": "laptop_028",
    "text": "Samsung Spectre 16 - Samsung\nGiá: 20,721,053 VND\nMô tả: Laptop ultrabook Samsung với hiệu năng ổn định cho công việc.\nThông số kỹ thuật:\n- cpu: AMD Ryzen 5 7530U\n- ram: 8GB LPDDR5\n- storage: 256GB SSD\n- gpu: AMD Radeon Graphics\n- display: 17.3 inch 4K VA\n- battery: 90Wh\n- weight: 2.5kg\n- os: Windows 11 Pro\nFeatures: Bluetooth 5.0, Thunderbolt, Wi-Fi 6, Sạc nhanh\nPros: Giá hợp lý, Pin trâu, Tản nhiệt tốt\nCons: Ít cổng kết nối, Hơi nặng\nUse_Cases: Văn phòng, Business, Lập trình, Video editing\nĐánh giá: 4.6/5 từ 495 người dùng",
    "metadata": {
      "type": "product",
      "category": "laptop",
      "subcategory": "ultrabook",
      "brand": "Samsung",
      "name": "Samsung Spectre 16",
      "price": 20721053,
      "rating": 4.6,
      "in_stock": false,
      "id": "laptop_028",
      "currency": "VND",
      "features": [
        "Bluetooth 5.0",
        "Thunderbolt",
        "Wi-Fi 6",
        "Sạc nhanh"
      ],
      "pros": [
        "Giá hợp lý",
        "Pin trâu",
        "Tản nhiệt tốt"
      ],
      "cons": [
        "Ít cổng kết nối",
        "Hơi nặng"
      ],
      "use_cases": [
        "Văn phòng",
        "Business",
        "Lập trình",
        "Video editing"
      ],
      "review_count": 495,
      "warranty": "12 tháng",
      "tags": [
        "ultrabook",
        "samsung",
        "new"
      ]
    }
  },
  {
    "id": "laptop_029",
    "text": "HP ExpertBook 15 - HP\nGiá: 18,654,205 VND\nMô tả: Laptop business HP với hiệu năng tốt cho sáng tạo.\nThông số kỹ thuật:\n- cpu: AMD Ryzen 5 PRO 7530U\n- ram: 16GB DDR4\n- storage: 512GB SSD\n- gpu: AMD Radeon Graphics\n- display: 16 inch FHD VA\n- battery: 75Wh\n- weight: 1.5kg\n- os: Windows 11 Pro\nFeatures: HDMI, Vân tay, USB-C, Thunderbolt\nPros: Pin trâu, Nâng cấp dễ, Hiệu năng tốt, Giá hợp lý\nCons: Nóng máy, Loa không hay\nUse_Cases: Văn phòng, Gaming, Business\nĐánh giá: 4.4/5 từ 127 người dùng",
    "metadata": {
      "type": "product",
      "category": "laptop",
      "subcategory": "business",
      "brand": "HP",
      "name": "HP ExpertBook 15",
      "price": 18654205,
      "rating": 4.4,
      "in_stock": false,
      "id": "laptop_029",
      "currency": "VND",
      "features": [
        "HDMI",
        "Vân tay",
        "USB-C",
        "Thunderbolt"
      ],
      "pros": [
        "Pin trâu",
        "Nâng cấp dễ",
        "Hiệu năng tốt",
        "Giá hợp lý"
      ],
      "cons": [
        "Nóng máy",
        "Loa không hay"
      ],
      "use_cases": [
        "Văn phòng",
        "Gaming",
        "Business"
      ],
      "review_count": 127,
      "warranty": "24 tháng",
      "tags": [
        "business",
        "hp",
        "popular"
      ]
    }
  },
  {
    "id": "laptop_030",
    "text": "Dell ThinkPad 16 - Dell\nGiá: 26,029,014 VND\nMô tả: Laptop business Dell với hiệu năng tốt cho sáng tạo.\nThông số kỹ thuật:\n- cpu: AMD Ryzen 5 PRO 7530U\n- ram: 8GB DDR4\n- storage: 512GB NVMe\n- gpu: Intel Iris Xe\n- display: 14 inch 2K VA\n- battery: 78Wh\n- weight: 2.4kg\n- os: Windows 11 Home\nFeatures: HDMI, Loa stereo, Vân tay, Sạc nhanh, Thunderbolt\nPros: Pin trâu, Thiết kế đẹp, Tản nhiệt tốt\nCons: Loa không hay, Nóng máy, Màn hình tối\nUse_Cases: Thiết kế, Học tập\nĐánh giá: 4.0/5 từ 57 người dùng",
    "metadata": {
      "type": "product",
      "category": "laptop",
      "subcategory": "business",
      "brand": "Dell",
      "name": "Dell ThinkPad 16",
      "price": 26029014,
      "rating": 4.0,
      "in_stock": true,
      "id": "laptop_030",
      "currency": "VND",
      "features": [
        "HDMI",
        "Loa stereo",
        "Vân tay",
        "Sạc nhanh",
        "Thunderbolt"
      ],
      "pros": [
        "Pin trâu",
        "Thiết kế đẹp",
        "Tản nhiệt tốt"
      ],
      "cons": [
        "Loa không hay",
        "Nóng máy",
        "Màn hình tối"
      ],
      "use_cases": [
        "Thiết kế",
        "Học tập"
      ],
      "review_count": 57,
      "warranty": "24 tháng",
      "tags": [
        "business",
        "dell",
        "recommended"
      ]
    }
  },
  {
    "id": "laptop_031",
    "text": "Lenovo Latitude 17 - Lenovo\nGiá: 25,666,268 VND\nMô tả: Laptop business Lenovo với hiệu năng tốt cho học tập.\nThông số kỹ thuật:\n- cpu: Intel Core i7-1365U\n- ram: 32GB DDR4\n- storage: 512GB SSD\n- gpu: Intel Iris Xe\n- display: 16 inch FHD VA\n- battery: 65Wh\n- weight: 2.6kg\n- os: Ubuntu\nFeatures: Sạc nhanh, USB-C, Vân tay\nPros: Màn hình chất lượng, Thiết kế đẹp, Giá hợp lý\nCons: Loa không hay, Giá cao, Ít cổng kết nối, Nóng máy\nUse_Cases: Streaming, Lập trình, Video editing, Gaming\nĐánh giá: 4.3/5 từ 432 người dùng",
    "metadata": {
      "type": "product",
      "category": "laptop",
      "subcategory": "business",
      "brand": "Lenovo",
      "name": "Lenovo Latitude 17",
      "price": 25666268,
      "rating": 4.3,
      "in_stock": true,
      "id": "laptop_031",
      "currency": "VND",
      "features": [
        "Sạc nhanh",
        "USB-C",
        "Vân tay"
      ],
      "pros": [
        "Màn hình chất lượng",
        "Thiết kế đẹp",
        "Giá hợp lý"
      ],
      "cons": [
        "Loa không hay",
        "Giá cao",
        "Ít cổng kết nối",
        "Nóng máy"
      ],
      "use_cases": [
        "Streaming",
        "Lập trình",
        "Video editing",
        "Gaming"
      ],
      "review_count": 432,
      "warranty": "24 tháng",
      "tags": [
        "business",
        "lenovo",
        "bestseller"
      ]
    }
  },
  {
    "id": "laptop_032",
    "text": "Samsung ROG 15 - Samsung\nGiá: 30,433,808 VND\nMô tả: Laptop gaming Samsung với hiệu năng cao cho gaming.\nThông số kỹ thuật:\n- cpu: Intel Core i9-13900H\n- ram: 16GB DDR5\n- storage: 256GB SSD\n- gpu: RTX 4060 8GB\n- display: 15.6 inch 2K OLED\n- battery: 71Wh\n- weight: 1.7kg\n- os: Windows 11 Pro\nFeatures: Loa stereo, Vân tay, USB-C, Thunderbolt, Webcam HD\nPros: Bàn phím thoải mái, Giá hợp lý, Tản nhiệt tốt\nCons: Pin yếu, Màn hình tối, Hơi nặng\nUse_Cases: Streaming, Lập trình, Học tập\nĐánh giá: 4.0/5 từ 417 người dùng",
    "metadata": {
      "type": "product",
      "category": "laptop",
      "subcategory": "gaming",
      "brand": "Samsung",
      "name": "Samsung ROG 15",
      "price": 30433808,
      "rating": 4.0,
      "in_stock": true,
      "id": "laptop_032",
      "currency": "VND",
      "features": [
        "Loa stereo",
        "Vân tay",
        "USB-C",
        "Thunderbolt",
        "Webcam HD"
      ],
      "pros": [
        "Bàn phím thoải mái",
        "Giá hợp lý",
        "Tản nhiệt tốt"
      ],
      "cons": [
        "Pin yếu",
        "Màn hình tối",
        "Hơi nặng"
      ],
      "use_cases": [
        "Streaming",
        "Lập trình",
        "Học tập"
      ],
      "review_count": 417,
      "warranty": "36 tháng",
      "tags": [
        "gaming",
        "samsung",
        "bestseller"
      ]
    }
  },
  {
    "id": "laptop_033",
    "text": "Razer ThinkPad X 17 - Razer\nGiá: 38,535,619 VND\nMô tả: Laptop ultrabook Razer với hiệu năng cao cho học tập.\nThông số kỹ thuật:\n- cpu: Intel Core i5-1340P\n- ram: 16GB DDR4\n- storage: 512GB SSD\n- gpu: Intel UHD Graphics\n- display: 14 inch 4K VA\n- battery: 75Wh\n- weight: 1.3kg\n- os: Ubuntu\nFeatures: Sạc nhanh, Bluetooth 5.0, Thunderbolt, Bàn phím có đèn nền, USB-C\nPros: Nâng cấp dễ, Bàn phím thoải mái, Màn hình chất lượng, Pin trâu\nCons: Hơi nặng, Ít cổng kết nối, Nóng máy, Giá cao\nUse_Cases: Video editing, Lập trình, Văn phòng\nĐánh giá: 4.6/5 từ 481 người dùng",
    "metadata": {
      "type": "product",
      "category": "laptop",
      "subcategory": "ultrabook",
      "brand": "Razer",
      "name": "Razer ThinkPad X 17",
      "price": 38535619,
      "rating": 4.6,
      "in_stock": true,
      "id": "laptop_033",
      "currency": "VND",
      "features": [
        "Sạc nhanh",
        "Bluetooth 5.0",
        "Thunderbolt",
        "Bàn phím có đèn nền",
        "USB-C"
      ],
      "pros": [
        "Nâng cấp dễ",
        "Bàn phím thoải mái",
        "Màn hình chất lượng",
        "Pin trâu"
      ],
      "cons": [
        "Hơi nặng",
        "Ít cổng kết nối",
        "Nóng máy",
        "Giá cao"
      ],
      "use_cases": [
        "Video editing",
        "Lập trình",
        "Văn phòng"
      ],
      "review_count": 481,
      "warranty": "12 tháng",
      "tags": [
        "ultrabook",
        "razer",
        "popular"
      ]
    }
  },
  {
    "id": "laptop_034",
    "text": "Acer VivoBook 14 - Acer\nGiá: 19,770,212 VND\nMô tả: Laptop budget Acer với hiệu năng tốt cho công việc.\nThông số kỹ thuật:\n- cpu: AMD Ryzen 5 5500U\n- ram: 8GB LPDDR4\n- storage: 1TB SSD\n- gpu: AMD Radeon Graphics\n- display: 14 inch FHD OLED\n- battery: 50Wh\n- weight: 1.6kg\n- os: Windows 11 Pro\nFeatures: Vân tay, Bàn phím có đèn nền, Bluetooth 5.0\nPros: Bàn phím thoải mái, Hiệu năng tốt, Tản nhiệt tốt, Nâng cấp dễ\nCons: Pin yếu, Nóng máy\nUse_Cases: Gaming, Streaming\nĐánh giá: 4.1/5 từ 55 người dùng",
    "metadata": {
      "type": "product",
      "category": "laptop",
      "subcategory": "budget",
      "brand": "Acer",
      "name": "Acer VivoBook 14",
      "price": 19770212,
      "rating": 4.1,
      "in_stock": true,
      "id": "laptop_034",
      "currency": "VND",
      "features": [
        "Vân tay",
        "Bàn phím có đèn nền",
        "Bluetooth 5.0"
      ],
      "pros": [
        "Bàn phím thoải mái",
        "Hiệu năng tốt",
        "Tản nhiệt tốt",
        "Nâng cấp dễ"
      ],
      "cons": [
        "Pin yếu",
        "Nóng máy"
      ],
      "use_cases": [
        "Gaming",
        "Streaming"
      ],
      "review_count": 55,
      "warranty": "24 tháng",
      "tags": [
        "budget",
        "acer",
        "popular"
      ]
    }
  },
  {
    "id": "laptop_035",
    "text": "LG Nitro 15 - LG\nGiá: 41,197,904 VND\nMô tả: Laptop gaming LG với hiệu năng cao cho công việc.\nThông số kỹ thuật:\n- cpu: Intel Core i7-13700H\n- ram: 16GB DDR5\n- storage: 512GB SSD\n- gpu: RTX 4060 8GB\n- display: 14 inch 2K IPS\n- battery: 59Wh\n- weight: 1.3kg\n- os: Windows 11 Pro\nFeatures: Wi-Fi 6, Sạc nhanh, Bàn phím có đèn nền, Vân tay, Loa stereo, HDMI\nPros: Bàn phím thoải mái, Giá hợp lý, Nâng cấp dễ\nCons: Ít cổng kết nối, Hơi nặng, Nóng máy\nUse_Cases: Văn phòng, Business, Streaming, Video editing\nĐánh giá: 3.9/5 từ 66 người dùng",
    "metadata": {
      "type": "product",
      "category": "laptop",
      "subcategory": "gaming",
      "brand": "LG",
      "name": "LG Nitro 15",
      "price": 41197904,
      "rating": 3.9,
      "in_stock": true,
      "id": "laptop_035",
      "currency": "VND",
      "features": [
        "Wi-Fi 6",
        "Sạc nhanh",
        "Bàn phím có đèn nền",
        "Vân tay",
        "Loa stereo",
        "HDMI"
      ],
      "pros": [
        "Bàn phím thoải mái",
        "Giá hợp lý",
        "Nâng cấp dễ"
      ],
      "cons": [
        "Ít cổng kết nối",
        "Hơi nặng",
        "Nóng máy"
      ],
      "use_cases": [
        "Văn phòng",
        "Business",
        "Streaming",
        "Video editing"
      ],
      "review_count": 66,
      "warranty": "36 tháng",
      "tags": [
        "gaming",
        "lg",
        "new"
      ]
    }
  },
  {
    "id": "laptop_036",
    "text": "Alienware XPS 14 - Alienware\nGiá: 35,051,726 VND\nMô tả: Laptop ultrabook Alienware với hiệu năng cao cho sáng tạo.\nThông số kỹ thuật:\n- cpu: AMD Ryzen 7 7730U\n- ram: 16GB DDR4\n- storage: 512GB SSD\n- gpu: Intel Iris Xe\n- display: 15.6 inch 2K IPS\n- battery: 63Wh\n- weight: 2.3kg\n- os: Windows 11 Home\nFeatures: Bluetooth 5.0, Webcam HD, Bàn phím có đèn nền, Thunderbolt, HDMI\nPros: Thiết kế đẹp, Hiệu năng tốt, Bàn phím thoải mái, Tản nhiệt tốt\nCons: Giá cao, Hơi nặng, Ít cổng kết nối\nUse_Cases: Streaming, Business\nĐánh giá: 4.5/5 từ 166 người dùng",
    "metadata": {
      "type": "product",
      "category": "laptop",
      "subcategory": "ultrabook",
      "brand": "Alienware",
      "name": "Alienware XPS 14",
      "price": 35051726,
      "rating": 4.5,
      "in_stock": true,
      "id": "laptop_036",
      "currency": "VND",
      "features": [
        "Bluetooth 5.0",
        "Webcam HD",
        "Bàn phím có đèn nền",
        "Thunderbolt",
        "HDMI"
      ],
      "pros": [
        "Thiết kế đẹp",
        "Hiệu năng tốt",
        "Bàn phím thoải mái",
        "Tản nhiệt tốt"
      ],
      "cons": [
        "Giá cao",
        "Hơi nặng",
        "Ít cổng kết nối"
      ],
      "use_cases": [
        "Streaming",
        "Business"
      ],
      "review_count": 166,
      "warranty": "24 tháng",
      "tags": [
        "ultrabook",
        "alienware",
        "new"
      ]
    }
  },
  {
    "id": "laptop_037",
    "text": "Acer Inspiron 17 - Acer\nGiá: 10,586,129 VND\nMô tả: Laptop budget Acer với hiệu năng cao cho học tập.\nThông số kỹ thuật:\n- cpu: Intel Core i5-1235U\n- ram: 4GB DDR4\n- storage: 512GB SSD\n- gpu: Intel UHD Graphics\n- display: 14 inch FHD IPS\n- battery: 76Wh\n- weight: 2.5kg\n- os: Windows 11 Home\nFeatures: Bàn phím có đèn nền, HDMI, Loa stereo, Webcam HD, USB-C, Vân tay\nPros: Bàn phím thoải mái, Nâng cấp dễ, Màn hình chất lượng, Giá hợp lý\nCons: Webcam kém, Giá cao, Pin yếu, Loa không hay\nUse_Cases: Gaming, Lập trình\nĐánh giá: 4.5/5 từ 450 người dùng",
    "metadata": {
      "type": "product",
      "category": "laptop",
      "subcategory": "budget",
      "brand": "Acer",
      "name": "Acer Inspiron 17",
      "price": 10586129,
      "rating": 4.5,
      "in_stock": true,
      "id": "laptop_037",
      "currency": "VND",
      "features": [
        "Bàn phím có đèn nền",
        "HDMI",
        "Loa stereo",
        "Webcam HD",
        "USB-C",
        "Vân tay"
      ],
      "pros": [
        "Bàn phím thoải mái",
        "Nâng cấp dễ",
        "Màn hình chất lượng",
        "Giá hợp lý"
      ],
      "cons": [
        "Webcam kém",
        "Giá cao",
        "Pin yếu",
        "Loa không hay"
      ],
      "use_cases": [
        "Gaming",
        "Lập trình"
      ],
      "review_count": 450,
      "warranty": "12 tháng",
      "tags": [
        "budget",
        "acer",
        "recommended"
      ]
    }
  },
  {
    "id": "laptop_038",
    "text": "Alienware Swift 14 - Alienware\nGiá: 22,982,556 VND\nMô tả: Laptop ultrabook Alienware với hiệu năng ổn định cho sáng tạo.\nThông số kỹ thuật:\n- cpu: Intel Core i5-1340P\n- ram: 16GB DDR4\n- storage: 256GB SSD\n- gpu: Intel Iris Xe\n- display: 17.3 inch 2K IPS\n- battery: 68Wh\n- weight: 2.7kg\n- os: Windows 11 Pro\nFeatures: Vân tay, Bluetooth 5.0, Loa stereo, Webcam HD, Sạc nhanh, Thunderbolt\nPros: Giá hợp lý, Nâng cấp dễ, Pin trâu, Màn hình chất lượng, Thiết kế đẹp\nCons: Nóng máy, Pin yếu, Giá cao\nUse_Cases: Học tập, Video editing\nĐánh giá: 3.8/5 từ 254 người dùng",
    "metadata": {
      "type": "product",
      "category": "laptop",
      "subcategory": "ultrabook",
      "brand": "Alienware",
      "name": "Alienware Swift 14",
      "price": 22982556,
      "rating": 3.8,
      "in_stock": true,
      "id": "laptop_038",
      "currency": "VND",
      "features": [
        "Vân tay",
        "Bluetooth 5.0",
        "Loa stereo",
        "Webcam HD",
        "Sạc nhanh",
        "Thunderbolt"
      ],
      "pros": [
        "Giá hợp lý",
        "Nâng cấp dễ",
        "Pin trâu",
        "Màn hình chất lượng",
        "Thiết kế đẹp"
      ],
      "cons": [
        "Nóng máy",
        "Pin yếu",
        "Giá cao"
      ],
      "use_cases": [
        "Học tập",
        "Video editing"
      ],
      "review_count": 254,
      "warranty": "36 tháng",
      "tags": [
        "ultrabook",
        "alienware",
        "new"
      ]
    }
  },
  {
    "id": "laptop_039",
    "text": "Alienware IdeaPad 17 - Alienware\nGiá: 18,910,735 VND\nMô tả: Laptop budget Alienware với hiệu năng ổn định cho gaming.\nThông số kỹ thuật:\n- cpu: AMD Ryzen 3 7320U\n- ram: 8GB DDR4\n- storage: 512GB NVMe\n- gpu: Intel UHD Graphics\n- display: 17.3 inch 2K VA\n- battery: 79Wh\n- weight: 2.5kg\n- os: Windows 11 Pro\nFeatures: Loa stereo, Thunderbolt, Wi-Fi 6, Bluetooth 5.0\nPros: Tản nhiệt tốt, Nâng cấp dễ, Thiết kế đẹp\nCons: Pin yếu, Webcam kém, Màn hình tối\nUse_Cases: Business, Streaming, Học tập\nĐánh giá: 3.7/5 từ 199 người dùng",
    "metadata": {
      "type": "product",
      "category": "laptop",
      "subcategory": "budget",
      "brand": "Alienware",
      "name": "Alienware IdeaPad 17",
      "price": 18910735,
      "rating": 3.7,
      "in_stock": true,
      "id": "laptop_039",
      "currency": "VND",
      "features": [
        "Loa stereo",
        "Thunderbolt",
        "Wi-Fi 6",
        "Bluetooth 5.0"
      ],
      "pros": [
        "Tản nhiệt tốt",
        "Nâng cấp dễ",
        "Thiết kế đẹp"
      ],
      "cons": [
        "Pin yếu",
        "Webcam kém",
        "Màn hình tối"
      ],
      "use_cases": [
        "Business",
        "Streaming",
        "Học tập"
      ],
      "review_count": 199,
      "warranty": "24 tháng",
      "tags": [
        "budget",
        "alienware",
        "bestseller"
      ]
    }
  },
  {
    "id": "laptop_040",
    "text": "Samsung ExpertBook 15 - Samsung\nGiá: 25,682,165 VND\nMô tả: Laptop business Samsung với hiệu năng cao cho sáng tạo.\nThông số kỹ thuật:\n- cpu: Intel Core i5-1335U\n- ram: 16GB DDR4\n- storage: 512GB SSD\n- gpu: AMD Radeon Graphics\n- display: 14 inch 4K OLED\n- battery: 58Wh\n- weight: 2.0kg\n- os: Ubuntu\nFeatures: Vân tay, Sạc nhanh, Bluetooth 5.0, Webcam HD, USB-C\nPros: Giá hợp lý, Nâng cấp dễ, Thiết kế đẹp\nCons: Ít cổng kết nối, Pin yếu, Nóng máy\nUse_Cases: Học tập, Video editing, Văn phòng\nĐánh giá: 4.0/5 từ 213 người dùng",
    "metadata": {
      "type": "product",
      "category": "laptop",
      "subcategory": "business",
      "brand": "Samsung",
      "name": "Samsung ExpertBook 15",
      "price": 25682165,
      "rating": 4.0,
      "in_stock": true,
      "id": "laptop_040",
      "currency": "VND",
      "features": [
        "Vân tay",
        "Sạc nhanh",
        "Bluetooth 5.0",
        "Webcam HD",
        "USB-C"
      ],
      "pros": [
        "Giá hợp lý",
        "Nâng cấp dễ",
        "Thiết kế đẹp"
      ],
      "cons": [
        "Ít cổng kết nối",
        "Pin yếu",
        "Nóng máy"
      ],
      "use_cases": [
        "Học tập",
        "Video editing",
        "Văn phòng"
      ],
      "review_count": 213,
      "warranty": "36 tháng",
      "tags": [
        "business",
        "samsung",
        "bestseller"
      ]
    }
  },
  {
    "id": "laptop_041",
    "text": "HP ProBook 17 - HP\nGiá: 28,281,352 VND\nMô tả: Laptop business HP với hiệu năng ổn định cho sáng tạo.\nThông số kỹ thuật:\n- cpu: AMD Ryzen 5 PRO 7530U\n- ram: 8GB DDR4\n- storage: 256GB SSD\n- gpu: Intel Iris Xe\n- display: 16 inch FHD VA\n- battery: 78Wh\n- weight: 2.6kg\n- os: Ubuntu\nFeatures: Sạc nhanh, USB-C, Webcam HD\nPros: Thiết kế đẹp, Giá hợp lý, Hiệu năng tốt, Tản nhiệt tốt, Pin trâu\nCons: Pin yếu, Nóng máy, Giá cao\nUse_Cases: Thiết kế, Gaming\nĐánh giá: 4.3/5 từ 420 người dùng",
    "metadata": {
      "type": "product",
      "category": "laptop",
      "subcategory": "business",
      "brand": "HP",
      "name": "HP ProBook 17",
      "price": 28281352,
      "rating": 4.3,
      "in_stock": true,
      "id": "laptop_041",
      "currency": "VND",
      "features": [
        "Sạc nhanh",
        "USB-C",
        "Webcam HD"
      ],
      "pros": [
        "Thiết kế đẹp",
        "Giá hợp lý",
        "Hiệu năng tốt",
        "Tản nhiệt tốt",
        "Pin trâu"
      ],
      "cons": [
        "Pin yếu",
        "Nóng máy",
        "Giá cao"
      ],
      "use_cases": [
        "Thiết kế",
        "Gaming"
      ],
      "review_count": 420,
      "warranty": "36 tháng",
      "tags": [
        "business",
        "hp",
        "popular"
      ]
    }
  },
  {
    "id": "laptop_042",
    "text": "Samsung TUF 14 - Samsung\nGiá: 27,008,158 VND\nMô tả: Laptop gaming Samsung với hiệu năng mạnh mẽ cho gaming.\nThông số kỹ thuật:\n- cpu: Intel Core i7-13700H\n- ram: 16GB DDR4\n- storage: 256GB SSD\n- gpu: RTX 4080 12GB\n- display: 15.6 inch FHD OLED\n- battery: 78Wh\n- weight: 2.7kg\n- os: Windows 11 Pro\nFeatures: Loa stereo, USB-C, HDMI\nPros: Bàn phím thoải mái, Nâng cấp dễ, Màn hình chất lượng, Hiệu năng tốt, Thiết kế đẹp\nCons: Hơi nặng, Nóng máy, Pin yếu, Loa không hay\nUse_Cases: Video editing, Học tập, Văn phòng\nĐánh giá: 4.3/5 từ 197 người dùng",
    "metadata": {
      "type": "product",
      "category": "laptop",
      "subcategory": "gaming",
      "brand": "Samsung",
      "name": "Samsung TUF 14",
      "price": 27008158,
      "rating": 4.3,
      "in_stock": true,
      "id": "laptop_042",
      "currency": "VND",
      "features": [
        "Loa stereo",
        "USB-C",
        "HDMI"
      ],
      "pros": [
        "Bàn phím thoải mái",
        "Nâng cấp dễ",
        "Màn hình chất lượng",
        "Hiệu năng tốt",
        "Thiết kế đẹp"
      ],
      "cons": [
        "Hơi nặng",
        "Nóng máy",
        "Pin yếu",
        "Loa không hay"
      ],
      "use_cases": [
        "Video editing",
        "Học tập",
        "Văn phòng"
      ],
      "review_count": 197,
      "warranty": "36 tháng",
      "tags": [
        "gaming",
        "samsung",
        "recommended"
      ]
    }
  },
  {
    "id": "laptop_043",
    "text": "MSI XPS 14 - MSI\nGiá: 22,702,391 VND\nMô tả: Laptop ultrabook MSI với hiệu năng ổn định cho học tập.\nThông số kỹ thuật:\n- cpu: Intel Core i7-1360P\n- ram: 16GB DDR4\n- storage: 1TB SSD\n- gpu: Intel Iris Xe\n- display: 17.3 inch 2K IPS\n- battery: 70Wh\n- weight: 1.9kg\n- os: Ubuntu\nFeatures: Loa stereo, Bàn phím có đèn nền, USB-C\nPros: Bàn phím thoải mái, Tản nhiệt tốt, Hiệu năng tốt, Màn hình chất lượng\nCons: Loa không hay, Webcam kém, Hơi nặng, Màn hình tối\nUse_Cases: Business, Văn phòng\nĐánh giá: 4.1/5 từ 321 người dùng",
    "metadata": {
      "type": "product",
      "category": "laptop",
      "subcategory": "ultrabook",
      "brand": "MSI",
      "name": "MSI XPS 14",
      "price": 22702391,
      "rating": 4.1,
      "in_stock": false,
      "id": "laptop_043",
      "currency": "VND",
      "features": [
        "Loa stereo",
        "Bàn phím có đèn nền",
        "USB-C"
      ],
      "pros": [
        "Bàn phím thoải mái",
        "Tản nhiệt tốt",
        "Hiệu năng tốt",
        "Màn hình chất lượng"
      ],
      "cons": [
        "Loa không hay",
        "Webcam kém",
        "Hơi nặng",
        "Màn hình tối"
      ],
      "use_cases": [
        "Business",
        "Văn phòng"
      ],
      "review_count": 321,
      "warranty": "12 tháng",
      "tags": [
        "ultrabook",
        "msi",
        "new"
      ]
    }
  },
  {
    "id": "laptop_044",
    "text": "HP Pavilion 17 - HP\nGiá: 9,420,890 VND\nMô tả: Laptop budget HP với hiệu năng mạnh mẽ cho công việc.\nThông số kỹ thuật:\n- cpu: Intel Core i3-1215U\n- ram: 8GB DDR4\n- storage: 512GB NVMe\n- gpu: Intel UHD Graphics\n- display: 17.3 inch 2K IPS\n- battery: 76Wh\n- weight: 1.7kg\n- os: Ubuntu\nFeatures: Sạc nhanh, Bluetooth 5.0, Wi-Fi 6, HDMI\nPros: Tản nhiệt tốt, Giá hợp lý, Màn hình chất lượng, Nâng cấp dễ\nCons: Loa không hay, Nóng máy, Ít cổng kết nối, Pin yếu\nUse_Cases: Business, Thiết kế, Lập trình, Gaming\nĐánh giá: 4.2/5 từ 358 người dùng",
    "metadata": {
      "type": "product",
      "category": "laptop",
      "subcategory": "budget",
      "brand": "HP",
      "name": "HP Pavilion 17",
      "price": 9420890,
      "rating": 4.2,
      "in_stock": false,
      "id": "laptop_044",
      "currency": "VND",
      "features": [
        "Sạc nhanh",
        "Bluetooth 5.0",
        "Wi-Fi 6",
        "HDMI"
      ],
      "pros": [
        "Tản nhiệt tốt",
        "Giá hợp lý",
        "Màn hình chất lượng",
        "Nâng cấp dễ"
      ],
      "cons": [
        "Loa không hay",
        "Nóng máy",
        "Ít cổng kết nối",
        "Pin yếu"
      ],
      "use_cases": [
        "Business",
        "Thiết kế",
        "Lập trình",
        "Gaming"
      ],
      "review_count": 358,
      "warranty": "12 tháng",
      "tags": [
        "budget",
        "hp",
        "bestseller"
      ]
    }
  },
  {
    "id": "laptop_045",
    "text": "Lenovo ZenBook 15 - Lenovo\nGiá: 22,922,934 VND\nMô tả: Laptop ultrabook Lenovo với hiệu năng cao cho gaming.\nThông số kỹ thuật:\n- cpu: AMD Ryzen 5 7530U\n- ram: 16GB DDR4\n- storage: 512GB SSD\n- gpu: Intel UHD Graphics\n- display: 14 inch 4K IPS\n- battery: 74Wh\n- weight: 2.1kg\n- os: Ubuntu\nFeatures: HDMI, Sạc nhanh, Bluetooth 5.0\nPros: Tản nhiệt tốt, Nâng cấp dễ, Giá hợp lý, Pin trâu\nCons: Ít cổng kết nối, Giá cao\nUse_Cases: Video editing, Lập trình, Văn phòng\nĐánh giá: 4.4/5 từ 178 người dùng",
    "metadata": {
      "type": "product",
      "category": "laptop",
      "subcategory": "ultrabook",
      "brand": "Lenovo",
      "name": "Lenovo ZenBook 15",
      "price": 22922934,
      "rating": 4.4,
      "in_stock": true,
      "id": "laptop_045",
      "currency": "VND",
      "features": [
        "HDMI",
        "Sạc nhanh",
        "Bluetooth 5.0"
      ],
      "pros": [
        "Tản nhiệt tốt",
        "Nâng cấp dễ",
        "Giá hợp lý",
        "Pin trâu"
      ],
      "cons": [
        "Ít cổng kết nối",
        "Giá cao"
      ],
      "use_cases": [
        "Video editing",
        "Lập trình",
        "Văn phòng"
      ],
      "review_count": 178,
      "warranty": "12 tháng",
      "tags": [
        "ultrabook",
        "lenovo",
        "popular"
      ]
    }
  },
  {
    "id": "laptop_046",
    "text": "Razer Aspire 14 - Razer\nGiá: 11,120,666 VND\nMô tả: Laptop budget Razer với hiệu năng ổn định cho sáng tạo.\nThông số kỹ thuật:\n- cpu: Intel Core i3-1215U\n- ram: 8GB LPDDR4\n- storage: 1TB SSD\n- gpu: AMD Radeon Graphics\n- display: 17.3 inch 4K VA\n- battery: 65Wh\n- weight: 2.1kg\n- os: Windows 11 Pro\nFeatures: Bluetooth 5.0, Vân tay, Sạc nhanh, USB-C, Thunderbolt\nPros: Màn hình chất lượng, Thiết kế đẹp, Giá hợp lý, Bàn phím thoải mái, Nâng cấp dễ\nCons: Webcam kém, Nóng máy\nUse_Cases: Thiết kế, Streaming, Gaming, Lập trình\nĐánh giá: 4.5/5 từ 446 người dùng",
    "metadata": {
      "type": "product",
      "category": "laptop",
      "subcategory": "budget",
      "brand": "Razer",
      "name": "Razer Aspire 14",
      "price": 11120666,
      "rating": 4.5,
      "in_stock": false,
      "id": "laptop_046",
      "currency": "VND",
      "features": [
        "Bluetooth 5.0",
        "Vân tay",
        "Sạc nhanh",
        "USB-C",
        "Thunderbolt"
      ],
      "pros": [
        "Màn hình chất lượng",
        "Thiết kế đẹp",
        "Giá hợp lý",
        "Bàn phím thoải mái",
        "Nâng cấp dễ"
      ],
      "cons": [
        "Webcam kém",
        "Nóng máy"
      ],
      "use_cases": [
        "Thiết kế",
        "Streaming",
        "Gaming",
        "Lập trình"
      ],
      "review_count": 446,
      "warranty": "36 tháng",
      "tags": [
        "budget",
        "razer",
        "popular"
      ]
    }
  },
  {
    "id": "laptop_047",
    "text": "Dell ExpertBook 14 - Dell\nGiá: 37,962,010 VND\nMô tả: Laptop business Dell với hiệu năng cao cho công việc.\nThông số kỹ thuật:\n- cpu: Intel Core i5-1335U\n- ram: 8GB DDR4\n- storage: 256GB SSD\n- gpu: AMD Radeon Graphics\n- display: 15.6 inch 2K IPS\n- battery: 78Wh\n- weight: 1.7kg\n- os: Windows 11 Pro\nFeatures: HDMI, Sạc nhanh, USB-C, Webcam HD\nPros: Thiết kế đẹp, Hiệu năng tốt, Tản nhiệt tốt, Màn hình chất lượng, Bàn phím thoải mái\nCons: Webcam kém, Màn hình tối\nUse_Cases: Thiết kế, Streaming\nĐánh giá: 4.3/5 từ 59 người dùng",
    "metadata": {
      "type": "product",
      "category": "laptop",
      "subcategory": "business",
      "brand": "Dell",
      "name": "Dell ExpertBook 14",
      "price": 37962010,
      "rating": 4.3,
      "in_stock": true,
      "id": "laptop_047",
      "currency": "VND",
      "features": [
        "HDMI",
        "Sạc nhanh",
        "USB-C",
        "Webcam HD"
      ],
      "pros": [
        "Thiết kế đẹp",
        "Hiệu năng tốt",
        "Tản nhiệt tốt",
        "Màn hình chất lượng",
        "Bàn phím thoải mái"
      ],
      "cons": [
        "Webcam kém",
        "Màn hình tối"
      ],
      "use_cases": [
        "Thiết kế",
        "Streaming"
      ],
      "review_count": 59,
      "warranty": "24 tháng",
      "tags": [
        "business",
        "dell",
        "recommended"
      ]
    }
  },
  {
    "id": "laptop_048",
    "text": "Alienware Gram 17 - Alienware\nGiá: 38,433,645 VND\nMô tả: Laptop ultrabook Alienware với hiệu năng mạnh mẽ cho công việc.\nThông số kỹ thuật:\n- cpu: Intel Core i5-1340P\n- ram: 16GB DDR4\n- storage: 512GB NVMe\n- gpu: Intel Iris Xe\n- display: 15.6 inch FHD OLED\n- battery: 82Wh\n- weight: 2.8kg\n- os: Windows 11 Pro\nFeatures: HDMI, Sạc nhanh, Thunderbolt\nPros: Màn hình chất lượng, Giá hợp lý, Thiết kế đẹp, Tản nhiệt tốt\nCons: Ít cổng kết nối, Webcam kém, Pin yếu, Loa không hay\nUse_Cases: Streaming, Business\nĐánh giá: 4.2/5 từ 384 người dùng",
    "metadata": {
      "type": "product",
      "category": "laptop",
      "subcategory": "ultrabook",
      "brand": "Alienware",
      "name": "Alienware Gram 17",
      "price": 38433645,
      "rating": 4.2,
      "in_stock": true,
      "id": "laptop_048",
      "currency": "VND",
      "features": [
        "HDMI",
        "Sạc nhanh",
        "Thunderbolt"
      ],
      "pros": [
        "Màn hình chất lượng",
        "Giá hợp lý",
        "Thiết kế đẹp",
        "Tản nhiệt tốt"
      ],
      "cons": [
        "Ít cổng kết nối",
        "Webcam kém",
        "Pin yếu",
        "Loa không hay"
      ],
      "use_cases": [
        "Streaming",
        "Business"
      ],
      "review_count": 384,
      "warranty": "24 tháng",
      "tags": [
        "ultrabook",
        "alienware",
        "recommended"
      ]
    }
  },
  {
    "id": "laptop_049",
    "text": "Dell IdeaPad 15 - Dell\nGiá: 18,572,927 VND\nMô tả: Laptop budget Dell với hiệu năng ổn định cho học tập.\nThông số kỹ thuật:\n- cpu: AMD Ryzen 5 5500U\n- ram: 8GB LPDDR4\n- storage: 512GB NVMe\n- gpu: AMD Radeon Graphics\n- display: 16 inch 2K VA\n- battery: 52Wh\n- weight: 1.2kg\n- os: Windows 11 Pro\nFeatures: Wi-Fi 6, Loa stereo, HDMI, Thunderbolt, Bàn phím có đèn nền\nPros: Thiết kế đẹp, Tản nhiệt tốt, Giá hợp lý\nCons: Nóng máy, Pin yếu\nUse_Cases: Văn phòng, Video editing, Streaming\nĐánh giá: 4.2/5 từ 18 người dùng",
    "metadata": {
      "type": "product",
      "category": "laptop",
      "subcategory": "budget",
      "brand": "Dell",
      "name": "Dell IdeaPad 15",
      "price": 18572927,
      "rating": 4.2,
      "in_stock": true,
      "id": "laptop_049",
      "currency": "VND",
      "features": [
        "Wi-Fi 6",
        "Loa stereo",
        "HDMI",
        "Thunderbolt",
        "Bàn phím có đèn nền"
      ],
      "pros": [
        "Thiết kế đẹp",
        "Tản nhiệt tốt",
        "Giá hợp lý"
      ],
      "cons": [
        "Nóng máy",
        "Pin yếu"
      ],
      "use_cases": [
        "Văn phòng",
        "Video editing",
        "Streaming"
      ],
      "review_count": 18,
      "warranty": "36 tháng",
      "tags": [
        "budget",
        "dell",
        "recommended"
      ]
    }
  },
  {
    "id": "laptop_050",
    "text": "Dell Swift 17 - Dell\nGiá: 30,313,545 VND\nMô tả: Laptop ultrabook Dell với hiệu năng cao cho gaming.\nThông số kỹ thuật:\n- cpu: AMD Ryzen 5 7530U\n- ram: 8GB LPDDR5\n- storage: 256GB SSD\n- gpu: AMD Radeon Graphics\n- display: 15.6 inch 2K IPS\n- battery: 50Wh\n- weight: 2.4kg\n- os: Windows 11 Pro\nFeatures: Bàn phím có đèn nền, Webcam HD, USB-C, Wi-Fi 6, Vân tay, Loa stereo\nPros: Thiết kế đẹp, Màn hình chất lượng, Pin trâu, Tản nhiệt tốt, Nâng cấp dễ\nCons: Hơi nặng, Pin yếu\nUse_Cases: Video editing, Streaming, Business\nĐánh giá: 4.5/5 từ 162 người dùng",
    "metadata": {
      "type": "product",
      "category": "laptop",
      "subcategory": "ultrabook",
      "brand": "Dell",
      "name": "Dell Swift 17",
      "price": 30313545,
      "rating": 4.5,
      "in_stock": true,
      "id": "laptop_050",
      "currency": "VND",
      "features": [
        "Bàn phím có đèn nền",
        "Webcam HD",
        "USB-C",
        "Wi-Fi 6",
        "Vân tay",
        "Loa stereo"
      ],
      "pros": [
        "Thiết kế đẹp",
        "Màn hình chất lượng",
        "Pin trâu",
        "Tản nhiệt tốt",
        "Nâng cấp dễ"
      ],
      "cons": [
        "Hơi nặng",
        "Pin yếu"
      ],
      "use_cases": [
        "Video editing",
        "Streaming",
        "Business"
      ],
      "review_count": 162,
      "warranty": "12 tháng",
      "tags": [
        "ultrabook",
        "dell",
        "popular"
      ]
    }
  },
  {
    "id": "phone_001",
    "text": "iPhone 15 Pro Max - Apple\nGiá: 34,990,000 VND\nMô tả: iPhone cao cấp nhất của Apple với chip A17 Pro 3nm đầu tiên, camera 48MP với zoom 5x, và khung titan nhẹ nhưng cực kỳ bền. Action Button mới cho phép tùy chỉnh các tác vụ nhanh.\nThông số kỹ thuật:\n- cpu: Apple A17 Pro (3nm)\n- ram: 8GB\n- storage: 256GB\n- display: 6.7 inch Super Retina XDR OLED, 2796x1290, 120Hz ProMotion\n- camera_main: 48MP wide (f/1.78) + 12MP ultra wide (f/2.2) + 12MP telephoto 5x (f/2.8)\n- camera_front: 12MP TrueDepth (f/1.9)\n- battery: 4422mAh, 29W wired, 15W MagSafe wireless\n- weight: 221g\n- os: iOS 17\n- connectivity: 5G, Wi-Fi 6E, Bluetooth 5.3, NFC\n- water_resistance: IP68\nFeatures: Dynamic Island, Always-On Display, Action Button có thể tùy chỉnh, Khung Titanium Grade 5, USB-C với USB 3.0, ProRAW và ProRes video, Spatial Video cho Vision Pro, Crash Detection, Satellite SOS\nPros: Hiệu năng đỉnh cao với A17 Pro, Camera zoom 5x ấn tượng, Màn hình ProMotion 120Hz mượt mà, Khung titan nhẹ và bền, Thời lượng pin tốt, Hệ sinh thái Apple hoàn hảo\nCons: Giá rất cao, Nặng và to, Sạc chậm so với Android flagship, Không có Touch ID\nUse_Cases: Photography chuyên nghiệp, Video content creation, Gaming mobile cao cấp, Business professionals, Apple ecosystem users\nĐánh giá: 4.8/5 từ 892 người dùng",
    "metadata": {
      "type": "product",
      "category": "smartphone",
      "subcategory": "flagship",
      "brand": "Apple",
      "name": "iPhone 15 Pro Max",
      "price": 34990000,
      "rating": 4.8,
      "in_stock": true,
      "id": "phone_001",
      "currency": "VND",
      "features": [
        "Dynamic Island",
        "Always-On Display",
        "Action Button có thể tùy chỉnh",
        "Khung Titanium Grade 5",
        "USB-C với USB 3.0",
        "ProRAW và ProRes video",
        "Spatial Video cho Vision Pro",
        "Crash Detection",
        "Satellite SOS"
      ],
      "pros": [
        "Hiệu năng đỉnh cao với A17 Pro",
        "Camera zoom 5x ấn tượng",
        "Màn hình ProMotion 120Hz mượt mà",
        "Khung titan nhẹ và bền",
        "Thời lượng pin tốt",
        "Hệ sinh thái Apple hoàn hảo"
      ],
      "cons": [
        "Giá rất cao",
        "Nặng và to",
        "Sạc chậm so với Android flagship",
        "Không có Touch ID"
      ],
      "use_cases": [
        "Photography chuyên nghiệp",
        "Video content creation",
        "Gaming mobile cao cấp",
        "Business professionals",
        "Apple ecosystem users"
      ],
      "review_count": 892,
      "warranty": "12 tháng",
      "colors": [
        "Natural Titanium",
        "Blue Titanium",
        "White Titanium",
        "Black Titanium"
      ],
      "tags": [
        "flagship",
        "pro-camera",
        "5g",
        "titanium",
        "a17-pro"
      ]
    }
  },
  {
    "id": "phone_002",
    "text": "Samsung Galaxy S24 Ultra - Samsung\nGiá: 33,990,000 VND\nMô tả: Flagship Android mạnh nhất với S Pen tích hợp, camera 200MP với AI processing, và màn hình 2K 120Hz sáng nhất. Galaxy AI mang đến các tính năng AI thông minh cho cuộc sống hàng ngày.\nThông số kỹ thuật:\n- cpu: Snapdragon 8 Gen 3 for Galaxy\n- ram: 12GB LPDDR5X\n- storage: 256GB UFS 4.0\n- display: 6.8 inch Dynamic AMOLED 2X, 3120x1440, 120Hz, 2600 nits peak\n- camera_main: 200MP wide (f/1.7) + 12MP ultra wide (f/2.2) + 50MP telephoto 5x (f/3.4) + 10MP telephoto 3x (f/2.4)\n- camera_front: 12MP (f/2.2)\n- battery: 5000mAh, 45W wired, 15W wireless\n- weight: 232g\n- os: Android 14 with One UI 6.1\n- connectivity: 5G, Wi-Fi 7, Bluetooth 5.3, NFC\n- water_resistance: IP68\nFeatures: S Pen tích hợp với Air Actions, Galaxy AI (Circle to Search, Live Translate), Corning Gorilla Armor (giảm 75% phản chiếu), Camera Nightography, 8K video recording, Samsung DeX, Ultrasonic fingerprint sensor, Reverse wireless charging\nPros: Màn hình sáng và sắc nét nhất, Camera 200MP chi tiết cao, S Pen đa năng, Pin lớn 5000mAh, Galaxy AI features hữu ích, Hiệu năng Snapdragon 8 Gen 3 mạnh mẽ\nCons: Giá cao, Thiết kế vuông vức, nặng, Nhiệt độ cao khi sử dụng nặng, Bloatware khá nhiều\nUse_Cases: Power users, Note-taking với S Pen, Photography và videography, Multitasking nặng, Samsung DeX desktop mode\nĐánh giá: 4.7/5 từ 756 người dùng",
    "metadata": {
      "type": "product",
      "category": "smartphone",
      "subcategory": "flagship",
      "brand": "Samsung",
      "name": "Samsung Galaxy S24 Ultra",
      "price": 33990000,
      "rating": 4.7,
      "in_stock": true,
      "id": "phone_002",
      "currency": "VND",
      "features": [
        "S Pen tích hợp với Air Actions",
        "Galaxy AI (Circle to Search, Live Translate)",
        "Corning Gorilla Armor (giảm 75% phản chiếu)",
        "Camera Nightography",
        "8K video recording",
        "Samsung DeX",
        "Ultrasonic fingerprint sensor",
        "Reverse wireless charging"
      ],
      "pros": [
        "Màn hình sáng và sắc nét nhất",
        "Camera 200MP chi tiết cao",
        "S Pen đa năng",
        "Pin lớn 5000mAh",
        "Galaxy AI features hữu ích",
        "Hiệu năng Snapdragon 8 Gen 3 mạnh mẽ"
      ],
      "cons": [
        "Giá cao",
        "Thiết kế vuông vức, nặng",
        "Nhiệt độ cao khi sử dụng nặng",
        "Bloatware khá nhiều"
      ],
      "use_cases": [
        "Power users",
        "Note-taking với S Pen",
        "Photography và videography",
        "Multitasking nặng",
        "Samsung DeX desktop mode"
      ],
      "review_count": 756,
      "warranty": "12 tháng",
      "colors": [
        "Titanium Black",
        "Titanium Gray",
        "Titanium Violet",
        "Titanium Yellow"
      ],
      "tags": [
        "flagship",
        "s-pen",
        "200mp-camera",
        "galaxy-ai",
        "snapdragon-8-gen3"
      ]
    }
  },
  {
    "id": "phone_003",
    "text": "Xiaomi 14 - Xiaomi\nGiá: 22,990,000 VND\nMô tả: Flagship compact với camera Leica thế hệ mới, Snapdragon 8 Gen 3, và thiết kế premium. Kích thước nhỏ gọn 6.36 inch nhưng không compromise về hiệu năng.\nThông số kỹ thuật:\n- cpu: Snapdragon 8 Gen 3\n- ram: 12GB LPDDR5X\n- storage: 256GB UFS 4.0\n- display: 6.36 inch LTPO OLED, 2670x1200, 120Hz, 3000 nits peak\n- camera_main: 50MP wide Leica (f/1.6) + 50MP ultra wide (f/2.2) + 50MP telephoto 3.2x (f/2.0)\n- camera_front: 32MP (f/2.0)\n- battery: 4610mAh, 90W wired, 50W wireless\n- weight: 193g\n- os: Android 14 with HyperOS\n- connectivity: 5G, Wi-Fi 7, Bluetooth 5.4, NFC\n- water_resistance: IP68\nFeatures: Leica Summilux lens, Leica Authentic Look và Vibrant Look, HyperOS mới thay thế MIUI, Xiaomi Surge battery management, Dolby Vision display, 90W HyperCharge, In-display fingerprint sensor\nPros: Kích thước nhỏ gọn, dễ cầm, Camera Leica chất lượng cao, Sạc siêu nhanh 90W, Màn hình sáng 3000 nits, Giá tốt cho flagship, HyperOS mượt mà hơn MIUI\nCons: Pin nhỏ hơn đối thủ, Không có jack 3.5mm, Software ads (có thể tắt), Hỗ trợ sau bán hàng còn hạn chế\nUse_Cases: Người thích điện thoại nhỏ gọn, Photography enthusiasts, Daily driver mạnh mẽ, Gaming casual, Value flagship seekers\nĐánh giá: 4.5/5 từ 423 người dùng",
    "metadata": {
      "type": "product",
      "category": "smartphone",
      "subcategory": "flagship",
      "brand": "Xiaomi",
      "name": "Xiaomi 14",
      "price": 22990000,
      "rating": 4.5,
      "in_stock": true,
      "id": "phone_003",
      "currency": "VND",
      "features": [
        "Leica Summilux lens",
        "Leica Authentic Look và Vibrant Look",
        "HyperOS mới thay thế MIUI",
        "Xiaomi Surge battery management",
        "Dolby Vision display",
        "90W HyperCharge",
        "In-display fingerprint sensor"
      ],
      "pros": [
        "Kích thước nhỏ gọn, dễ cầm",
        "Camera Leica chất lượng cao",
        "Sạc siêu nhanh 90W",
        "Màn hình sáng 3000 nits",
        "Giá tốt cho flagship",
        "HyperOS mượt mà hơn MIUI"
      ],
      "cons": [
        "Pin nhỏ hơn đối thủ",
        "Không có jack 3.5mm",
        "Software ads (có thể tắt)",
        "Hỗ trợ sau bán hàng còn hạn chế"
      ],
      "use_cases": [
        "Người thích điện thoại nhỏ gọn",
        "Photography enthusiasts",
        "Daily driver mạnh mẽ",
        "Gaming casual",
        "Value flagship seekers"
      ],
      "review_count": 423,
      "warranty": "12 tháng",
      "colors": [
        "Black",
        "White",
        "Jade Green"
      ],
      "tags": [
        "compact-flagship",
        "leica-camera",
        "90w-charging",
        "hyperos",
        "value"
      ]
    }
  },
  {
    "id": "phone_004",
    "text": "Google Pixel 8 Pro - Google\nGiá: 27,990,000 VND\nMô tả: Smartphone AI-first của Google với Tensor G3, camera computational photography tốt nhất và 7 năm cập nhật. Magic Eraser, Best Take và các tính năng AI độc quyền.\nThông số kỹ thuật:\n- cpu: Google Tensor G3\n- ram: 12GB LPDDR5X\n- storage: 128GB UFS 3.1\n- display: 6.7 inch LTPO OLED, 2992x1344, 120Hz, 2400 nits peak\n- camera_main: 50MP wide (f/1.68) + 48MP ultra wide (f/1.95) + 48MP telephoto 5x (f/2.8)\n- camera_front: 10.5MP (f/2.2)\n- battery: 5050mAh, 30W wired, 23W wireless\n- weight: 213g\n- os: Android 14\n- connectivity: 5G, Wi-Fi 7, Bluetooth 5.3, NFC, UWB\n- water_resistance: IP68\nFeatures: Magic Eraser và Magic Editor, Best Take (chọn khuôn mặt tốt nhất), Audio Magic Eraser, Live Translate, Temperature sensor, 7 năm cập nhật OS, Titan M2 security chip, Face Unblur\nPros: Camera AI tốt nhất Android, 7 năm support dài nhất, Tính năng AI độc quyền, Android thuần, không bloat, Màn hình sáng và mượt\nCons: Tensor G3 không mạnh bằng Snapdragon, Sạc chậm 30W, Thiết kế camera bar gây tranh cãi, Giá cao cho cấu hình\nUse_Cases: Photography với AI, Android purists, Long-term phone users, Google ecosystem, AI features lovers\nĐánh giá: 4.4/5 từ 345 người dùng",
    "metadata": {
      "type": "product",
      "category": "smartphone",
      "subcategory": "flagship",
      "brand": "Google",
      "name": "Google Pixel 8 Pro",
      "price": 27990000,
      "rating": 4.4,
      "in_stock": true,
      "id": "phone_004",
      "currency": "VND",
      "features": [
        "Magic Eraser và Magic Editor",
        "Best Take (chọn khuôn mặt tốt nhất)",
        "Audio Magic Eraser",
        "Live Translate",
        "Temperature sensor",
        "7 năm cập nhật OS",
        "Titan M2 security chip",
        "Face Unblur"
      ],
      "pros": [
        "Camera AI tốt nhất Android",
        "7 năm support dài nhất",
        "Tính năng AI độc quyền",
        "Android thuần, không bloat",
        "Màn hình sáng và mượt"
      ],
      "cons": [
        "Tensor G3 không mạnh bằng Snapdragon",
        "Sạc chậm 30W",
        "Thiết kế camera bar gây tranh cãi",
        "Giá cao cho cấu hình"
      ],
      "use_cases": [
        "Photography với AI",
        "Android purists",
        "Long-term phone users",
        "Google ecosystem",
        "AI features lovers"
      ],
      "review_count": 345,
      "warranty": "12 tháng",
      "colors": [
        "Obsidian",
        "Porcelain",
        "Bay"
      ],
      "tags": [
        "ai-first",
        "pixel-camera",
        "7-year-updates",
        "tensor-g3",
        "pure-android"
      ]
    }
  },
  {
    "id": "phone_005",
    "text": "OnePlus 12 - OnePlus\nGiá: 23,990,000 VND\nMô tả: Flagship killer với Snapdragon 8 Gen 3, sạc nhanh 100W, và camera Hasselblad thế hệ 4. Màn hình 2K 120Hz với độ sáng 4500 nits kỷ lục.\nThông số kỹ thuật:\n- cpu: Snapdragon 8 Gen 3\n- ram: 16GB LPDDR5X\n- storage: 256GB UFS 4.0\n- display: 6.82 inch LTPO AMOLED, 3168x1440, 120Hz, 4500 nits peak\n- camera_main: 50MP wide Sony LYT-808 (f/1.6) + 48MP ultra wide (f/2.2) + 64MP telephoto 3x (f/2.6)\n- camera_front: 32MP (f/2.4)\n- battery: 5400mAh, 100W wired, 50W wireless\n- weight: 220g\n- os: Android 14 with OxygenOS 14\n- connectivity: 5G, Wi-Fi 7, Bluetooth 5.4, NFC\n- water_resistance: IP65\nFeatures: Hasselblad Camera for Mobile, 100W SuperVOOC charging, Alert Slider 3 chế độ, Aqua Touch (dùng khi tay ướt), Dolby Vision và Dolby Atmos, Bionic Vibration Motor, RAM-Vita compression\nPros: Màn hình sáng nhất thị trường, Sạc 100W siêu nhanh, RAM 16GB khủng, Camera Hasselblad ấn tượng, OxygenOS mượt mà, Alert Slider tiện lợi\nCons: Chỉ IP65, không IP68, Không có sạc không dây ở một số thị trường, Camera tele chỉ 3x, Hơi nặng và to\nUse_Cases: Power users, Gaming enthusiasts, Multimedia consumption, Fast charging lovers, OnePlus fans\nĐánh giá: 4.6/5 từ 512 người dùng",
    "metadata": {
      "type": "product",
      "category": "smartphone",
      "subcategory": "flagship",
      "brand": "OnePlus",
      "name": "OnePlus 12",
      "price": 23990000,
      "rating": 4.6,
      "in_stock": true,
      "id": "phone_005",
      "currency": "VND",
      "features": [
        "Hasselblad Camera for Mobile",
        "100W SuperVOOC charging",
        "Alert Slider 3 chế độ",
        "Aqua Touch (dùng khi tay ướt)",
        "Dolby Vision và Dolby Atmos",
        "Bionic Vibration Motor",
        "RAM-Vita compression"
      ],
      "pros": [
        "Màn hình sáng nhất thị trường",
        "Sạc 100W siêu nhanh",
        "RAM 16GB khủng",
        "Camera Hasselblad ấn tượng",
        "OxygenOS mượt mà",
        "Alert Slider tiện lợi"
      ],
      "cons": [
        "Chỉ IP65, không IP68",
        "Không có sạc không dây ở một số thị trường",
        "Camera tele chỉ 3x",
        "Hơi nặng và to"
      ],
      "use_cases": [
        "Power users",
        "Gaming enthusiasts",
        "Multimedia consumption",
        "Fast charging lovers",
        "OnePlus fans"
      ],
      "review_count": 512,
      "warranty": "12 tháng",
      "colors": [
        "Silky Black",
        "Emerald",
        "Iron Gray"
      ],
      "tags": [
        "flagship-killer",
        "100w-charging",
        "hasselblad",
        "16gb-ram",
        "bright-display"
      ]
    }
  },
  {
    "id": "phone_006",
    "text": "iPhone 15 - Apple\nGiá: 22,990,000 VND\nMô tả: iPhone tiêu chuẩn với Dynamic Island, camera 48MP mới, và cuối cùng đã có USB-C. Chip A16 Bionic từ Pro series năm ngoái vẫn cực kỳ mạnh mẽ.\nThông số kỹ thuật:\n- cpu: Apple A16 Bionic\n- ram: 6GB\n- storage: 128GB\n- display: 6.1 inch Super Retina XDR OLED, 2556x1179, 60Hz\n- camera_main: 48MP wide (f/1.6) + 12MP ultra wide (f/2.4)\n- camera_front: 12MP TrueDepth (f/1.9)\n- battery: 3349mAh, 20W wired, 15W MagSafe wireless\n- weight: 171g\n- os: iOS 17\n- connectivity: 5G, Wi-Fi 6, Bluetooth 5.3, NFC\n- water_resistance: IP68\nFeatures: Dynamic Island, USB-C port, Camera 48MP với 2x zoom, Photographic Styles, Cinematic mode 4K, Action mode, Crash Detection, Ceramic Shield front\nPros: Dynamic Island từ Pro series, Camera 48MP nâng cấp lớn, USB-C tiện lợi, Nhẹ và cân bằng tốt, Chip A16 vẫn rất mạnh, Hệ sinh thái Apple\nCons: Màn hình vẫn 60Hz, Sạc chậm 20W, Không có Always-On Display, Telephoto lens chỉ ở Pro\nUse_Cases: Everyday users, First-time iPhone buyers, Upgrade từ iPhone cũ, Social media, Apple ecosystem\nĐánh giá: 4.6/5 từ 678 người dùng",
    "metadata": {
      "type": "product",
      "category": "smartphone",
      "subcategory": "premium",
      "brand": "Apple",
      "name": "iPhone 15",
      "price": 22990000,
      "rating": 4.6,
      "in_stock": true,
      "id": "phone_006",
      "currency": "VND",
      "features": [
        "Dynamic Island",
        "USB-C port",
        "Camera 48MP với 2x zoom",
        "Photographic Styles",
        "Cinematic mode 4K",
        "Action mode",
        "Crash Detection",
        "Ceramic Shield front"
      ],
      "pros": [
        "Dynamic Island từ Pro series",
        "Camera 48MP nâng cấp lớn",
        "USB-C tiện lợi",
        "Nhẹ và cân bằng tốt",
        "Chip A16 vẫn rất mạnh",
        "Hệ sinh thái Apple"
      ],
      "cons": [
        "Màn hình vẫn 60Hz",
        "Sạc chậm 20W",
        "Không có Always-On Display",
        "Telephoto lens chỉ ở Pro"
      ],
      "use_cases": [
        "Everyday users",
        "First-time iPhone buyers",
        "Upgrade từ iPhone cũ",
        "Social media",
        "Apple ecosystem"
      ],
      "review_count": 678,
      "warranty": "12 tháng",
      "colors": [
        "Black",
        "Blue",
        "Green",
        "Yellow",
        "Pink"
      ],
      "tags": [
        "mainstream",
        "dynamic-island",
        "48mp",
        "usb-c",
        "a16-bionic"
      ]
    }
  },
  {
    "id": "phone_007",
    "text": "Samsung Galaxy A54 5G - Samsung\nGiá: 10,990,000 VND\nMô tả: Mid-range tốt nhất của Samsung với thiết kế flagship, camera 50MP OIS, màn hình 120Hz và 4 năm cập nhật OS. IP67 hiếm có trong phân khúc.\nThông số kỹ thuật:\n- cpu: Exynos 1380\n- ram: 8GB\n- storage: 256GB + microSD\n- display: 6.4 inch Super AMOLED, 2340x1080, 120Hz, 1000 nits\n- camera_main: 50MP wide OIS (f/1.8) + 12MP ultra wide (f/2.2) + 5MP macro (f/2.4)\n- camera_front: 32MP (f/2.2)\n- battery: 5000mAh, 25W wired\n- weight: 202g\n- os: Android 13 with One UI 5.1\n- connectivity: 5G, Wi-Fi 6, Bluetooth 5.3, NFC\n- water_resistance: IP67\nFeatures: Thiết kế Awesome Identity, Camera OIS chống rung, 4 năm OS updates, 5 năm security updates, Samsung Knox, Gorilla Glass 5, Stereo speakers\nPros: Thiết kế đẹp như flagship, Màn hình AMOLED 120Hz, Camera OIS trong tầm giá, Pin 5000mAh lâu, IP67 chống nước, Support lâu dài\nCons: Exynos 1380 không mạnh, Sạc 25W chậm, Không có sạc không dây, Bezels hơi dày\nUse_Cases: Daily driver ổn định, Social media và photography, Long-term usage, Samsung fans với ngân sách vừa, Cần điện thoại chống nước\nĐánh giá: 4.3/5 từ 892 người dùng",
    "metadata": {
      "type": "product",
      "category": "smartphone",
      "subcategory": "midrange",
      "brand": "Samsung",
      "name": "Samsung Galaxy A54 5G",
      "price": 10990000,
      "rating": 4.3,
      "in_stock": true,
      "id": "phone_007",
      "currency": "VND",
      "features": [
        "Thiết kế Awesome Identity",
        "Camera OIS chống rung",
        "4 năm OS updates",
        "5 năm security updates",
        "Samsung Knox",
        "Gorilla Glass 5",
        "Stereo speakers"
      ],
      "pros": [
        "Thiết kế đẹp như flagship",
        "Màn hình AMOLED 120Hz",
        "Camera OIS trong tầm giá",
        "Pin 5000mAh lâu",
        "IP67 chống nước",
        "Support lâu dài"
      ],
      "cons": [
        "Exynos 1380 không mạnh",
        "Sạc 25W chậm",
        "Không có sạc không dây",
        "Bezels hơi dày"
      ],
      "use_cases": [
        "Daily driver ổn định",
        "Social media và photography",
        "Long-term usage",
        "Samsung fans với ngân sách vừa",
        "Cần điện thoại chống nước"
      ],
      "review_count": 892,
      "warranty": "12 tháng",
      "colors": [
        "Awesome Graphite",
        "Awesome Violet",
        "Awesome Lime",
        "Awesome White"
      ],
      "tags": [
        "midrange",
        "ip67",
        "120hz",
        "long-support",
        "value"
      ]
    }
  },
  {
    "id": "phone_008",
    "text": "Xiaomi Redmi Note 13 Pro+ 5G - Xiaomi\nGiá: 11,990,000 VND\nMô tả: Mid-range với camera 200MP đầu tiên, sạc nhanh 120W, và màn hình cong 1.5K. Thiết kế premium với khung viền phẳng và mặt lưng da thuần chay.\nThông số kỹ thuật:\n- cpu: MediaTek Dimensity 7200 Ultra\n- ram: 12GB LPDDR5\n- storage: 256GB UFS 3.1\n- display: 6.67 inch AMOLED, 2712x1220, 120Hz, 1800 nits peak\n- camera_main: 200MP wide OIS (f/1.65) + 8MP ultra wide (f/2.2) + 2MP macro (f/2.4)\n- camera_front: 16MP (f/2.4)\n- battery: 5000mAh, 120W wired\n- weight: 204.5g\n- os: Android 13 with MIUI 14\n- connectivity: 5G, Wi-Fi 6, Bluetooth 5.3, NFC, IR blaster\n- water_resistance: IP54\nFeatures: Camera 200MP Samsung HP3, 120W HyperCharge (19 phút full), Màn hình cong 1.5K, Dolby Vision và Dolby Atmos, IR blaster, In-display fingerprint, Gorilla Glass Victus\nPros: Camera 200MP ấn tượng, Sạc 120W siêu nhanh, RAM 12GB mượt mà, Thiết kế premium, Màn hình sáng và sắc nét, Giá tốt cho cấu hình\nCons: MediaTek chip không mạnh bằng Snapdragon, MIUI ads nhiều, Chỉ IP54, Camera phụ yếu\nUse_Cases: Photography với budget, Fast charging needs, Media consumption, Gaming tầm trung, Xiaomi ecosystem\nĐánh giá: 4.4/5 từ 567 người dùng",
    "metadata": {
      "type": "product",
      "category": "smartphone",
      "subcategory": "midrange",
      "brand": "Xiaomi",
      "name": "Xiaomi Redmi Note 13 Pro+ 5G",
      "price": 11990000,
      "rating": 4.4,
      "in_stock": true,
      "id": "phone_008",
      "currency": "VND",
      "features": [
        "Camera 200MP Samsung HP3",
        "120W HyperCharge (19 phút full)",
        "Màn hình cong 1.5K",
        "Dolby Vision và Dolby Atmos",
        "IR blaster",
        "In-display fingerprint",
        "Gorilla Glass Victus"
      ],
      "pros": [
        "Camera 200MP ấn tượng",
        "Sạc 120W siêu nhanh",
        "RAM 12GB mượt mà",
        "Thiết kế premium",
        "Màn hình sáng và sắc nét",
        "Giá tốt cho cấu hình"
      ],
      "cons": [
        "MediaTek chip không mạnh bằng Snapdragon",
        "MIUI ads nhiều",
        "Chỉ IP54",
        "Camera phụ yếu"
      ],
      "use_cases": [
        "Photography với budget",
        "Fast charging needs",
        "Media consumption",
        "Gaming tầm trung",
        "Xiaomi ecosystem"
      ],
      "review_count": 567,
      "warranty": "18 tháng",
      "colors": [
        "Midnight Black",
        "Moonlight White",
        "Aurora Purple"
      ],
      "tags": [
        "200mp-camera",
        "120w-charging",
        "midrange",
        "value",
        "amoled"
      ]
    }
  },
  {
    "id": "phone_009",
    "text": "OPPO Reno11 5G - OPPO\nGiá: 10,990,000 VND\nMô tả: Portrait Expert với camera telephoto portrait 32MP hiếm có trong phân khúc. Thiết kế mỏng nhẹ 7.99mm, sạc nhanh 67W và màn hình cong 120Hz.\nThông số kỹ thuật:\n- cpu: MediaTek Dimensity 7050\n- ram: 8GB + 8GB RAM mở rộng\n- storage: 256GB\n- display: 6.7 inch AMOLED, 2412x1080, 120Hz, 950 nits peak\n- camera_main: 50MP wide (f/1.8) + 32MP telephoto portrait 2x (f/2.0) + 8MP ultra wide (f/2.2)\n- camera_front: 32MP (f/2.4)\n- battery: 4800mAh, 67W wired\n- weight: 182g\n- os: Android 14 with ColorOS 14\n- connectivity: 5G, Wi-Fi 6, Bluetooth 5.2, NFC\n- water_resistance: IP65\nFeatures: Portrait camera chuyên dụng, Thiết kế siêu mỏng 7.99mm, 67W SuperVOOC, RAM mở rộng +8GB, Ultra-Volume Mode, Smart Image Matting 2.0, LinkBoost signal enhancement\nPros: Camera portrait xuất sắc, Thiết kế mỏng nhẹ đẹp, Sạc nhanh 67W, ColorOS 14 nhiều tính năng, IP65 chống nước\nCons: Chip Dimensity 7050 yếu, Pin nhỏ 4800mAh, Không có OIS, Giá hơi cao cho cấu hình\nUse_Cases: Portrait photography, Fashion và lifestyle, Social media content, Người thích điện thoại mỏng nhẹ, OPPO fans\nĐánh giá: 4.2/5 từ 345 người dùng",
    "metadata": {
      "type": "product",
      "category": "smartphone",
      "subcategory": "midrange",
      "brand": "OPPO",
      "name": "OPPO Reno11 5G",
      "price": 10990000,
      "rating": 4.2,
      "in_stock": true,
      "id": "phone_009",
      "currency": "VND",
      "features": [
        "Portrait camera chuyên dụng",
        "Thiết kế siêu mỏng 7.99mm",
        "67W SuperVOOC",
        "RAM mở rộng +8GB",
        "Ultra-Volume Mode",
        "Smart Image Matting 2.0",
        "LinkBoost signal enhancement"
      ],
      "pros": [
        "Camera portrait xuất sắc",
        "Thiết kế mỏng nhẹ đẹp",
        "Sạc nhanh 67W",
        "ColorOS 14 nhiều tính năng",
        "IP65 chống nước"
      ],
      "cons": [
        "Chip Dimensity 7050 yếu",
        "Pin nhỏ 4800mAh",
        "Không có OIS",
        "Giá hơi cao cho cấu hình"
      ],
      "use_cases": [
        "Portrait photography",
        "Fashion và lifestyle",
        "Social media content",
        "Người thích điện thoại mỏng nhẹ",
        "OPPO fans"
      ],
      "review_count": 345,
      "warranty": "12 tháng",
      "colors": [
        "Wave Green",
        "Rock Grey"
      ],
      "tags": [
        "portrait-expert",
        "slim-design",
        "67w-charging",
        "midrange",
        "stylish"
      ]
    }
  },
  {
    "id": "phone_010",
    "text": "Realme 11 Pro+ - Realme\nGiá: 11,990,000 VND\nMô tả: Mid-range với camera 200MP OIS và sạc nhanh 100W. Thiết kế da thuần chay cao cấp, màn hình cong 120Hz. Giá trị tốt nhất phân khúc.\nThông số kỹ thuật:\n- cpu: MediaTek Dimensity 7050\n- ram: 12GB\n- storage: 256GB\n- display: 6.7 inch AMOLED, 2412x1080, 120Hz, 950 nits\n- camera_main: 200MP wide OIS (f/1.69) + 8MP ultra wide (f/2.2) + 2MP macro (f/2.4)\n- camera_front: 32MP (f/2.5)\n- battery: 5000mAh, 100W wired\n- weight: 183g\n- os: Android 13 with Realme UI 4.0\n- connectivity: 5G, Wi-Fi 6, Bluetooth 5.2, NFC\n- water_resistance: No official rating\nFeatures: Camera 200MP Samsung HP3 với OIS, 100W SuperVOOC charging, Thiết kế Lychee Vegan Leather, Màn hình cong 61 độ, Dolby Atmos dual speakers, In-display fingerprint, Hi-Res Audio certification\nPros: Camera 200MP với OIS, Sạc 100W cực nhanh, RAM 12GB mượt mà, Thiết kế da độc đáo, Giá cạnh tranh\nCons: Chip Dimensity không mạnh, Không chống nước, Software còn nhiều ads, Camera góc siêu rộng yếu\nUse_Cases: Budget photography, Fast charging lovers, Daily multitasking, Value seekers, First 5G phone\nĐánh giá: 4.3/5 từ 423 người dùng",
    "metadata": {
      "type": "product",
      "category": "smartphone",
      "subcategory": "midrange",
      "brand": "Realme",
      "name": "Realme 11 Pro+",
      "price": 11990000,
      "rating": 4.3,
      "in_stock": true,
      "id": "phone_010",
      "currency": "VND",
      "features": [
        "Camera 200MP Samsung HP3 với OIS",
        "100W SuperVOOC charging",
        "Thiết kế Lychee Vegan Leather",
        "Màn hình cong 61 độ",
        "Dolby Atmos dual speakers",
        "In-display fingerprint",
        "Hi-Res Audio certification"
      ],
      "pros": [
        "Camera 200MP với OIS",
        "Sạc 100W cực nhanh",
        "RAM 12GB mượt mà",
        "Thiết kế da độc đáo",
        "Giá cạnh tranh"
      ],
      "cons": [
        "Chip Dimensity không mạnh",
        "Không chống nước",
        "Software còn nhiều ads",
        "Camera góc siêu rộng yếu"
      ],
      "use_cases": [
        "Budget photography",
        "Fast charging lovers",
        "Daily multitasking",
        "Value seekers",
        "First 5G phone"
      ],
      "review_count": 423,
      "warranty": "12 tháng",
      "colors": [
        "Sunrise Beige",
        "Oasis Green",
        "Astral Black"
      ],
      "tags": [
        "200mp-ois",
        "100w-charging",
        "value-king",
        "vegan-leather",
        "midrange"
      ]
    }
  },
  {
    "id": "phone_011",
    "text": "Xiaomi Mi 13 - Xiaomi\nGiá: 28,834,462 VND\nMô tả: Smartphone flagship Xiaomi với camera 48MP và hiệu năng tốt.\nThông số kỹ thuật:\n- cpu: Snapdragon 8 Gen 3\n- ram: 8GB\n- storage: 128GB\n- display: 6.0 inch AMOLED 90Hz\n- camera_main: 108MP main + 12MP ultra wide\n- camera_front: 16MP selfie\n- battery: 4314mAh\n- os: iOS 17\n- connectivity: 5G, Wi-Fi 6, Bluetooth 5.3\nFeatures: Night mode, Stereo speakers, Water resistant, Face unlock, Always-on display\nPros: Loa hay, Sạc nhanh, Màn hình đẹp, Giá hợp lý, Pin trâu\nCons: Camera kém ánh sáng, Nặng, Pin yếu, Nóng máy\nUse_Cases: Photography, Chụp ảnh, Gaming mobile\nĐánh giá: 3.8/5 từ 20 người dùng",
    "metadata": {
      "type": "product",
      "category": "smartphone",
      "subcategory": "flagship",
      "brand": "Xiaomi",
      "name": "Xiaomi Mi 13",
      "price": 28834462,
      "rating": 3.8,
      "in_stock": false,
      "id": "phone_011",
      "currency": "VND",
      "features": [
        "Night mode",
        "Stereo speakers",
        "Water resistant",
        "Face unlock",
        "Always-on display"
      ],
      "pros": [
        "Loa hay",
        "Sạc nhanh",
        "Màn hình đẹp",
        "Giá hợp lý",
        "Pin trâu"
      ],
      "cons": [
        "Camera kém ánh sáng",
        "Nặng",
        "Pin yếu",
        "Nóng máy"
      ],
      "use_cases": [
        "Photography",
        "Chụp ảnh",
        "Gaming mobile"
      ],
      "review_count": 20,
      "warranty": "12 tháng",
      "tags": [
        "flagship",
        "xiaomi",
        "hot"
      ]
    }
  },
  {
    "id": "phone_012",
    "text": "Samsung Galaxy 10 - Samsung\nGiá: 22,943,311 VND\nMô tả: Smartphone flagship Samsung với camera 108MP và hiệu năng tốt.\nThông số kỹ thuật:\n- cpu: Exynos 2400\n- ram: 12GB\n- storage: 128GB\n- display: 6.1 inch Super AMOLED 60Hz\n- camera_main: 48MP main + 5MP ultra wide\n- camera_front: 16MP selfie\n- battery: 3815mAh\n- os: Android 13\n- connectivity: 5G, Wi-Fi 6, Bluetooth 5.3\nFeatures: Water resistant, Wireless charging, NFC, Fingerprint, Night mode\nPros: Camera chất lượng, Loa hay, Sạc nhanh\nCons: Loa đơn, Không sạc không dây, Nóng máy\nUse_Cases: Streaming, Video call, Photography\nĐánh giá: 4.7/5 từ 656 người dùng",
    "metadata": {
      "type": "product",
      "category": "smartphone",
      "subcategory": "flagship",
      "brand": "Samsung",
      "name": "Samsung Galaxy 10",
      "price": 22943311,
      "rating": 4.7,
      "in_stock": false,
      "id": "phone_012",
      "currency": "VND",
      "features": [
        "Water resistant",
        "Wireless charging",
        "NFC",
        "Fingerprint",
        "Night mode"
      ],
      "pros": [
        "Camera chất lượng",
        "Loa hay",
        "Sạc nhanh"
      ],
      "cons": [
        "Loa đơn",
        "Không sạc không dây",
        "Nóng máy"
      ],
      "use_cases": [
        "Streaming",
        "Video call",
        "Photography"
      ],
      "review_count": 656,
      "warranty": "24 tháng",
      "tags": [
        "flagship",
        "samsung",
        "new-arrival"
      ]
    }
  },
  {
    "id": "phone_013",
    "text": "Samsung iPhone 10 - Samsung\nGiá: 5,944,131 VND\nMô tả: Smartphone budget Samsung với camera 13MP và hiệu năng ổn định.\nThông số kỹ thuật:\n- cpu: Helio G99\n- ram: 6GB\n- storage: 64GB\n- display: 6.2 inch AMOLED 90Hz\n- camera_main: 48MP main + 5MP ultra wide\n- camera_front: 12MP selfie\n- battery: 3390mAh\n- os: Android 13\n- connectivity: 5G, Wi-Fi 6, Bluetooth 5.3\nFeatures: Face unlock, Stereo speakers, Water resistant, Always-on display, Fast charging, Wireless charging\nPros: Giá hợp lý, Camera chất lượng, Thiết kế premium, Màn hình đẹp\nCons: Pin yếu, Không sạc không dây, Nặng, Giá cao\nUse_Cases: Công việc, Streaming, Chụp ảnh, Gaming mobile, Giải trí\nĐánh giá: 4.4/5 từ 712 người dùng",
    "metadata": {
      "type": "product",
      "category": "smartphone",
      "subcategory": "budget",
      "brand": "Samsung",
      "name": "Samsung iPhone 10",
      "price": 5944131,
      "rating": 4.4,
      "in_stock": true,
      "id": "phone_013",
      "currency": "VND",
      "features": [
        "Face unlock",
        "Stereo speakers",
        "Water resistant",
        "Always-on display",
        "Fast charging",
        "Wireless charging"
      ],
      "pros": [
        "Giá hợp lý",
        "Camera chất lượng",
        "Thiết kế premium",
        "Màn hình đẹp"
      ],
      "cons": [
        "Pin yếu",
        "Không sạc không dây",
        "Nặng",
        "Giá cao"
      ],
      "use_cases": [
        "Công việc",
        "Streaming",
        "Chụp ảnh",
        "Gaming mobile",
        "Giải trí"
      ],
      "review_count": 712,
      "warranty": "24 tháng",
      "tags": [
        "budget",
        "samsung",
        "trending"
      ]
    }
  },
  {
    "id": "phone_014",
    "text": "Samsung Pixel 13 - Samsung\nGiá: 19,153,894 VND\nMô tả: Smartphone midrange Samsung với camera 64MP và hiệu năng tốt.\nThông số kỹ thuật:\n- cpu: Snapdragon 7 Gen 3\n- ram: 8GB\n- storage: 256GB\n- display: 6.3 inch Super AMOLED 120Hz\n- camera_main: 108MP main + 5MP ultra wide\n- camera_front: 8MP selfie\n- battery: 4560mAh\n- os: Android 13\n- connectivity: 5G, Wi-Fi 6, Bluetooth 5.3\nFeatures: Dual SIM, Water resistant, Night mode, Face unlock, Wireless charging\nPros: Loa hay, Sạc nhanh, Giá hợp lý\nCons: Không có jack 3.5mm, Loa đơn, Pin yếu\nUse_Cases: Video call, Streaming, Photography, Công việc, Giải trí\nĐánh giá: 4.4/5 từ 70 người dùng",
    "metadata": {
      "type": "product",
      "category": "smartphone",
      "subcategory": "midrange",
      "brand": "Samsung",
      "name": "Samsung Pixel 13",
      "price": 19153894,
      "rating": 4.4,
      "in_stock": true,
      "id": "phone_014",
      "currency": "VND",
      "features": [
        "Dual SIM",
        "Water resistant",
        "Night mode",
        "Face unlock",
        "Wireless charging"
      ],
      "pros": [
        "Loa hay",
        "Sạc nhanh",
        "Giá hợp lý"
      ],
      "cons": [
        "Không có jack 3.5mm",
        "Loa đơn",
        "Pin yếu"
      ],
      "use_cases": [
        "Video call",
        "Streaming",
        "Photography",
        "Công việc",
        "Giải trí"
      ],
      "review_count": 70,
      "warranty": "12 tháng",
      "tags": [
        "midrange",
        "samsung",
        "hot"
      ]
    }
  },
  {
    "id": "phone_015",
    "text": "OnePlus OnePlus 13 - OnePlus\nGiá: 5,076,480 VND\nMô tả: Smartphone budget OnePlus với camera 13MP và hiệu năng cao.\nThông số kỹ thuật:\n- cpu: Helio G99\n- ram: 6GB\n- storage: 128GB\n- display: 6.6 inch AMOLED 90Hz\n- camera_main: 50MP main + 12MP ultra wide\n- camera_front: 12MP selfie\n- battery: 4264mAh\n- os: Android 13\n- connectivity: 5G, Wi-Fi 6, Bluetooth 5.3\nFeatures: Face unlock, Fast charging, Fingerprint, Wireless charging, Stereo speakers, Dual SIM, Water resistant\nPros: Pin trâu, Loa hay, Hiệu năng mượt, Sạc nhanh\nCons: Nặng, Không sạc không dây, Loa đơn\nUse_Cases: Mạng xã hội, Video call, Streaming, Photography, Gaming mobile\nĐánh giá: 3.9/5 từ 22 người dùng",
    "metadata": {
      "type": "product",
      "category": "smartphone",
      "subcategory": "budget",
      "brand": "OnePlus",
      "name": "OnePlus OnePlus 13",
      "price": 5076480,
      "rating": 3.9,
      "in_stock": false,
      "id": "phone_015",
      "currency": "VND",
      "features": [
        "Face unlock",
        "Fast charging",
        "Fingerprint",
        "Wireless charging",
        "Stereo speakers",
        "Dual SIM",
        "Water resistant"
      ],
      "pros": [
        "Pin trâu",
        "Loa hay",
        "Hiệu năng mượt",
        "Sạc nhanh"
      ],
      "cons": [
        "Nặng",
        "Không sạc không dây",
        "Loa đơn"
      ],
      "use_cases": [
        "Mạng xã hội",
        "Video call",
        "Streaming",
        "Photography",
        "Gaming mobile"
      ],
      "review_count": 22,
      "warranty": "18 tháng",
      "tags": [
        "budget",
        "oneplus",
        "trending"
      ]
    }
  },
  {
    "id": "phone_016",
    "text": "Samsung Mi 15 - Samsung\nGiá: 5,590,460 VND\nMô tả: Smartphone budget Samsung với camera 50MP và hiệu năng mạnh mẽ.\nThông số kỹ thuật:\n- cpu: Helio G99\n- ram: 4GB\n- storage: 256GB\n- display: 6.4 inch Super AMOLED 90Hz\n- camera_main: 8MP main + 5MP ultra wide\n- camera_front: 12MP selfie\n- battery: 3314mAh\n- os: Android 14\n- connectivity: 5G, Wi-Fi 6, Bluetooth 5.3\nFeatures: Fast charging, NFC, Face unlock, Stereo speakers, Always-on display\nPros: Hiệu năng mượt, Giá hợp lý, Camera chất lượng, Thiết kế premium, Sạc nhanh\nCons: Không có jack 3.5mm, Không sạc không dây, Pin yếu, Camera kém ánh sáng\nUse_Cases: Mạng xã hội, Video call, Photography, Gaming mobile, Công việc\nĐánh giá: 4.6/5 từ 431 người dùng",
    "metadata": {
      "type": "product",
      "category": "smartphone",
      "subcategory": "budget",
      "brand": "Samsung",
      "name": "Samsung Mi 15",
      "price": 5590460,
      "rating": 4.6,
      "in_stock": false,
      "id": "phone_016",
      "currency": "VND",
      "features": [
        "Fast charging",
        "NFC",
        "Face unlock",
        "Stereo speakers",
        "Always-on display"
      ],
      "pros": [
        "Hiệu năng mượt",
        "Giá hợp lý",
        "Camera chất lượng",
        "Thiết kế premium",
        "Sạc nhanh"
      ],
      "cons": [
        "Không có jack 3.5mm",
        "Không sạc không dây",
        "Pin yếu",
        "Camera kém ánh sáng"
      ],
      "use_cases": [
        "Mạng xã hội",
        "Video call",
        "Photography",
        "Gaming mobile",
        "Công việc"
      ],
      "review_count": 431,
      "warranty": "24 tháng",
      "tags": [
        "budget",
        "samsung",
        "new-arrival"
      ]
    }
  },
  {
    "id": "phone_017",
    "text": "Apple Mi 13 - Apple\nGiá: 12,626,436 VND\nMô tả: Smartphone midrange Apple với camera 64MP và hiệu năng cao.\nThông số kỹ thuật:\n- cpu: Snapdragon 7 Gen 3\n- ram: 12GB\n- storage: 64GB\n- display: 5.7 inch IPS 120Hz\n- camera_main: 50MP main + 5MP ultra wide\n- camera_front: 8MP selfie\n- battery: 3091mAh\n- os: Android 13\n- connectivity: 5G, Wi-Fi 6, Bluetooth 5.3\nFeatures: Always-on display, Dual SIM, Wireless charging, NFC, Water resistant\nPros: Pin trâu, Giá hợp lý, Màn hình đẹp, Thiết kế premium\nCons: Pin yếu, Giá cao, Nóng máy\nUse_Cases: Chụp ảnh, Streaming, Gaming mobile\nĐánh giá: 4.6/5 từ 415 người dùng",
    "metadata": {
      "type": "product",
      "category": "smartphone",
      "subcategory": "midrange",
      "brand": "Apple",
      "name": "Apple Mi 13",
      "price": 12626436,
      "rating": 4.6,
      "in_stock": true,
      "id": "phone_017",
      "currency": "VND",
      "features": [
        "Always-on display",
        "Dual SIM",
        "Wireless charging",
        "NFC",
        "Water resistant"
      ],
      "pros": [
        "Pin trâu",
        "Giá hợp lý",
        "Màn hình đẹp",
        "Thiết kế premium"
      ],
      "cons": [
        "Pin yếu",
        "Giá cao",
        "Nóng máy"
      ],
      "use_cases": [
        "Chụp ảnh",
        "Streaming",
        "Gaming mobile"
      ],
      "review_count": 415,
      "warranty": "24 tháng",
      "tags": [
        "midrange",
        "apple",
        "new-arrival"
      ]
    }
  },
  {
    "id": "phone_018",
    "text": "Huawei Find 10 - Huawei\nGiá: 3,943,934 VND\nMô tả: Smartphone budget Huawei với camera 8MP và hiệu năng ổn định.\nThông số kỹ thuật:\n- cpu: Dimensity 6020\n- ram: 4GB\n- storage: 128GB\n- display: 6.1 inch AMOLED 60Hz\n- camera_main: 8MP main + 12MP ultra wide\n- camera_front: 12MP selfie\n- battery: 4484mAh\n- os: iOS 17\n- connectivity: 5G, Wi-Fi 6, Bluetooth 5.3\nFeatures: Water resistant, Face unlock, Dual SIM, Always-on display, Wireless charging, NFC\nPros: Hiệu năng mượt, Camera chất lượng, Màn hình đẹp\nCons: Camera kém ánh sáng, Nặng, Nóng máy, Không có jack 3.5mm\nUse_Cases: Mạng xã hội, Công việc, Streaming\nĐánh giá: 4.5/5 từ 220 người dùng",
    "metadata": {
      "type": "product",
      "category": "smartphone",
      "subcategory": "budget",
      "brand": "Huawei",
      "name": "Huawei Find 10",
      "price": 3943934,
      "rating": 4.5,
      "in_stock": true,
      "id": "phone_018",
      "currency": "VND",
      "features": [
        "Water resistant",
        "Face unlock",
        "Dual SIM",
        "Always-on display",
        "Wireless charging",
        "NFC"
      ],
      "pros": [
        "Hiệu năng mượt",
        "Camera chất lượng",
        "Màn hình đẹp"
      ],
      "cons": [
        "Camera kém ánh sáng",
        "Nặng",
        "Nóng máy",
        "Không có jack 3.5mm"
      ],
      "use_cases": [
        "Mạng xã hội",
        "Công việc",
        "Streaming"
      ],
      "review_count": 220,
      "warranty": "12 tháng",
      "tags": [
        "budget",
        "huawei",
        "new-arrival"
      ]
    }
  },
  {
    "id": "phone_019",
    "text": "OnePlus Pixel 10 - OnePlus\nGiá: 38,958,947 VND\nMô tả: Smartphone flagship OnePlus với camera 108MP và hiệu năng tốt.\nThông số kỹ thuật:\n- cpu: Dimensity 9300\n- ram: 16GB\n- storage: 512GB\n- display: 5.9 inch Super AMOLED 60Hz\n- camera_main: 50MP main + 5MP ultra wide\n- camera_front: 8MP selfie\n- battery: 4198mAh\n- os: Android 13\n- connectivity: 5G, Wi-Fi 6, Bluetooth 5.3\nFeatures: Fast charging, Night mode, Fingerprint, NFC, Always-on display\nPros: Loa hay, Camera chất lượng, Màn hình đẹp, Thiết kế premium, Sạc nhanh\nCons: Camera kém ánh sáng, Pin yếu, Loa đơn\nUse_Cases: Giải trí, Video call, Streaming, Photography\nĐánh giá: 4.7/5 từ 348 người dùng",
    "metadata": {
      "type": "product",
      "category": "smartphone",
      "subcategory": "flagship",
      "brand": "OnePlus",
      "name": "OnePlus Pixel 10",
      "price": 38958947,
      "rating": 4.7,
      "in_stock": true,
      "id": "phone_019",
      "currency": "VND",
      "features": [
        "Fast charging",
        "Night mode",
        "Fingerprint",
        "NFC",
        "Always-on display"
      ],
      "pros": [
        "Loa hay",
        "Camera chất lượng",
        "Màn hình đẹp",
        "Thiết kế premium",
        "Sạc nhanh"
      ],
      "cons": [
        "Camera kém ánh sáng",
        "Pin yếu",
        "Loa đơn"
      ],
      "use_cases": [
        "Giải trí",
        "Video call",
        "Streaming",
        "Photography"
      ],
      "review_count": 348,
      "warranty": "18 tháng",
      "tags": [
        "flagship",
        "oneplus",
        "trending"
      ]
    }
  },
  {
    "id": "phone_020",
    "text": "Xiaomi OnePlus 15 - Xiaomi\nGiá: 19,882,971 VND\nMô tả: Smartphone midrange Xiaomi với camera 50MP và hiệu năng ổn định.\nThông số kỹ thuật:\n- cpu: A16 Bionic\n- ram: 8GB\n- storage: 128GB\n- display: 6.2 inch AMOLED 60Hz\n- camera_main: 50MP main + 5MP ultra wide\n- camera_front: 8MP selfie\n- battery: 4903mAh\n- os: Android 13\n- connectivity: 5G, Wi-Fi 6, Bluetooth 5.3\nFeatures: Stereo speakers, Wireless charging, Fingerprint, NFC, Dual SIM, Fast charging, Water resistant\nPros: Camera chất lượng, Màn hình đẹp, Giá hợp lý\nCons: Không sạc không dây, Giá cao, Loa đơn, Camera kém ánh sáng\nUse_Cases: Photography, Giải trí, Gaming mobile\nĐánh giá: 4.7/5 từ 235 người dùng",
    "metadata": {
      "type": "product",
      "category": "smartphone",
      "subcategory": "midrange",
      "brand": "Xiaomi",
      "name": "Xiaomi OnePlus 15",
      "price": 19882971,
      "rating": 4.7,
      "in_stock": true,
      "id": "phone_020",
      "currency": "VND",
      "features": [
        "Stereo speakers",
        "Wireless charging",
        "Fingerprint",
        "NFC",
        "Dual SIM",
        "Fast charging",
        "Water resistant"
      ],
      "pros": [
        "Camera chất lượng",
        "Màn hình đẹp",
        "Giá hợp lý"
      ],
      "cons": [
        "Không sạc không dây",
        "Giá cao",
        "Loa đơn",
        "Camera kém ánh sáng"
      ],
      "use_cases": [
        "Photography",
        "Giải trí",
        "Gaming mobile"
      ],
      "review_count": 235,
      "warranty": "24 tháng",
      "tags": [
        "midrange",
        "xiaomi",
        "trending"
      ]
    }
  },
  {
    "id": "phone_021",
    "text": "Google OnePlus 12 - Google\nGiá: 3,592,323 VND\nMô tả: Smartphone budget Google với camera 50MP và hiệu năng tốt.\nThông số kỹ thuật:\n- cpu: Unisoc Tiger T606\n- ram: 4GB\n- storage: 256GB\n- display: 5.6 inch AMOLED 60Hz\n- camera_main: 48MP main + 12MP ultra wide\n- camera_front: 12MP selfie\n- battery: 4538mAh\n- os: Android 13\n- connectivity: 5G, Wi-Fi 6, Bluetooth 5.3\nFeatures: Fingerprint, NFC, Night mode, Face unlock, Always-on display, Dual SIM, Stereo speakers\nPros: Camera chất lượng, Thiết kế premium, Pin trâu, Hiệu năng mượt\nCons: Không sạc không dây, Không có jack 3.5mm, Nóng máy, Pin yếu\nUse_Cases: Photography, Mạng xã hội, Chụp ảnh, Video call\nĐánh giá: 4.6/5 từ 336 người dùng",
    "metadata": {
      "type": "product",
      "category": "smartphone",
      "subcategory": "budget",
      "brand": "Google",
      "name": "Google OnePlus 12",
      "price": 3592323,
      "rating": 4.6,
      "in_stock": false,
      "id": "phone_021",
      "currency": "VND",
      "features": [
        "Fingerprint",
        "NFC",
        "Night mode",
        "Face unlock",
        "Always-on display",
        "Dual SIM",
        "Stereo speakers"
      ],
      "pros": [
        "Camera chất lượng",
        "Thiết kế premium",
        "Pin trâu",
        "Hiệu năng mượt"
      ],
      "cons": [
        "Không sạc không dây",
        "Không có jack 3.5mm",
        "Nóng máy",
        "Pin yếu"
      ],
      "use_cases": [
        "Photography",
        "Mạng xã hội",
        "Chụp ảnh",
        "Video call"
      ],
      "review_count": 336,
      "warranty": "18 tháng",
      "tags": [
        "budget",
        "google",
        "bestseller"
      ]
    }
  },
  {
    "id": "phone_022",
    "text": "OnePlus Galaxy 15 - OnePlus\nGiá: 9,161,272 VND\nMô tả: Smartphone midrange OnePlus với camera 108MP và hiệu năng tốt.\nThông số kỹ thuật:\n- cpu: Dimensity 8050\n- ram: 12GB\n- storage: 512GB\n- display: 6.6 inch Super AMOLED 90Hz\n- camera_main: 108MP main + 5MP ultra wide\n- camera_front: 12MP selfie\n- battery: 4919mAh\n- os: iOS 17\n- connectivity: 5G, Wi-Fi 6, Bluetooth 5.3\nFeatures: Always-on display, Wireless charging, NFC, Water resistant, Fast charging, Night mode\nPros: Thiết kế premium, Camera chất lượng, Màn hình đẹp\nCons: Camera kém ánh sáng, Pin yếu\nUse_Cases: Công việc, Giải trí, Mạng xã hội, Chụp ảnh\nĐánh giá: 4.0/5 từ 306 người dùng",
    "metadata": {
      "type": "product",
      "category": "smartphone",
      "subcategory": "midrange",
      "brand": "OnePlus",
      "name": "OnePlus Galaxy 15",
      "price": 9161272,
      "rating": 4.0,
      "in_stock": false,
      "id": "phone_022",
      "currency": "VND",
      "features": [
        "Always-on display",
        "Wireless charging",
        "NFC",
        "Water resistant",
        "Fast charging",
        "Night mode"
      ],
      "pros": [
        "Thiết kế premium",
        "Camera chất lượng",
        "Màn hình đẹp"
      ],
      "cons": [
        "Camera kém ánh sáng",
        "Pin yếu"
      ],
      "use_cases": [
        "Công việc",
        "Giải trí",
        "Mạng xã hội",
        "Chụp ảnh"
      ],
      "review_count": 306,
      "warranty": "18 tháng",
      "tags": [
        "midrange",
        "oneplus",
        "bestseller"
      ]
    }
  },
  {
    "id": "phone_023",
    "text": "OnePlus Mi 12 - OnePlus\nGiá: 22,800,123 VND\nMô tả: Smartphone flagship OnePlus với camera 50MP và hiệu năng tốt.\nThông số kỹ thuật:\n- cpu: Snapdragon 8 Gen 3\n- ram: 8GB\n- storage: 256GB\n- display: 6.6 inch Super AMOLED 90Hz\n- camera_main: 200MP main + 5MP ultra wide\n- camera_front: 16MP selfie\n- battery: 3171mAh\n- os: Android 14\n- connectivity: 5G, Wi-Fi 6, Bluetooth 5.3\nFeatures: Wireless charging, NFC, Face unlock, Always-on display, Night mode\nPros: Sạc nhanh, Giá hợp lý, Loa hay, Pin trâu\nCons: Nóng máy, Pin yếu, Loa đơn, Không có jack 3.5mm\nUse_Cases: Streaming, Công việc, Video call\nĐánh giá: 4.8/5 từ 634 người dùng",
    "metadata": {
      "type": "product",
      "category": "smartphone",
      "subcategory": "flagship",
      "brand": "OnePlus",
      "name": "OnePlus Mi 12",
      "price": 22800123,
      "rating": 4.8,
      "in_stock": false,
      "id": "phone_023",
      "currency": "VND",
      "features": [
        "Wireless charging",
        "NFC",
        "Face unlock",
        "Always-on display",
        "Night mode"
      ],
      "pros": [
        "Sạc nhanh",
        "Giá hợp lý",
        "Loa hay",
        "Pin trâu"
      ],
      "cons": [
        "Nóng máy",
        "Pin yếu",
        "Loa đơn",
        "Không có jack 3.5mm"
      ],
      "use_cases": [
        "Streaming",
        "Công việc",
        "Video call"
      ],
      "review_count": 634,
      "warranty": "18 tháng",
      "tags": [
        "flagship",
        "oneplus",
        "new-arrival"
      ]
    }
  },
  {
    "id": "phone_024",
    "text": "Huawei Galaxy 15 - Huawei\nGiá: 30,877,942 VND\nMô tả: Smartphone flagship Huawei với camera 108MP và hiệu năng mạnh mẽ.\nThông số kỹ thuật:\n- cpu: Exynos 2400\n- ram: 8GB\n- storage: 256GB\n- display: 6.2 inch IPS 120Hz\n- camera_main: 48MP main + 8MP ultra wide\n- camera_front: 32MP selfie\n- battery: 4910mAh\n- os: Android 14\n- connectivity: 5G, Wi-Fi 6, Bluetooth 5.3\nFeatures: Face unlock, Water resistant, Stereo speakers, Night mode, Wireless charging, NFC\nPros: Pin trâu, Camera chất lượng, Thiết kế premium\nCons: Camera kém ánh sáng, Giá cao\nUse_Cases: Giải trí, Mạng xã hội, Công việc, Photography, Chụp ảnh\nĐánh giá: 4.0/5 từ 358 người dùng",
    "metadata": {
      "type": "product",
      "category": "smartphone",
      "subcategory": "flagship",
      "brand": "Huawei",
      "name": "Huawei Galaxy 15",
      "price": 30877942,
      "rating": 4.0,
      "in_stock": true,
      "id": "phone_024",
      "currency": "VND",
      "features": [
        "Face unlock",
        "Water resistant",
        "Stereo speakers",
        "Night mode",
        "Wireless charging",
        "NFC"
      ],
      "pros": [
        "Pin trâu",
        "Camera chất lượng",
        "Thiết kế premium"
      ],
      "cons": [
        "Camera kém ánh sáng",
        "Giá cao"
      ],
      "use_cases": [
        "Giải trí",
        "Mạng xã hội",
        "Công việc",
        "Photography",
        "Chụp ảnh"
      ],
      "review_count": 358,
      "warranty": "18 tháng",
      "tags": [
        "flagship",
        "huawei",
        "new-arrival"
      ]
    }
  },
  {
    "id": "phone_025",
    "text": "Huawei iPhone 12 - Huawei\nGiá: 7,034,991 VND\nMô tả: Smartphone budget Huawei với camera 8MP và hiệu năng cao.\nThông số kỹ thuật:\n- cpu: Unisoc Tiger T606\n- ram: 3GB\n- storage: 64GB\n- display: 6.8 inch Super AMOLED 120Hz\n- camera_main: 8MP main + 8MP ultra wide\n- camera_front: 32MP selfie\n- battery: 3099mAh\n- os: iOS 17\n- connectivity: 5G, Wi-Fi 6, Bluetooth 5.3\nFeatures: Wireless charging, Fingerprint, NFC, Dual SIM, Stereo speakers, Fast charging, Night mode\nPros: Màn hình đẹp, Giá hợp lý, Sạc nhanh, Hiệu năng mượt, Pin trâu\nCons: Giá cao, Không có jack 3.5mm, Loa đơn\nUse_Cases: Photography, Giải trí, Chụp ảnh\nĐánh giá: 4.2/5 từ 718 người dùng",
    "metadata": {
      "type": "product",
      "category": "smartphone",
      "subcategory": "budget",
      "brand": "Huawei",
      "name": "Huawei iPhone 12",
      "price": 7034991,
      "rating": 4.2,
      "in_stock": true,
      "id": "phone_025",
      "currency": "VND",
      "features": [
        "Wireless charging",
        "Fingerprint",
        "NFC",
        "Dual SIM",
        "Stereo speakers",
        "Fast charging",
        "Night mode"
      ],
      "pros": [
        "Màn hình đẹp",
        "Giá hợp lý",
        "Sạc nhanh",
        "Hiệu năng mượt",
        "Pin trâu"
      ],
      "cons": [
        "Giá cao",
        "Không có jack 3.5mm",
        "Loa đơn"
      ],
      "use_cases": [
        "Photography",
        "Giải trí",
        "Chụp ảnh"
      ],
      "review_count": 718,
      "warranty": "12 tháng",
      "tags": [
        "budget",
        "huawei",
        "bestseller"
      ]
    }
  },
  {
    "id": "phone_026",
    "text": "Samsung Find 11 - Samsung\nGiá: 5,469,892 VND\nMô tả: Smartphone budget Samsung với camera 48MP và hiệu năng tốt.\nThông số kỹ thuật:\n- cpu: Snapdragon 4 Gen 2\n- ram: 6GB\n- storage: 256GB\n- display: 6.6 inch Super AMOLED 60Hz\n- camera_main: 48MP main + 12MP ultra wide\n- camera_front: 16MP selfie\n- battery: 4906mAh\n- os: iOS 17\n- connectivity: 5G, Wi-Fi 6, Bluetooth 5.3\nFeatures: Dual SIM, Wireless charging, Stereo speakers, Fingerprint\nPros: Giá hợp lý, Thiết kế premium, Camera chất lượng, Hiệu năng mượt, Pin trâu\nCons: Không có jack 3.5mm, Không sạc không dây, Giá cao, Loa đơn\nUse_Cases: Photography, Công việc, Mạng xã hội, Giải trí, Video call\nĐánh giá: 4.8/5 từ 613 người dùng",
    "metadata": {
      "type": "product",
      "category": "smartphone",
      "subcategory": "budget",
      "brand": "Samsung",
      "name": "Samsung Find 11",
      "price": 5469892,
      "rating": 4.8,
      "in_stock": true,
      "id": "phone_026",
      "currency": "VND",
      "features": [
        "Dual SIM",
        "Wireless charging",
        "Stereo speakers",
        "Fingerprint"
      ],
      "pros": [
        "Giá hợp lý",
        "Thiết kế premium",
        "Camera chất lượng",
        "Hiệu năng mượt",
        "Pin trâu"
      ],
      "cons": [
        "Không có jack 3.5mm",
        "Không sạc không dây",
        "Giá cao",
        "Loa đơn"
      ],
      "use_cases": [
        "Photography",
        "Công việc",
        "Mạng xã hội",
        "Giải trí",
        "Video call"
      ],
      "review_count": 613,
      "warranty": "24 tháng",
      "tags": [
        "budget",
        "samsung",
        "bestseller"
      ]
    }
  },
  {
    "id": "phone_027",
    "text": "Google Galaxy 13 - Google\nGiá: 20,888,844 VND\nMô tả: Smartphone flagship Google với camera 48MP và hiệu năng mạnh mẽ.\nThông số kỹ thuật:\n- cpu: A17 Pro\n- ram: 12GB\n- storage: 256GB\n- display: 5.6 inch AMOLED 90Hz\n- camera_main: 200MP main + 12MP ultra wide\n- camera_front: 12MP selfie\n- battery: 4223mAh\n- os: Android 13\n- connectivity: 5G, Wi-Fi 6, Bluetooth 5.3\nFeatures: Fast charging, Stereo speakers, Water resistant, Face unlock, NFC\nPros: Hiệu năng mượt, Loa hay, Sạc nhanh, Thiết kế premium, Camera chất lượng\nCons: Nặng, Pin yếu\nUse_Cases: Chụp ảnh, Giải trí, Video call\nĐánh giá: 4.8/5 từ 573 người dùng",
    "metadata": {
      "type": "product",
      "category": "smartphone",
      "subcategory": "flagship",
      "brand": "Google",
      "name": "Google Galaxy 13",
      "price": 20888844,
      "rating": 4.8,
      "in_stock": true,
      "id": "phone_027",
      "currency": "VND",
      "features": [
        "Fast charging",
        "Stereo speakers",
        "Water resistant",
        "Face unlock",
        "NFC"
      ],
      "pros": [
        "Hiệu năng mượt",
        "Loa hay",
        "Sạc nhanh",
        "Thiết kế premium",
        "Camera chất lượng"
      ],
      "cons": [
        "Nặng",
        "Pin yếu"
      ],
      "use_cases": [
        "Chụp ảnh",
        "Giải trí",
        "Video call"
      ],
      "review_count": 573,
      "warranty": "12 tháng",
      "tags": [
        "flagship",
        "google",
        "bestseller"
      ]
    }
  },
  {
    "id": "phone_028",
    "text": "OPPO Pixel 13 - OPPO\nGiá: 19,584,586 VND\nMô tả: Smartphone midrange OPPO với camera 50MP và hiệu năng tốt.\nThông số kỹ thuật:\n- cpu: Snapdragon 7 Gen 3\n- ram: 8GB\n- storage: 128GB\n- display: 5.6 inch Super AMOLED 90Hz\n- camera_main: 48MP main + 5MP ultra wide\n- camera_front: 16MP selfie\n- battery: 4296mAh\n- os: Android 13\n- connectivity: 5G, Wi-Fi 6, Bluetooth 5.3\nFeatures: Dual SIM, Fast charging, Night mode, Stereo speakers, Face unlock\nPros: Loa hay, Camera chất lượng, Hiệu năng mượt\nCons: Loa đơn, Không sạc không dây, Không có jack 3.5mm\nUse_Cases: Chụp ảnh, Công việc, Photography\nĐánh giá: 4.8/5 từ 536 người dùng",
    "metadata": {
      "type": "product",
      "category": "smartphone",
      "subcategory": "midrange",
      "brand": "OPPO",
      "name": "OPPO Pixel 13",
      "price": 19584586,
      "rating": 4.8,
      "in_stock": true,
      "id": "phone_028",
      "currency": "VND",
      "features": [
        "Dual SIM",
        "Fast charging",
        "Night mode",
        "Stereo speakers",
        "Face unlock"
      ],
      "pros": [
        "Loa hay",
        "Camera chất lượng",
        "Hiệu năng mượt"
      ],
      "cons": [
        "Loa đơn",
        "Không sạc không dây",
        "Không có jack 3.5mm"
      ],
      "use_cases": [
        "Chụp ảnh",
        "Công việc",
        "Photography"
      ],
      "review_count": 536,
      "warranty": "18 tháng",
      "tags": [
        "midrange",
        "oppo",
        "trending"
      ]
    }
  },
  {
    "id": "phone_029",
    "text": "OnePlus iPhone 15 - OnePlus\nGiá: 9,687,170 VND\nMô tả: Smartphone midrange OnePlus với camera 108MP và hiệu năng cao.\nThông số kỹ thuật:\n- cpu: Snapdragon 7 Gen 3\n- ram: 12GB\n- storage: 64GB\n- display: 5.5 inch Super AMOLED 120Hz\n- camera_main: 50MP main + 8MP ultra wide\n- camera_front: 16MP selfie\n- battery: 3523mAh\n- os: Android 13\n- connectivity: 5G, Wi-Fi 6, Bluetooth 5.3\nFeatures: NFC, Water resistant, Dual SIM, Stereo speakers, Face unlock\nPros: Thiết kế premium, Hiệu năng mượt, Camera chất lượng\nCons: Nặng, Nóng máy, Loa đơn\nUse_Cases: Gaming mobile, Công việc, Mạng xã hội, Streaming\nĐánh giá: 4.2/5 từ 688 người dùng",
    "metadata": {
      "type": "product",
      "category": "smartphone",
      "subcategory": "midrange",
      "brand": "OnePlus",
      "name": "OnePlus iPhone 15",
      "price": 9687170,
      "rating": 4.2,
      "in_stock": true,
      "id": "phone_029",
      "currency": "VND",
      "features": [
        "NFC",
        "Water resistant",
        "Dual SIM",
        "Stereo speakers",
        "Face unlock"
      ],
      "pros": [
        "Thiết kế premium",
        "Hiệu năng mượt",
        "Camera chất lượng"
      ],
      "cons": [
        "Nặng",
        "Nóng máy",
        "Loa đơn"
      ],
      "use_cases": [
        "Gaming mobile",
        "Công việc",
        "Mạng xã hội",
        "Streaming"
      ],
      "review_count": 688,
      "warranty": "24 tháng",
      "tags": [
        "midrange",
        "oneplus",
        "hot"
      ]
    }
  },
  {
    "id": "phone_030",
    "text": "OPPO Find 14 - OPPO\nGiá: 4,266,215 VND\nMô tả: Smartphone budget OPPO với camera 8MP và hiệu năng ổn định.\nThông số kỹ thuật:\n- cpu: Snapdragon 4 Gen 2\n- ram: 4GB\n- storage: 512GB\n- display: 6.3 inch IPS 60Hz\n- camera_main: 13MP main + 8MP ultra wide\n- camera_front: 32MP selfie\n- battery: 3667mAh\n- os: iOS 17\n- connectivity: 5G, Wi-Fi 6, Bluetooth 5.3\nFeatures: Fast charging, Always-on display, Fingerprint, Night mode, Water resistant\nPros: Giá hợp lý, Thiết kế premium, Màn hình đẹp\nCons: Nặng, Không có jack 3.5mm, Camera kém ánh sáng\nUse_Cases: Giải trí, Mạng xã hội, Chụp ảnh, Streaming\nĐánh giá: 4.6/5 từ 43 người dùng",
    "metadata": {
      "type": "product",
      "category": "smartphone",
      "subcategory": "budget",
      "brand": "OPPO",
      "name": "OPPO Find 14",
      "price": 4266215,
      "rating": 4.6,
      "in_stock": true,
      "id": "phone_030",
      "currency": "VND",
      "features": [
        "Fast charging",
        "Always-on display",
        "Fingerprint",
        "Night mode",
        "Water resistant"
      ],
      "pros": [
        "Giá hợp lý",
        "Thiết kế premium",
        "Màn hình đẹp"
      ],
      "cons": [
        "Nặng",
        "Không có jack 3.5mm",
        "Camera kém ánh sáng"
      ],
      "use_cases": [
        "Giải trí",
        "Mạng xã hội",
        "Chụp ảnh",
        "Streaming"
      ],
      "review_count": 43,
      "warranty": "24 tháng",
      "tags": [
        "budget",
        "oppo",
        "new-arrival"
      ]
    }
  },
  {
    "id": "phone_031",
    "text": "Vivo Pixel 11 - Vivo\nGiá: 19,943,110 VND\nMô tả: Smartphone midrange Vivo với camera 48MP và hiệu năng mạnh mẽ.\nThông số kỹ thuật:\n- cpu: Dimensity 8050\n- ram: 6GB\n- storage: 256GB\n- display: 5.6 inch AMOLED 60Hz\n- camera_main: 64MP main + 12MP ultra wide\n- camera_front: 8MP selfie\n- battery: 3921mAh\n- os: Android 14\n- connectivity: 5G, Wi-Fi 6, Bluetooth 5.3\nFeatures: Dual SIM, Night mode, Stereo speakers, NFC\nPros: Hiệu năng mượt, Camera chất lượng, Màn hình đẹp\nCons: Không có jack 3.5mm, Giá cao, Pin yếu, Camera kém ánh sáng\nUse_Cases: Giải trí, Chụp ảnh, Mạng xã hội\nĐánh giá: 4.1/5 từ 480 người dùng",
    "metadata": {
      "type": "product",
      "category": "smartphone",
      "subcategory": "midrange",
      "brand": "Vivo",
      "name": "Vivo Pixel 11",
      "price": 19943110,
      "rating": 4.1,
      "in_stock": false,
      "id": "phone_031",
      "currency": "VND",
      "features": [
        "Dual SIM",
        "Night mode",
        "Stereo speakers",
        "NFC"
      ],
      "pros": [
        "Hiệu năng mượt",
        "Camera chất lượng",
        "Màn hình đẹp"
      ],
      "cons": [
        "Không có jack 3.5mm",
        "Giá cao",
        "Pin yếu",
        "Camera kém ánh sáng"
      ],
      "use_cases": [
        "Giải trí",
        "Chụp ảnh",
        "Mạng xã hội"
      ],
      "review_count": 480,
      "warranty": "24 tháng",
      "tags": [
        "midrange",
        "vivo",
        "trending"
      ]
    }
  },
  {
    "id": "phone_032",
    "text": "Apple OnePlus 13 - Apple\nGiá: 2,931,840 VND\nMô tả: Smartphone budget Apple với camera 8MP và hiệu năng cao.\nThông số kỹ thuật:\n- cpu: Snapdragon 4 Gen 2\n- ram: 3GB\n- storage: 256GB\n- display: 5.8 inch IPS 60Hz\n- camera_main: 8MP main + 12MP ultra wide\n- camera_front: 16MP selfie\n- battery: 3383mAh\n- os: iOS 17\n- connectivity: 5G, Wi-Fi 6, Bluetooth 5.3\nFeatures: Dual SIM, Fingerprint, Stereo speakers, Water resistant, NFC, Night mode, Fast charging\nPros: Thiết kế premium, Camera chất lượng, Pin trâu, Loa hay, Giá hợp lý\nCons: Không sạc không dây, Không có jack 3.5mm\nUse_Cases: Video call, Gaming mobile, Photography\nĐánh giá: 4.7/5 từ 232 người dùng",
    "metadata": {
      "type": "product",
      "category": "smartphone",
      "subcategory": "budget",
      "brand": "Apple",
      "name": "Apple OnePlus 13",
      "price": 2931840,
      "rating": 4.7,
      "in_stock": true,
      "id": "phone_032",
      "currency": "VND",
      "features": [
        "Dual SIM",
        "Fingerprint",
        "Stereo speakers",
        "Water resistant",
        "NFC",
        "Night mode",
        "Fast charging"
      ],
      "pros": [
        "Thiết kế premium",
        "Camera chất lượng",
        "Pin trâu",
        "Loa hay",
        "Giá hợp lý"
      ],
      "cons": [
        "Không sạc không dây",
        "Không có jack 3.5mm"
      ],
      "use_cases": [
        "Video call",
        "Gaming mobile",
        "Photography"
      ],
      "review_count": 232,
      "warranty": "12 tháng",
      "tags": [
        "budget",
        "apple",
        "bestseller"
      ]
    }
  },
  {
    "id": "phone_033",
    "text": "Samsung Galaxy 10 - Samsung\nGiá: 19,527,527 VND\nMô tả: Smartphone midrange Samsung với camera 50MP và hiệu năng mạnh mẽ.\nThông số kỹ thuật:\n- cpu: Exynos 1380\n- ram: 12GB\n- storage: 512GB\n- display: 6.2 inch Super AMOLED 90Hz\n- camera_main: 108MP main + 5MP ultra wide\n- camera_front: 12MP selfie\n- battery: 4455mAh\n- os: Android 14\n- connectivity: 5G, Wi-Fi 6, Bluetooth 5.3\nFeatures: Wireless charging, Always-on display, Face unlock, Dual SIM, NFC, Water resistant, Stereo speakers\nPros: Sạc nhanh, Giá hợp lý, Camera chất lượng\nCons: Nóng máy, Giá cao, Không sạc không dây, Camera kém ánh sáng\nUse_Cases: Video call, Gaming mobile, Công việc\nĐánh giá: 4.4/5 từ 331 người dùng",
    "metadata": {
      "type": "product",
      "category": "smartphone",
      "subcategory": "midrange",
      "brand": "Samsung",
      "name": "Samsung Galaxy 10",
      "price": 19527527,
      "rating": 4.4,
      "in_stock": true,
      "id": "phone_033",
      "currency": "VND",
      "features": [
        "Wireless charging",
        "Always-on display",
        "Face unlock",
        "Dual SIM",
        "NFC",
        "Water resistant",
        "Stereo speakers"
      ],
      "pros": [
        "Sạc nhanh",
        "Giá hợp lý",
        "Camera chất lượng"
      ],
      "cons": [
        "Nóng máy",
        "Giá cao",
        "Không sạc không dây",
        "Camera kém ánh sáng"
      ],
      "use_cases": [
        "Video call",
        "Gaming mobile",
        "Công việc"
      ],
      "review_count": 331,
      "warranty": "24 tháng",
      "tags": [
        "midrange",
        "samsung",
        "trending"
      ]
    }
  },
  {
    "id": "phone_034",
    "text": "Xiaomi Mi 10 - Xiaomi\nGiá: 23,991,739 VND\nMô tả: Smartphone flagship Xiaomi với camera 50MP và hiệu năng cao.\nThông số kỹ thuật:\n- cpu: Exynos 2400\n- ram: 8GB\n- storage: 256GB\n- display: 6.4 inch Super AMOLED 60Hz\n- camera_main: 200MP main + 5MP ultra wide\n- camera_front: 12MP selfie\n- battery: 4118mAh\n- os: Android 14\n- connectivity: 5G, Wi-Fi 6, Bluetooth 5.3\nFeatures: Fingerprint, Dual SIM, Fast charging, Night mode, Always-on display\nPros: Thiết kế premium, Loa hay, Màn hình đẹp\nCons: Loa đơn, Nặng, Nóng máy, Không có jack 3.5mm\nUse_Cases: Gaming mobile, Mạng xã hội, Giải trí\nĐánh giá: 4.4/5 từ 490 người dùng",
    "metadata": {
      "type": "product",
      "category": "smartphone",
      "subcategory": "flagship",
      "brand": "Xiaomi",
      "name": "Xiaomi Mi 10",
      "price": 23991739,
      "rating": 4.4,
      "in_stock": true,
      "id": "phone_034",
      "currency": "VND",
      "features": [
        "Fingerprint",
        "Dual SIM",
        "Fast charging",
        "Night mode",
        "Always-on display"
      ],
      "pros": [
        "Thiết kế premium",
        "Loa hay",
        "Màn hình đẹp"
      ],
      "cons": [
        "Loa đơn",
        "Nặng",
        "Nóng máy",
        "Không có jack 3.5mm"
      ],
      "use_cases": [
        "Gaming mobile",
        "Mạng xã hội",
        "Giải trí"
      ],
      "review_count": 490,
      "warranty": "18 tháng",
      "tags": [
        "flagship",
        "xiaomi",
        "trending"
      ]
    }
  },
  {
    "id": "phone_035",
    "text": "OnePlus OnePlus 11 - OnePlus\nGiá: 7,115,894 VND\nMô tả: Smartphone budget OnePlus với camera 48MP và hiệu năng cao.\nThông số kỹ thuật:\n- cpu: Dimensity 6020\n- ram: 4GB\n- storage: 256GB\n- display: 6.4 inch IPS 90Hz\n- camera_main: 48MP main + 12MP ultra wide\n- camera_front: 8MP selfie\n- battery: 4586mAh\n- os: iOS 17\n- connectivity: 5G, Wi-Fi 6, Bluetooth 5.3\nFeatures: Face unlock, Dual SIM, Fingerprint, Stereo speakers, Always-on display\nPros: Hiệu năng mượt, Loa hay, Sạc nhanh, Camera chất lượng\nCons: Camera kém ánh sáng, Không sạc không dây, Pin yếu, Giá cao\nUse_Cases: Photography, Video call, Mạng xã hội, Giải trí\nĐánh giá: 4.6/5 từ 490 người dùng",
    "metadata": {
      "type": "product",
      "category": "smartphone",
      "subcategory": "budget",
      "brand": "OnePlus",
      "name": "OnePlus OnePlus 11",
      "price": 7115894,
      "rating": 4.6,
      "in_stock": true,
      "id": "phone_035",
      "currency": "VND",
      "features": [
        "Face unlock",
        "Dual SIM",
        "Fingerprint",
        "Stereo speakers",
        "Always-on display"
      ],
      "pros": [
        "Hiệu năng mượt",
        "Loa hay",
        "Sạc nhanh",
        "Camera chất lượng"
      ],
      "cons": [
        "Camera kém ánh sáng",
        "Không sạc không dây",
        "Pin yếu",
        "Giá cao"
      ],
      "use_cases": [
        "Photography",
        "Video call",
        "Mạng xã hội",
        "Giải trí"
      ],
      "review_count": 490,
      "warranty": "18 tháng",
      "tags": [
        "budget",
        "oneplus",
        "bestseller"
      ]
    }
  },
  {
    "id": "phone_036",
    "text": "Huawei OnePlus 15 - Huawei\nGiá: 28,734,563 VND\nMô tả: Smartphone flagship Huawei với camera 48MP và hiệu năng ổn định.\nThông số kỹ thuật:\n- cpu: Dimensity 9300\n- ram: 8GB\n- storage: 64GB\n- display: 5.6 inch IPS 90Hz\n- camera_main: 200MP main + 5MP ultra wide\n- camera_front: 16MP selfie\n- battery: 3566mAh\n- os: iOS 17\n- connectivity: 5G, Wi-Fi 6, Bluetooth 5.3\nFeatures: Water resistant, Wireless charging, Night mode, NFC\nPros: Loa hay, Màn hình đẹp, Thiết kế premium\nCons: Loa đơn, Không có jack 3.5mm, Nóng máy, Giá cao\nUse_Cases: Video call, Streaming, Chụp ảnh, Gaming mobile\nĐánh giá: 4.3/5 từ 248 người dùng",
    "metadata": {
      "type": "product",
      "category": "smartphone",
      "subcategory": "flagship",
      "brand": "Huawei",
      "name": "Huawei OnePlus 15",
      "price": 28734563,
      "rating": 4.3,
      "in_stock": true,
      "id": "phone_036",
      "currency": "VND",
      "features": [
        "Water resistant",
        "Wireless charging",
        "Night mode",
        "NFC"
      ],
      "pros": [
        "Loa hay",
        "Màn hình đẹp",
        "Thiết kế premium"
      ],
      "cons": [
        "Loa đơn",
        "Không có jack 3.5mm",
        "Nóng máy",
        "Giá cao"
      ],
      "use_cases": [
        "Video call",
        "Streaming",
        "Chụp ảnh",
        "Gaming mobile"
      ],
      "review_count": 248,
      "warranty": "18 tháng",
      "tags": [
        "flagship",
        "huawei",
        "new-arrival"
      ]
    }
  },
  {
    "id": "phone_037",
    "text": "Xiaomi OnePlus 14 - Xiaomi\nGiá: 14,412,559 VND\nMô tả: Smartphone midrange Xiaomi với camera 48MP và hiệu năng cao.\nThông số kỹ thuật:\n- cpu: Snapdragon 7 Gen 3\n- ram: 12GB\n- storage: 512GB\n- display: 6.2 inch Super AMOLED 60Hz\n- camera_main: 50MP main + 5MP ultra wide\n- camera_front: 12MP selfie\n- battery: 3288mAh\n- os: Android 13\n- connectivity: 5G, Wi-Fi 6, Bluetooth 5.3\nFeatures: Fast charging, Water resistant, Always-on display, Wireless charging, Stereo speakers, Night mode\nPros: Thiết kế premium, Camera chất lượng, Pin trâu, Loa hay\nCons: Nóng máy, Loa đơn, Nặng, Không sạc không dây\nUse_Cases: Video call, Chụp ảnh, Mạng xã hội, Gaming mobile\nĐánh giá: 4.9/5 từ 712 người dùng",
    "metadata": {
      "type": "product",
      "category": "smartphone",
      "subcategory": "midrange",
      "brand": "Xiaomi",
      "name": "Xiaomi OnePlus 14",
      "price": 14412559,
      "rating": 4.9,
      "in_stock": true,
      "id": "phone_037",
      "currency": "VND",
      "features": [
        "Fast charging",
        "Water resistant",
        "Always-on display",
        "Wireless charging",
        "Stereo speakers",
        "Night mode"
      ],
      "pros": [
        "Thiết kế premium",
        "Camera chất lượng",
        "Pin trâu",
        "Loa hay"
      ],
      "cons": [
        "Nóng máy",
        "Loa đơn",
        "Nặng",
        "Không sạc không dây"
      ],
      "use_cases": [
        "Video call",
        "Chụp ảnh",
        "Mạng xã hội",
        "Gaming mobile"
      ],
      "review_count": 712,
      "warranty": "18 tháng",
      "tags": [
        "midrange",
        "xiaomi",
        "trending"
      ]
    }
  },
  {
    "id": "phone_038",
    "text": "OPPO Galaxy 15 - OPPO\nGiá: 12,571,360 VND\nMô tả: Smartphone midrange OPPO với camera 108MP và hiệu năng cao.\nThông số kỹ thuật:\n- cpu: Dimensity 8050\n- ram: 6GB\n- storage: 128GB\n- display: 5.9 inch Super AMOLED 60Hz\n- camera_main: 64MP main + 8MP ultra wide\n- camera_front: 8MP selfie\n- battery: 4207mAh\n- os: Android 13\n- connectivity: 5G, Wi-Fi 6, Bluetooth 5.3\nFeatures: Fast charging, Fingerprint, Night mode, Face unlock, NFC, Water resistant, Stereo speakers\nPros: Màn hình đẹp, Sạc nhanh, Hiệu năng mượt, Giá hợp lý\nCons: Camera kém ánh sáng, Không có jack 3.5mm\nUse_Cases: Giải trí, Streaming, Mạng xã hội, Gaming mobile, Photography\nĐánh giá: 3.8/5 từ 777 người dùng",
    "metadata": {
      "type": "product",
      "category": "smartphone",
      "subcategory": "midrange",
      "brand": "OPPO",
      "name": "OPPO Galaxy 15",
      "price": 12571360,
      "rating": 3.8,
      "in_stock": true,
      "id": "phone_038",
      "currency": "VND",
      "features": [
        "Fast charging",
        "Fingerprint",
        "Night mode",
        "Face unlock",
        "NFC",
        "Water resistant",
        "Stereo speakers"
      ],
      "pros": [
        "Màn hình đẹp",
        "Sạc nhanh",
        "Hiệu năng mượt",
        "Giá hợp lý"
      ],
      "cons": [
        "Camera kém ánh sáng",
        "Không có jack 3.5mm"
      ],
      "use_cases": [
        "Giải trí",
        "Streaming",
        "Mạng xã hội",
        "Gaming mobile",
        "Photography"
      ],
      "review_count": 777,
      "warranty": "24 tháng",
      "tags": [
        "midrange",
        "oppo",
        "bestseller"
      ]
    }
  },
  {
    "id": "phone_039",
    "text": "OPPO iPhone 12 - OPPO\nGiá: 30,282,978 VND\nMô tả: Smartphone flagship OPPO với camera 200MP và hiệu năng cao.\nThông số kỹ thuật:\n- cpu: Dimensity 9300\n- ram: 8GB\n- storage: 256GB\n- display: 6.0 inch AMOLED 120Hz\n- camera_main: 50MP main + 5MP ultra wide\n- camera_front: 8MP selfie\n- battery: 3545mAh\n- os: Android 13\n- connectivity: 5G, Wi-Fi 6, Bluetooth 5.3\nFeatures: Dual SIM, Water resistant, Fingerprint, NFC, Always-on display, Fast charging\nPros: Màn hình đẹp, Sạc nhanh, Hiệu năng mượt\nCons: Không có jack 3.5mm, Nặng\nUse_Cases: Video call, Chụp ảnh, Streaming\nĐánh giá: 4.2/5 từ 50 người dùng",
    "metadata": {
      "type": "product",
      "category": "smartphone",
      "subcategory": "flagship",
      "brand": "OPPO",
      "name": "OPPO iPhone 12",
      "price": 30282978,
      "rating": 4.2,
      "in_stock": true,
      "id": "phone_039",
      "currency": "VND",
      "features": [
        "Dual SIM",
        "Water resistant",
        "Fingerprint",
        "NFC",
        "Always-on display",
        "Fast charging"
      ],
      "pros": [
        "Màn hình đẹp",
        "Sạc nhanh",
        "Hiệu năng mượt"
      ],
      "cons": [
        "Không có jack 3.5mm",
        "Nặng"
      ],
      "use_cases": [
        "Video call",
        "Chụp ảnh",
        "Streaming"
      ],
      "review_count": 50,
      "warranty": "12 tháng",
      "tags": [
        "flagship",
        "oppo",
        "new-arrival"
      ]
    }
  },
  {
    "id": "phone_040",
    "text": "Samsung Galaxy 14 - Samsung\nGiá: 2,905,994 VND\nMô tả: Smartphone budget Samsung với camera 48MP và hiệu năng tốt.\nThông số kỹ thuật:\n- cpu: Helio G99\n- ram: 3GB\n- storage: 64GB\n- display: 6.0 inch IPS 120Hz\n- camera_main: 8MP main + 8MP ultra wide\n- camera_front: 12MP selfie\n- battery: 4206mAh\n- os: iOS 17\n- connectivity: 5G, Wi-Fi 6, Bluetooth 5.3\nFeatures: Night mode, Wireless charging, Face unlock, NFC\nPros: Hiệu năng mượt, Loa hay, Màn hình đẹp, Pin trâu\nCons: Camera kém ánh sáng, Không có jack 3.5mm, Nặng, Nóng máy\nUse_Cases: Gaming mobile, Công việc, Chụp ảnh\nĐánh giá: 4.5/5 từ 343 người dùng",
    "metadata": {
      "type": "product",
      "category": "smartphone",
      "subcategory": "budget",
      "brand": "Samsung",
      "name": "Samsung Galaxy 14",
      "price": 2905994,
      "rating": 4.5,
      "in_stock": false,
      "id": "phone_040",
      "currency": "VND",
      "features": [
        "Night mode",
        "Wireless charging",
        "Face unlock",
        "NFC"
      ],
      "pros": [
        "Hiệu năng mượt",
        "Loa hay",
        "Màn hình đẹp",
        "Pin trâu"
      ],
      "cons": [
        "Camera kém ánh sáng",
        "Không có jack 3.5mm",
        "Nặng",
        "Nóng máy"
      ],
      "use_cases": [
        "Gaming mobile",
        "Công việc",
        "Chụp ảnh"
      ],
      "review_count": 343,
      "warranty": "12 tháng",
      "tags": [
        "budget",
        "samsung",
        "trending"
      ]
    }
  },
  {
    "id": "phone_041",
    "text": "Huawei Galaxy 13 - Huawei\nGiá: 19,191,438 VND\nMô tả: Smartphone midrange Huawei với camera 108MP và hiệu năng cao.\nThông số kỹ thuật:\n- cpu: Dimensity 8050\n- ram: 12GB\n- storage: 256GB\n- display: 6.8 inch Super AMOLED 120Hz\n- camera_main: 108MP main + 12MP ultra wide\n- camera_front: 12MP selfie\n- battery: 3282mAh\n- os: Android 14\n- connectivity: 5G, Wi-Fi 6, Bluetooth 5.3\nFeatures: NFC, Water resistant, Face unlock, Fast charging, Always-on display, Night mode\nPros: Thiết kế premium, Màn hình đẹp, Hiệu năng mượt\nCons: Loa đơn, Nặng\nUse_Cases: Công việc, Photography, Gaming mobile, Chụp ảnh\nĐánh giá: 4.2/5 từ 791 người dùng",
    "metadata": {
      "type": "product",
      "category": "smartphone",
      "subcategory": "midrange",
      "brand": "Huawei",
      "name": "Huawei Galaxy 13",
      "price": 19191438,
      "rating": 4.2,
      "in_stock": true,
      "id": "phone_041",
      "currency": "VND",
      "features": [
        "NFC",
        "Water resistant",
        "Face unlock",
        "Fast charging",
        "Always-on display",
        "Night mode"
      ],
      "pros": [
        "Thiết kế premium",
        "Màn hình đẹp",
        "Hiệu năng mượt"
      ],
      "cons": [
        "Loa đơn",
        "Nặng"
      ],
      "use_cases": [
        "Công việc",
        "Photography",
        "Gaming mobile",
        "Chụp ảnh"
      ],
      "review_count": 791,
      "warranty": "18 tháng",
      "tags": [
        "midrange",
        "huawei",
        "new-arrival"
      ]
    }
  },
  {
    "id": "phone_042",
    "text": "Xiaomi Galaxy 10 - Xiaomi\nGiá: 5,300,002 VND\nMô tả: Smartphone budget Xiaomi với camera 8MP và hiệu năng mạnh mẽ.\nThông số kỹ thuật:\n- cpu: Helio G99\n- ram: 3GB\n- storage: 64GB\n- display: 6.6 inch IPS 60Hz\n- camera_main: 48MP main + 12MP ultra wide\n- camera_front: 16MP selfie\n- battery: 3023mAh\n- os: iOS 17\n- connectivity: 5G, Wi-Fi 6, Bluetooth 5.3\nFeatures: Dual SIM, Water resistant, Fingerprint, Fast charging, Always-on display, Wireless charging, Face unlock\nPros: Màn hình đẹp, Loa hay, Camera chất lượng\nCons: Không có jack 3.5mm, Nặng, Không sạc không dây\nUse_Cases: Công việc, Chụp ảnh, Mạng xã hội, Video call, Photography\nĐánh giá: 4.5/5 từ 715 người dùng",
    "metadata": {
      "type": "product",
      "category": "smartphone",
      "subcategory": "budget",
      "brand": "Xiaomi",
      "name": "Xiaomi Galaxy 10",
      "price": 5300002,
      "rating": 4.5,
      "in_stock": true,
      "id": "phone_042",
      "currency": "VND",
      "features": [
        "Dual SIM",
        "Water resistant",
        "Fingerprint",
        "Fast charging",
        "Always-on display",
        "Wireless charging",
        "Face unlock"
      ],
      "pros": [
        "Màn hình đẹp",
        "Loa hay",
        "Camera chất lượng"
      ],
      "cons": [
        "Không có jack 3.5mm",
        "Nặng",
        "Không sạc không dây"
      ],
      "use_cases": [
        "Công việc",
        "Chụp ảnh",
        "Mạng xã hội",
        "Video call",
        "Photography"
      ],
      "review_count": 715,
      "warranty": "24 tháng",
      "tags": [
        "budget",
        "xiaomi",
        "new-arrival"
      ]
    }
  },
  {
    "id": "phone_043",
    "text": "Vivo Find 11 - Vivo\nGiá: 13,234,152 VND\nMô tả: Smartphone midrange Vivo với camera 64MP và hiệu năng ổn định.\nThông số kỹ thuật:\n- cpu: A16 Bionic\n- ram: 6GB\n- storage: 128GB\n- display: 6.8 inch IPS 60Hz\n- camera_main: 108MP main + 12MP ultra wide\n- camera_front: 16MP selfie\n- battery: 4902mAh\n- os: iOS 17\n- connectivity: 5G, Wi-Fi 6, Bluetooth 5.3\nFeatures: Night mode, Stereo speakers, Face unlock, Water resistant, Fast charging, Always-on display\nPros: Camera chất lượng, Sạc nhanh, Thiết kế premium, Hiệu năng mượt, Giá hợp lý\nCons: Nặng, Loa đơn, Giá cao, Pin yếu\nUse_Cases: Mạng xã hội, Công việc, Video call\nĐánh giá: 4.1/5 từ 703 người dùng",
    "metadata": {
      "type": "product",
      "category": "smartphone",
      "subcategory": "midrange",
      "brand": "Vivo",
      "name": "Vivo Find 11",
      "price": 13234152,
      "rating": 4.1,
      "in_stock": true,
      "id": "phone_043",
      "currency": "VND",
      "features": [
        "Night mode",
        "Stereo speakers",
        "Face unlock",
        "Water resistant",
        "Fast charging",
        "Always-on display"
      ],
      "pros": [
        "Camera chất lượng",
        "Sạc nhanh",
        "Thiết kế premium",
        "Hiệu năng mượt",
        "Giá hợp lý"
      ],
      "cons": [
        "Nặng",
        "Loa đơn",
        "Giá cao",
        "Pin yếu"
      ],
      "use_cases": [
        "Mạng xã hội",
        "Công việc",
        "Video call"
      ],
      "review_count": 703,
      "warranty": "18 tháng",
      "tags": [
        "midrange",
        "vivo",
        "trending"
      ]
    }
  },
  {
    "id": "phone_044",
    "text": "Google iPhone 14 - Google\nGiá: 32,954,465 VND\nMô tả: Smartphone flagship Google với camera 50MP và hiệu năng cao.\nThông số kỹ thuật:\n- cpu: Dimensity 9300\n- ram: 16GB\n- storage: 512GB\n- display: 6.5 inch AMOLED 120Hz\n- camera_main: 50MP main + 12MP ultra wide\n- camera_front: 8MP selfie\n- battery: 3815mAh\n- os: Android 13\n- connectivity: 5G, Wi-Fi 6, Bluetooth 5.3\nFeatures: Water resistant, NFC, Fingerprint, Face unlock\nPros: Màn hình đẹp, Thiết kế premium, Giá hợp lý\nCons: Pin yếu, Nặng\nUse_Cases: Chụp ảnh, Mạng xã hội, Giải trí, Video call, Photography\nĐánh giá: 4.7/5 từ 440 người dùng",
    "metadata": {
      "type": "product",
      "category": "smartphone",
      "subcategory": "flagship",
      "brand": "Google",
      "name": "Google iPhone 14",
      "price": 32954465,
      "rating": 4.7,
      "in_stock": true,
      "id": "phone_044",
      "currency": "VND",
      "features": [
        "Water resistant",
        "NFC",
        "Fingerprint",
        "Face unlock"
      ],
      "pros": [
        "Màn hình đẹp",
        "Thiết kế premium",
        "Giá hợp lý"
      ],
      "cons": [
        "Pin yếu",
        "Nặng"
      ],
      "use_cases": [
        "Chụp ảnh",
        "Mạng xã hội",
        "Giải trí",
        "Video call",
        "Photography"
      ],
      "review_count": 440,
      "warranty": "24 tháng",
      "tags": [
        "flagship",
        "google",
        "hot"
      ]
    }
  },
  {
    "id": "phone_045",
    "text": "Samsung Find 12 - Samsung\nGiá: 6,765,281 VND\nMô tả: Smartphone budget Samsung với camera 50MP và hiệu năng ổn định.\nThông số kỹ thuật:\n- cpu: Helio G99\n- ram: 4GB\n- storage: 128GB\n- display: 6.7 inch IPS 90Hz\n- camera_main: 13MP main + 8MP ultra wide\n- camera_front: 8MP selfie\n- battery: 3188mAh\n- os: Android 14\n- connectivity: 5G, Wi-Fi 6, Bluetooth 5.3\nFeatures: Always-on display, Face unlock, Fast charging, Fingerprint, NFC\nPros: Camera chất lượng, Giá hợp lý, Hiệu năng mượt\nCons: Camera kém ánh sáng, Giá cao, Nặng, Nóng máy\nUse_Cases: Streaming, Công việc, Video call\nĐánh giá: 4.4/5 từ 619 người dùng",
    "metadata": {
      "type": "product",
      "category": "smartphone",
      "subcategory": "budget",
      "brand": "Samsung",
      "name": "Samsung Find 12",
      "price": 6765281,
      "rating": 4.4,
      "in_stock": true,
      "id": "phone_045",
      "currency": "VND",
      "features": [
        "Always-on display",
        "Face unlock",
        "Fast charging",
        "Fingerprint",
        "NFC"
      ],
      "pros": [
        "Camera chất lượng",
        "Giá hợp lý",
        "Hiệu năng mượt"
      ],
      "cons": [
        "Camera kém ánh sáng",
        "Giá cao",
        "Nặng",
        "Nóng máy"
      ],
      "use_cases": [
        "Streaming",
        "Công việc",
        "Video call"
      ],
      "review_count": 619,
      "warranty": "18 tháng",
      "tags": [
        "budget",
        "samsung",
        "bestseller"
      ]
    }
  },
  {
    "id": "phone_046",
    "text": "Google Pixel 14 - Google\nGiá: 23,411,704 VND\nMô tả: Smartphone flagship Google với camera 48MP và hiệu năng mạnh mẽ.\nThông số kỹ thuật:\n- cpu: A17 Pro\n- ram: 8GB\n- storage: 64GB\n- display: 5.6 inch IPS 90Hz\n- camera_main: 108MP main + 12MP ultra wide\n- camera_front: 32MP selfie\n- battery: 3572mAh\n- os: Android 13\n- connectivity: 5G, Wi-Fi 6, Bluetooth 5.3\nFeatures: Always-on display, Face unlock, Night mode, Wireless charging\nPros: Thiết kế premium, Loa hay, Pin trâu, Camera chất lượng\nCons: Không có jack 3.5mm, Nóng máy, Không sạc không dây, Camera kém ánh sáng\nUse_Cases: Gaming mobile, Video call, Công việc, Photography, Mạng xã hội\nĐánh giá: 4.2/5 từ 349 người dùng",
    "metadata": {
      "type": "product",
      "category": "smartphone",
      "subcategory": "flagship",
      "brand": "Google",
      "name": "Google Pixel 14",
      "price": 23411704,
      "rating": 4.2,
      "in_stock": true,
      "id": "phone_046",
      "currency": "VND",
      "features": [
        "Always-on display",
        "Face unlock",
        "Night mode",
        "Wireless charging"
      ],
      "pros": [
        "Thiết kế premium",
        "Loa hay",
        "Pin trâu",
        "Camera chất lượng"
      ],
      "cons": [
        "Không có jack 3.5mm",
        "Nóng máy",
        "Không sạc không dây",
        "Camera kém ánh sáng"
      ],
      "use_cases": [
        "Gaming mobile",
        "Video call",
        "Công việc",
        "Photography",
        "Mạng xã hội"
      ],
      "review_count": 349,
      "warranty": "18 tháng",
      "tags": [
        "flagship",
        "google",
        "new-arrival"
      ]
    }
  },
  {
    "id": "phone_047",
    "text": "Xiaomi Galaxy 12 - Xiaomi\nGiá: 14,579,992 VND\nMô tả: Smartphone midrange Xiaomi với camera 50MP và hiệu năng ổn định.\nThông số kỹ thuật:\n- cpu: Dimensity 8050\n- ram: 6GB\n- storage: 64GB\n- display: 6.6 inch AMOLED 90Hz\n- camera_main: 50MP main + 8MP ultra wide\n- camera_front: 12MP selfie\n- battery: 4501mAh\n- os: iOS 17\n- connectivity: 5G, Wi-Fi 6, Bluetooth 5.3\nFeatures: Always-on display, Wireless charging, Face unlock, Water resistant, Fast charging, Night mode, Stereo speakers\nPros: Màn hình đẹp, Loa hay, Thiết kế premium\nCons: Pin yếu, Nóng máy, Không sạc không dây, Loa đơn\nUse_Cases: Streaming, Video call, Công việc, Mạng xã hội\nĐánh giá: 4.4/5 từ 21 người dùng",
    "metadata": {
      "type": "product",
      "category": "smartphone",
      "subcategory": "midrange",
      "brand": "Xiaomi",
      "name": "Xiaomi Galaxy 12",
      "price": 14579992,
      "rating": 4.4,
      "in_stock": true,
      "id": "phone_047",
      "currency": "VND",
      "features": [
        "Always-on display",
        "Wireless charging",
        "Face unlock",
        "Water resistant",
        "Fast charging",
        "Night mode",
        "Stereo speakers"
      ],
      "pros": [
        "Màn hình đẹp",
        "Loa hay",
        "Thiết kế premium"
      ],
      "cons": [
        "Pin yếu",
        "Nóng máy",
        "Không sạc không dây",
        "Loa đơn"
      ],
      "use_cases": [
        "Streaming",
        "Video call",
        "Công việc",
        "Mạng xã hội"
      ],
      "review_count": 21,
      "warranty": "12 tháng",
      "tags": [
        "midrange",
        "xiaomi",
        "bestseller"
      ]
    }
  },
  {
    "id": "phone_048",
    "text": "Samsung iPhone 15 - Samsung\nGiá: 3,256,157 VND\nMô tả: Smartphone budget Samsung với camera 50MP và hiệu năng cao.\nThông số kỹ thuật:\n- cpu: Snapdragon 4 Gen 2\n- ram: 3GB\n- storage: 512GB\n- display: 6.5 inch AMOLED 120Hz\n- camera_main: 13MP main + 5MP ultra wide\n- camera_front: 8MP selfie\n- battery: 3820mAh\n- os: iOS 17\n- connectivity: 5G, Wi-Fi 6, Bluetooth 5.3\nFeatures: Fingerprint, Fast charging, Wireless charging, Dual SIM, Stereo speakers\nPros: Sạc nhanh, Pin trâu, Camera chất lượng, Giá hợp lý, Loa hay\nCons: Giá cao, Pin yếu\nUse_Cases: Mạng xã hội, Streaming, Gaming mobile, Công việc, Chụp ảnh\nĐánh giá: 4.4/5 từ 708 người dùng",
    "metadata": {
      "type": "product",
      "category": "smartphone",
      "subcategory": "budget",
      "brand": "Samsung",
      "name": "Samsung iPhone 15",
      "price": 3256157,
      "rating": 4.4,
      "in_stock": false,
      "id": "phone_048",
      "currency": "VND",
      "features": [
        "Fingerprint",
        "Fast charging",
        "Wireless charging",
        "Dual SIM",
        "Stereo speakers"
      ],
      "pros": [
        "Sạc nhanh",
        "Pin trâu",
        "Camera chất lượng",
        "Giá hợp lý",
        "Loa hay"
      ],
      "cons": [
        "Giá cao",
        "Pin yếu"
      ],
      "use_cases": [
        "Mạng xã hội",
        "Streaming",
        "Gaming mobile",
        "Công việc",
        "Chụp ảnh"
      ],
      "review_count": 708,
      "warranty": "18 tháng",
      "tags": [
        "budget",
        "samsung",
        "hot"
      ]
    }
  },
  {
    "id": "phone_049",
    "text": "Samsung OnePlus 14 - Samsung\nGiá: 6,001,219 VND\nMô tả: Smartphone budget Samsung với camera 50MP và hiệu năng tốt.\nThông số kỹ thuật:\n- cpu: Dimensity 6020\n- ram: 3GB\n- storage: 64GB\n- display: 6.2 inch AMOLED 90Hz\n- camera_main: 8MP main + 12MP ultra wide\n- camera_front: 16MP selfie\n- battery: 4311mAh\n- os: Android 14\n- connectivity: 5G, Wi-Fi 6, Bluetooth 5.3\nFeatures: Water resistant, Wireless charging, Dual SIM, Stereo speakers, Always-on display\nPros: Camera chất lượng, Hiệu năng mượt, Màn hình đẹp, Loa hay\nCons: Nóng máy, Loa đơn, Không sạc không dây\nUse_Cases: Giải trí, Chụp ảnh, Video call, Photography, Streaming\nĐánh giá: 4.9/5 từ 294 người dùng",
    "metadata": {
      "type": "product",
      "category": "smartphone",
      "subcategory": "budget",
      "brand": "Samsung",
      "name": "Samsung OnePlus 14",
      "price": 6001219,
      "rating": 4.9,
      "in_stock": true,
      "id": "phone_049",
      "currency": "VND",
      "features": [
        "Water resistant",
        "Wireless charging",
        "Dual SIM",
        "Stereo speakers",
        "Always-on display"
      ],
      "pros": [
        "Camera chất lượng",
        "Hiệu năng mượt",
        "Màn hình đẹp",
        "Loa hay"
      ],
      "cons": [
        "Nóng máy",
        "Loa đơn",
        "Không sạc không dây"
      ],
      "use_cases": [
        "Giải trí",
        "Chụp ảnh",
        "Video call",
        "Photography",
        "Streaming"
      ],
      "review_count": 294,
      "warranty": "24 tháng",
      "tags": [
        "budget",
        "samsung",
        "new-arrival"
      ]
    }
  },
  {
    "id": "phone_050",
    "text": "Huawei Galaxy 12 - Huawei\nGiá: 4,245,176 VND\nMô tả: Smartphone budget Huawei với camera 8MP và hiệu năng cao.\nThông số kỹ thuật:\n- cpu: Snapdragon 4 Gen 2\n- ram: 6GB\n- storage: 256GB\n- display: 6.6 inch AMOLED 120Hz\n- camera_main: 48MP main + 12MP ultra wide\n- camera_front: 16MP selfie\n- battery: 3732mAh\n- os: Android 13\n- connectivity: 5G, Wi-Fi 6, Bluetooth 5.3\nFeatures: Face unlock, Stereo speakers, Water resistant, Fast charging, Night mode, Dual SIM, Always-on display\nPros: Camera chất lượng, Pin trâu, Sạc nhanh, Thiết kế premium\nCons: Không sạc không dây, Pin yếu\nUse_Cases: Giải trí, Công việc, Streaming, Mạng xã hội, Photography\nĐánh giá: 4.3/5 từ 657 người dùng",
    "metadata": {
      "type": "product",
      "category": "smartphone",
      "subcategory": "budget",
      "brand": "Huawei",
      "name": "Huawei Galaxy 12",
      "price": 4245176,
      "rating": 4.3,
      "in_stock": true,
      "id": "phone_050",
      "currency": "VND",
      "features": [
        "Face unlock",
        "Stereo speakers",
        "Water resistant",
        "Fast charging",
        "Night mode",
        "Dual SIM",
        "Always-on display"
      ],
      "pros": [
        "Camera chất lượng",
        "Pin trâu",
        "Sạc nhanh",
        "Thiết kế premium"
      ],
      "cons": [
        "Không sạc không dây",
        "Pin yếu"
      ],
      "use_cases": [
        "Giải trí",
        "Công việc",
        "Streaming",
        "Mạng xã hội",
        "Photography"
      ],
      "review_count": 657,
      "warranty": "18 tháng",
      "tags": [
        "budget",
        "huawei",
        "new-arrival"
      ]
    }
  },
  {
    "id": "review_001",
    "text": "Review: Laptop tuyệt vời cho lập trình và design\nĐánh giá: 5/5\nNội dung: Mình dùng Dell XPS 15 được 3 tháng cho công việc full-stack development và thỉnh thoảng edit video. Màn hình 4K OLED quá đẹp, code nhìn rất sướng mắt. Hiệu năng xử lý đa nhiệm mượt mà, build Docker, chạy multiple VMs không lag. Pin dùng được cả ngày làm việc nếu không bật 4K.\nƯu điểm: Màn hình xuất sắc, Build quality cao cấp, Hiệu năng mạnh\nNhược điểm: Hơi nóng khi render video, Giá cao",
    "metadata": {
      "type": "review",
      "product_id": "laptop_001",
      "rating": 5,
      "helpful_count": 45,
      "verified_purchase": true,
      "id": "review_001",
      "user_name": "Nguyễn Văn A",
      "title": "Laptop tuyệt vời cho lập trình và design",
      "content": "Mình dùng Dell XPS 15 được 3 tháng cho công việc full-stack development và thỉnh thoảng edit video. Màn hình 4K OLED quá đẹp, code nhìn rất sướng mắt. Hiệu năng xử lý đa nhiệm mượt mà, build Docker, chạy multiple VMs không lag. Pin dùng được cả ngày làm việc nếu không bật 4K.",
      "pros": [
        "Màn hình xuất sắc",
        "Build quality cao cấp",
        "Hiệu năng mạnh"
      ],
      "cons": [
        "Hơi nóng khi render video",
        "Giá cao"
      ],
      "date": "2024-01-15"
    }
  },
  {
    "id": "review_002",
    "text": "Review: Pin trâu, gọn nhẹ, hoàn hảo cho di chuyển\nĐánh giá: 5/5\nNội dung: Chuyển từ Windows sang Mac để code iOS app. Ban đầu hơi khó quen nhưng giờ thì không thể rời. Pin dùng code cả ngày 10-12 tiếng vẫn còn 20-30%. Máy không có quạt nên yên tĩnh tuyệt đối, code ở quán cafe không lo ồn. M2 chip xử lý compile Xcode rất nhanh. Chỉ tiếc RAM 8GB hơi ít khi mở nhiều app.\nƯu điểm: Pin cực trâu, Yên tĩnh hoàn toàn, Mỏng nhẹ, Màn hình đẹp\nNhược điểm: RAM không nâng cấp được, Ít cổng kết nối",
    "metadata": {
      "type": "review",
      "product_id": "laptop_002",
      "rating": 5,
      "helpful_count": 67,
      "verified_purchase": true,
      "id": "review_002",
      "user_name": "Trần Thị B",
      "title": "Pin trâu, gọn nhẹ, hoàn hảo cho di chuyển",
      "content": "Chuyển từ Windows sang Mac để code iOS app. Ban đầu hơi khó quen nhưng giờ thì không thể rời. Pin dùng code cả ngày 10-12 tiếng vẫn còn 20-30%. Máy không có quạt nên yên tĩnh tuyệt đối, code ở quán cafe không lo ồn. M2 chip xử lý compile Xcode rất nhanh. Chỉ tiếc RAM 8GB hơi ít khi mở nhiều app.",
      "pros": [
        "Pin cực trâu",
        "Yên tĩnh hoàn toàn",
        "Mỏng nhẹ",
        "Màn hình đẹp"
      ],
      "cons": [
        "RAM không nâng cấp được",
        "Ít cổng kết nối"
      ],
      "date": "2024-02-20"
    }
  },
  {
    "id": "review_003",
    "text": "Review: Gaming laptop mạnh mẽ, tản nhiệt tốt\nĐánh giá: 4/5\nNội dung: Mua ROG Strix G15 chủ yếu để gaming và thỉnh thoảng render 3D. Chơi Cyberpunk 2077 ở Ultra settings được 60-70 fps, nhiệt độ kiểm soát tốt nhờ liquid metal. Màn hình 300Hz mượt kinh khủng cho FPS games. Loa Dolby Atmos ấn tượng. Trừ điểm cho pin yếu (3-4 tiếng office work) và máy hơi nặng.\nƯu điểm: Hiệu năng gaming mạnh, Màn hình 300Hz, Tản nhiệt hiệu quả, Nâng cấp dễ\nNhược điểm: Pin yếu, Nặng, Ồn khi gaming",
    "metadata": {
      "type": "review",
      "product_id": "laptop_003",
      "rating": 4,
      "helpful_count": 34,
      "verified_purchase": true,
      "id": "review_003",
      "user_name": "Lê Văn C",
      "title": "Gaming laptop mạnh mẽ, tản nhiệt tốt",
      "content": "Mua ROG Strix G15 chủ yếu để gaming và thỉnh thoảng render 3D. Chơi Cyberpunk 2077 ở Ultra settings được 60-70 fps, nhiệt độ kiểm soát tốt nhờ liquid metal. Màn hình 300Hz mượt kinh khủng cho FPS games. Loa Dolby Atmos ấn tượng. Trừ điểm cho pin yếu (3-4 tiếng office work) và máy hơi nặng.",
      "pros": [
        "Hiệu năng gaming mạnh",
        "Màn hình 300Hz",
        "Tản nhiệt hiệu quả",
        "Nâng cấp dễ"
      ],
      "cons": [
        "Pin yếu",
        "Nặng",
        "Ồn khi gaming"
      ],
      "date": "2024-01-28"
    }
  },
  {
    "id": "review_004",
    "text": "Review: Camera zoom 5x ấn tượng, pin dùng cả ngày\nĐánh giá: 5/5\nNội dung: Nâng cấp từ iPhone 13 Pro lên 15 Pro Max. Camera zoom 5x thực sự ấn tượng, chụp xa vẫn net căng. ProRAW cho phép edit ảnh chuyên nghiệp. Action Button custom được rất tiện, mình set để bật camera nhanh. Pin dùng thoải mái cả ngày. Khung Titanium nhẹ hơn thép nhưng vẫn chắc chắn. Dynamic Island đã quen thì rất tiện.\nƯu điểm: Camera zoom 5x xuất sắc, Pin trâu, Khung titan nhẹ, Hiệu năng đỉnh\nNhược điểm: Giá cao, To và nặng, Sạc chậm",
    "metadata": {
      "type": "review",
      "product_id": "phone_001",
      "rating": 5,
      "helpful_count": 89,
      "verified_purchase": true,
      "id": "review_004",
      "user_name": "Phạm Thị D",
      "title": "Camera zoom 5x ấn tượng, pin dùng cả ngày",
      "content": "Nâng cấp từ iPhone 13 Pro lên 15 Pro Max. Camera zoom 5x thực sự ấn tượng, chụp xa vẫn net căng. ProRAW cho phép edit ảnh chuyên nghiệp. Action Button custom được rất tiện, mình set để bật camera nhanh. Pin dùng thoải mái cả ngày. Khung Titanium nhẹ hơn thép nhưng vẫn chắc chắn. Dynamic Island đã quen thì rất tiện.",
      "pros": [
        "Camera zoom 5x xuất sắc",
        "Pin trâu",
        "Khung titan nhẹ",
        "Hiệu năng đỉnh"
      ],
      "cons": [
        "Giá cao",
        "To và nặng",
        "Sạc chậm"
      ],
      "date": "2024-03-01"
    }
  },
  {
    "id": "review_005",
    "text": "Review: Android flagship mạnh nhất, S Pen hữu ích\nĐánh giá: 4/5\nNội dung: S24 Ultra là chiếc Android hoàn hảo nhất mình từng dùng. Màn hình 2K siêu sáng, ngoài trời nắng vẫn nhìn rõ. Camera 200MP chụp chi tiết kinh khủng, zoom 10x vẫn dùng được. S Pen tiện cho note-taking và ký tài liệu. Galaxy AI features như Circle to Search, Live Translate rất hữu ích. Mỗi tội máy hơi nóng khi quay 8K và pin không ấn tượng lắm.\nƯu điểm: Màn hình sáng nhất, Camera 200MP, S Pen, Galaxy AI\nNhược điểm: Nóng khi dùng nặng, Pin tụt nhanh, Nặng",
    "metadata": {
      "type": "review",
      "product_id": "phone_002",
      "rating": 4,
      "helpful_count": 76,
      "verified_purchase": true,
      "id": "review_005",
      "user_name": "Nguyễn Văn E",
      "title": "Android flagship mạnh nhất, S Pen hữu ích",
      "content": "S24 Ultra là chiếc Android hoàn hảo nhất mình từng dùng. Màn hình 2K siêu sáng, ngoài trời nắng vẫn nhìn rõ. Camera 200MP chụp chi tiết kinh khủng, zoom 10x vẫn dùng được. S Pen tiện cho note-taking và ký tài liệu. Galaxy AI features như Circle to Search, Live Translate rất hữu ích. Mỗi tội máy hơi nóng khi quay 8K và pin không ấn tượng lắm.",
      "pros": [
        "Màn hình sáng nhất",
        "Camera 200MP",
        "S Pen",
        "Galaxy AI"
      ],
      "cons": [
        "Nóng khi dùng nặng",
        "Pin tụt nhanh",
        "Nặng"
      ],
      "date": "2024-02-15"
    }
  },
  {
    "id": "review_006",
    "text": "Review: Flagship giá tốt, camera Leica không thể chê\nĐánh giá: 5/5\nNội dung: Xiaomi 14 là chiếc flagship compact hiếm hoi còn sót lại. Camera Leica chụp tone màu rất nghệ, đặc biệt portrait mode. Snapdragon 8 Gen 3 mạnh mẽ, chơi Genshin max setting mượt. Sạc 90W từ 0-100% chỉ 35 phút. HyperOS mượt hơn MIUI nhiều. Size 6.36 inch cầm rất vừa tay. Chỉ tiếc pin hơi nhỏ so với flagship khác.\nƯu điểm: Size nhỏ gọn, Camera Leica xuất sắc, Sạc siêu nhanh, Giá tốt\nNhược điểm: Pin nhỏ, Không có jack 3.5mm",
    "metadata": {
      "type": "review",
      "product_id": "phone_003",
      "rating": 5,
      "helpful_count": 54,
      "verified_purchase": true,
      "id": "review_006",
      "user_name": "Trần Văn F",
      "title": "Flagship giá tốt, camera Leica không thể chê",
      "content": "Xiaomi 14 là chiếc flagship compact hiếm hoi còn sót lại. Camera Leica chụp tone màu rất nghệ, đặc biệt portrait mode. Snapdragon 8 Gen 3 mạnh mẽ, chơi Genshin max setting mượt. Sạc 90W từ 0-100% chỉ 35 phút. HyperOS mượt hơn MIUI nhiều. Size 6.36 inch cầm rất vừa tay. Chỉ tiếc pin hơi nhỏ so với flagship khác.",
      "pros": [
        "Size nhỏ gọn",
        "Camera Leica xuất sắc",
        "Sạc siêu nhanh",
        "Giá tốt"
      ],
      "cons": [
        "Pin nhỏ",
        "Không có jack 3.5mm"
      ],
      "date": "2024-03-10"
    }
  },
  {
    "id": "review_007",
    "text": "Review: Laptop doanh nhân hoàn hảo, bàn phím đỉnh\nĐánh giá: 5/5\nNội dung: ThinkPad X1 Carbon là laptop doanh nhân tốt nhất mình từng dùng. Bàn phím gõ cực phê, travel key sâu, feedback rõ ràng. Máy siêu nhẹ 1.12kg nhưng vẫn đạt chuẩn quân đội, va đập thoải mái. Pin dùng cả ngày họp và làm việc. Màn hình anti-glare nhìn không mỏi mắt. TrackPoint đã quen thì nghiện. Mỗi tội giá hơi chát.\nƯu điểm: Bàn phím tốt nhất, Siêu nhẹ và bền, Pin lâu, Bảo mật tốt\nNhược điểm: Giá cao, Thiết kế cũ, GPU yếu",
    "metadata": {
      "type": "review",
      "product_id": "laptop_004",
      "rating": 5,
      "helpful_count": 43,
      "verified_purchase": true,
      "id": "review_007",
      "user_name": "Hoàng Thị G",
      "title": "Laptop doanh nhân hoàn hảo, bàn phím đỉnh",
      "content": "ThinkPad X1 Carbon là laptop doanh nhân tốt nhất mình từng dùng. Bàn phím gõ cực phê, travel key sâu, feedback rõ ràng. Máy siêu nhẹ 1.12kg nhưng vẫn đạt chuẩn quân đội, va đập thoải mái. Pin dùng cả ngày họp và làm việc. Màn hình anti-glare nhìn không mỏi mắt. TrackPoint đã quen thì nghiện. Mỗi tội giá hơi chát.",
      "pros": [
        "Bàn phím tốt nhất",
        "Siêu nhẹ và bền",
        "Pin lâu",
        "Bảo mật tốt"
      ],
      "cons": [
        "Giá cao",
        "Thiết kế cũ",
        "GPU yếu"
      ],
      "date": "2024-02-25"
    }
  },
  {
    "id": "review_008",
    "text": "Review: Mid-range tốt nhất của Samsung\nĐánh giá: 4/5\nNội dung: A54 5G là chiếc mid-range đáng mua nhất của Samsung. Thiết kế giống flagship, màn hình AMOLED 120Hz mượt. Camera 50MP OIS chụp đêm tốt trong tầm giá. Pin 5000mAh dùng thoải mái cả ngày. IP67 là điểm cộng lớn, không lo mưa hay rơi nước. 4 năm update OS là cam kết tốt. Chỉ tiếc chip Exynos không mạnh và sạc 25W hơi chậm.\nƯu điểm: Thiết kế đẹp, Màn hình tốt, IP67, Support lâu dài\nNhược điểm: Chip yếu, Sạc chậm, Camera macro vô dụng",
    "metadata": {
      "type": "review",
      "product_id": "phone_007",
      "rating": 4,
      "helpful_count": 98,
      "verified_purchase": true,
      "id": "review_008",
      "user_name": "Lý Văn H",
      "title": "Mid-range tốt nhất của Samsung",
      "content": "A54 5G là chiếc mid-range đáng mua nhất của Samsung. Thiết kế giống flagship, màn hình AMOLED 120Hz mượt. Camera 50MP OIS chụp đêm tốt trong tầm giá. Pin 5000mAh dùng thoải mái cả ngày. IP67 là điểm cộng lớn, không lo mưa hay rơi nước. 4 năm update OS là cam kết tốt. Chỉ tiếc chip Exynos không mạnh và sạc 25W hơi chậm.",
      "pros": [
        "Thiết kế đẹp",
        "Màn hình tốt",
        "IP67",
        "Support lâu dài"
      ],
      "cons": [
        "Chip yếu",
        "Sạc chậm",
        "Camera macro vô dụng"
      ],
      "date": "2024-03-05"
    }
  },
  {
    "id": "review_009",
    "text": "Review: Camera 200MP ấn tượng, sạc 120W quá nhanh\nĐánh giá: 4/5\nNội dung: Redmi Note 13 Pro+ làm mình bất ngờ về camera 200MP, chụp ban ngày chi tiết kinh khủng, crop zoom vẫn rõ. Sạc 120W từ 0-100% chỉ 19 phút là điên rồ. RAM 12GB mượt mà đa nhiệm. Màn hình cong 1.5K sắc nét. MIUI 14 vẫn còn ads nhưng tắt được. Chip MediaTek chơi game nặng hơi nóng. Tổng thể rất đáng tiền trong tầm giá.\nƯu điểm: Camera 200MP, Sạc 120W siêu nhanh, RAM 12GB, Màn hình đẹp\nNhược điểm: MIUI ads, Chip MediaTek nóng, Chỉ IP54",
    "metadata": {
      "type": "review",
      "product_id": "phone_008",
      "rating": 4,
      "helpful_count": 67,
      "verified_purchase": true,
      "id": "review_009",
      "user_name": "Võ Thị I",
      "title": "Camera 200MP ấn tượng, sạc 120W quá nhanh",
      "content": "Redmi Note 13 Pro+ làm mình bất ngờ về camera 200MP, chụp ban ngày chi tiết kinh khủng, crop zoom vẫn rõ. Sạc 120W từ 0-100% chỉ 19 phút là điên rồ. RAM 12GB mượt mà đa nhiệm. Màn hình cong 1.5K sắc nét. MIUI 14 vẫn còn ads nhưng tắt được. Chip MediaTek chơi game nặng hơi nóng. Tổng thể rất đáng tiền trong tầm giá.",
      "pros": [
        "Camera 200MP",
        "Sạc 120W siêu nhanh",
        "RAM 12GB",
        "Màn hình đẹp"
      ],
      "cons": [
        "MIUI ads",
        "Chip MediaTek nóng",
        "Chỉ IP54"
      ],
      "date": "2024-03-12"
    }
  },
  {
    "id": "review_010",
    "text": "Review: Laptop sinh viên giá tốt, đủ dùng\nĐánh giá: 4/5\nNội dung: HP Pavilion 15 là lựa chọn ổn cho sinh viên. Core i5 gen 12 đủ sức cho code, office, và giải trí nhẹ. SSD 512GB thoải mái lưu trữ. Màn hình IPS Full HD ok, chỉ hơi tối. Thiết kế đẹp trong tầm giá. Nâng cấp RAM và SSD dễ dàng. Pin dùng được 6-7 tiếng làm việc nhẹ. Loa B&O nghe nhạc tạm ổn. Giá dưới 20 triệu là hợp lý.\nƯu điểm: Giá tốt, Cấu hình ổn, Thiết kế đẹp, Nâng cấp dễ\nNhược điểm: Màn hình tối, Pin trung bình, Vỏ nhựa",
    "metadata": {
      "type": "review",
      "product_id": "laptop_005",
      "rating": 4,
      "helpful_count": 123,
      "verified_purchase": true,
      "id": "review_010",
      "user_name": "Đặng Văn K",
      "title": "Laptop sinh viên giá tốt, đủ dùng",
      "content": "HP Pavilion 15 là lựa chọn ổn cho sinh viên. Core i5 gen 12 đủ sức cho code, office, và giải trí nhẹ. SSD 512GB thoải mái lưu trữ. Màn hình IPS Full HD ok, chỉ hơi tối. Thiết kế đẹp trong tầm giá. Nâng cấp RAM và SSD dễ dàng. Pin dùng được 6-7 tiếng làm việc nhẹ. Loa B&O nghe nhạc tạm ổn. Giá dưới 20 triệu là hợp lý.",
      "pros": [
        "Giá tốt",
        "Cấu hình ổn",
        "Thiết kế đẹp",
        "Nâng cấp dễ"
      ],
      "cons": [
        "Màn hình tối",
        "Pin trung bình",
        "Vỏ nhựa"
      ],
      "date": "2024-02-18"
    }
  },
  {
    "id": "review_011",
    "text": "Review: Điện thoại tốt - Camera ấn tượng\nĐánh giá: 5/5\nNội dung: Nâng cấp từ Xiaomi 11 lên iPhone 15 Pro Max. Camera chụp ảnh rất đẹp, màu sắc tự nhiên Nhiệt độ kiểm soát tốt Sạc nhanh, tiện lợi Sẽ tiếp tục dùng brand này\nƯu điểm: Camera ấn tượng, Pin tốt, Hiệu năng ổn định\nNhược điểm: Giá hơi đắt, To và nặng, Cáp sạc ngắn",
    "metadata": {
      "type": "review",
      "product_id": "phone_001",
      "rating": 5,
      "helpful_count": 73,
      "verified_purchase": true,
      "id": "review_011",
      "user_name": "Chu Thị S",
      "title": "Điện thoại tốt - Camera ấn tượng",
      "content": "Nâng cấp từ Xiaomi 11 lên iPhone 15 Pro Max. Camera chụp ảnh rất đẹp, màu sắc tự nhiên Nhiệt độ kiểm soát tốt Sạc nhanh, tiện lợi Sẽ tiếp tục dùng brand này",
      "pros": [
        "Camera ấn tượng",
        "Pin tốt",
        "Hiệu năng ổn định"
      ],
      "cons": [
        "Giá hơi đắt",
        "To và nặng",
        "Cáp sạc ngắn"
      ],
      "date": "2025-05-24"
    }
  },
  {
    "id": "review_012",
    "text": "Review: Điện thoại xuất sắc - Camera xuất sắc\nĐánh giá: 5/5\nNội dung: Nâng cấp từ iPhone 14 lên iPhone 15 Pro Max. Portrait mode và night mode ấn tượng Đa nhiệm mượt, chuyển app nhanh Sạc nhanh, tiện lợi Tổng thể rất hài lòng\nƯu điểm: Camera xuất sắc, Pin ổn, Hiệu năng ổn định\nNhược điểm: Giá hơi đắt, Hơi dày, Không có sạc không dây",
    "metadata": {
      "type": "review",
      "product_id": "phone_001",
      "rating": 5,
      "helpful_count": 29,
      "verified_purchase": true,
      "id": "review_012",
      "user_name": "Đặng Văn G",
      "title": "Điện thoại xuất sắc - Camera xuất sắc",
      "content": "Nâng cấp từ iPhone 14 lên iPhone 15 Pro Max. Portrait mode và night mode ấn tượng Đa nhiệm mượt, chuyển app nhanh Sạc nhanh, tiện lợi Tổng thể rất hài lòng",
      "pros": [
        "Camera xuất sắc",
        "Pin ổn",
        "Hiệu năng ổn định"
      ],
      "cons": [
        "Giá hơi đắt",
        "Hơi dày",
        "Không có sạc không dây"
      ],
      "date": "2025-04-12"
    }
  },
  {
    "id": "review_013",
    "text": "Review: Điện thoại xuất sắc - Camera tốt\nĐánh giá: 4/5\nNội dung: Nâng cấp từ Samsung 14 lên Samsung Galaxy S24 Ultra. Video quay mượt, chống rung tốt Nhiệt độ kiểm soát tốt Pin hơi yếu khi dùng nhiều Nâng cấp đáng giá\nƯu điểm: Camera tốt, Pin ổn, Hiệu năng mạnh\nNhược điểm: Giá cao, To và nặng, Cáp sạc ngắn",
    "metadata": {
      "type": "review",
      "product_id": "phone_002",
      "rating": 4,
      "helpful_count": 90,
      "verified_purchase": true,
      "id": "review_013",
      "user_name": "Dương Văn I",
      "title": "Điện thoại xuất sắc - Camera tốt",
      "content": "Nâng cấp từ Samsung 14 lên Samsung Galaxy S24 Ultra. Video quay mượt, chống rung tốt Nhiệt độ kiểm soát tốt Pin hơi yếu khi dùng nhiều Nâng cấp đáng giá",
      "pros": [
        "Camera tốt",
        "Pin ổn",
        "Hiệu năng mạnh"
      ],
      "cons": [
        "Giá cao",
        "To và nặng",
        "Cáp sạc ngắn"
      ],
      "date": "2025-06-18"
    }
  },
  {
    "id": "review_014",
    "text": "Review: Điện thoại ấn tượng - Camera chất lượng\nĐánh giá: 5/5\nNội dung: Nâng cấp từ iPhone 14 lên iPhone 15 Pro Max. Zoom xa vẫn net, chụp đêm ổn Hiệu năng mượt mà, không lag Sạc nhanh, tiện lợi Sẽ tiếp tục dùng brand này\nƯu điểm: Camera chất lượng, Pin tốt, Hiệu năng mượt\nNhược điểm: Giá hơi đắt, To và nặng, Không có sạc không dây",
    "metadata": {
      "type": "review",
      "product_id": "phone_001",
      "rating": 5,
      "helpful_count": 21,
      "verified_purchase": true,
      "id": "review_014",
      "user_name": "Mai Thị Q",
      "title": "Điện thoại ấn tượng - Camera chất lượng",
      "content": "Nâng cấp từ iPhone 14 lên iPhone 15 Pro Max. Zoom xa vẫn net, chụp đêm ổn Hiệu năng mượt mà, không lag Sạc nhanh, tiện lợi Sẽ tiếp tục dùng brand này",
      "pros": [
        "Camera chất lượng",
        "Pin tốt",
        "Hiệu năng mượt"
      ],
      "cons": [
        "Giá hơi đắt",
        "To và nặng",
        "Không có sạc không dây"
      ],
      "date": "2025-05-01"
    }
  },
  {
    "id": "review_015",
    "text": "Review: Điện thoại ấn tượng - Camera tốt\nĐánh giá: 5/5\nNội dung: Nâng cấp từ Xiaomi 14 lên Samsung Galaxy S24 Ultra. Camera chụp ảnh rất đẹp, màu sắc tự nhiên Chơi game nặng vẫn ổn định Pin hơi yếu khi dùng nhiều Sẽ tiếp tục dùng brand này\nƯu điểm: Camera tốt, Pin dài, Hiệu năng mạnh\nNhược điểm: Giá hơi đắt, Hơi dày, Sạc chậm",
    "metadata": {
      "type": "review",
      "product_id": "phone_002",
      "rating": 5,
      "helpful_count": 0,
      "verified_purchase": false,
      "id": "review_015",
      "user_name": "Lý Thị K",
      "title": "Điện thoại ấn tượng - Camera tốt",
      "content": "Nâng cấp từ Xiaomi 14 lên Samsung Galaxy S24 Ultra. Camera chụp ảnh rất đẹp, màu sắc tự nhiên Chơi game nặng vẫn ổn định Pin hơi yếu khi dùng nhiều Sẽ tiếp tục dùng brand này",
      "pros": [
        "Camera tốt",
        "Pin dài",
        "Hiệu năng mạnh"
      ],
      "cons": [
        "Giá hơi đắt",
        "Hơi dày",
        "Sạc chậm"
      ],
      "date": "2025-04-20"
    }
  },
  {
    "id": "review_016",
    "text": "Review: Laptop tuyệt vời cho lập trình\nĐánh giá: 4/5\nNội dung: Mình dùng laptop này được 3 tháng cho lập trình. Chạy các phần mềm nặng không lag Độ sáng tốt, làm việc ngoài trời OK Pin hơi yếu khi gaming Bàn phím gõ thoải mái\nƯu điểm: Hiệu năng tốt, Màn hình tuyệt vời, Pin ổn\nNhược điểm: Hơi dày, nóng máy, Giá đắt",
    "metadata": {
      "type": "review",
      "product_id": "laptop_004",
      "rating": 4,
      "helpful_count": 44,
      "verified_purchase": true,
      "id": "review_016",
      "user_name": "Võ Thị O",
      "title": "Laptop tuyệt vời cho lập trình",
      "content": "Mình dùng laptop này được 3 tháng cho lập trình. Chạy các phần mềm nặng không lag Độ sáng tốt, làm việc ngoài trời OK Pin hơi yếu khi gaming Bàn phím gõ thoải mái",
      "pros": [
        "Hiệu năng tốt",
        "Màn hình tuyệt vời",
        "Pin ổn"
      ],
      "cons": [
        "Hơi dày",
        "nóng máy",
        "Giá đắt"
      ],
      "date": "2025-07-14"
    }
  },
  {
    "id": "review_017",
    "text": "Review: Laptop tuyệt vời cho gaming\nĐánh giá: 3/5\nNội dung: Mình dùng laptop này được 8 tháng cho gaming. Hiệu năng xử lý đa nhiệm mượt mà Góc nhìn rộng, không bị lóa Thời lượng pin khá ổn Touchpad responsive\nƯu điểm: Hiệu năng tốt, Màn hình sắc nét, Pin tốt\nNhược điểm: Hơi to, ấm khi render, Giá không rẻ",
    "metadata": {
      "type": "review",
      "product_id": "laptop_004",
      "rating": 3,
      "helpful_count": 22,
      "verified_purchase": false,
      "id": "review_017",
      "user_name": "Võ Thị O",
      "title": "Laptop tuyệt vời cho gaming",
      "content": "Mình dùng laptop này được 8 tháng cho gaming. Hiệu năng xử lý đa nhiệm mượt mà Góc nhìn rộng, không bị lóa Thời lượng pin khá ổn Touchpad responsive",
      "pros": [
        "Hiệu năng tốt",
        "Màn hình sắc nét",
        "Pin tốt"
      ],
      "cons": [
        "Hơi to",
        "ấm khi render",
        "Giá không rẻ"
      ],
      "date": "2025-05-13"
    }
  },
  {
    "id": "review_018",
    "text": "Review: Điện thoại tốt - Camera đẹp\nĐánh giá: 5/5\nNội dung: Nâng cấp từ iPhone 12 lên Xiaomi Redmi Note 13 Pro+ 5G. Video quay mượt, chống rung tốt Nhiệt độ kiểm soát tốt Wireless charging tiện Nâng cấp đáng giá\nƯu điểm: Camera đẹp, Pin dài, Hiệu năng ổn định\nNhược điểm: Giá cao, Hơi dày, Sạc chậm",
    "metadata": {
      "type": "review",
      "product_id": "phone_008",
      "rating": 5,
      "helpful_count": 36,
      "verified_purchase": true,
      "id": "review_018",
      "user_name": "Đặng Văn G",
      "title": "Điện thoại tốt - Camera đẹp",
      "content": "Nâng cấp từ iPhone 12 lên Xiaomi Redmi Note 13 Pro+ 5G. Video quay mượt, chống rung tốt Nhiệt độ kiểm soát tốt Wireless charging tiện Nâng cấp đáng giá",
      "pros": [
        "Camera đẹp",
        "Pin dài",
        "Hiệu năng ổn định"
      ],
      "cons": [
        "Giá cao",
        "Hơi dày",
        "Sạc chậm"
      ],
      "date": "2025-07-18"
    }
  },
  {
    "id": "review_019",
    "text": "Review: Điện thoại hài lòng - Camera xuất sắc\nĐánh giá: 5/5\nNội dung: Nâng cấp từ Samsung 12 lên Samsung Galaxy S24 Ultra. Portrait mode và night mode ấn tượng Đa nhiệm mượt, chuyển app nhanh Wireless charging tiện Đáng tiền, recommend\nƯu điểm: Camera xuất sắc, Pin tốt, Hiệu năng ổn định\nNhược điểm: Giá hơi đắt, To và nặng, Không có sạc không dây",
    "metadata": {
      "type": "review",
      "product_id": "phone_002",
      "rating": 5,
      "helpful_count": 48,
      "verified_purchase": false,
      "id": "review_019",
      "user_name": "Ngô Văn L",
      "title": "Điện thoại hài lòng - Camera xuất sắc",
      "content": "Nâng cấp từ Samsung 12 lên Samsung Galaxy S24 Ultra. Portrait mode và night mode ấn tượng Đa nhiệm mượt, chuyển app nhanh Wireless charging tiện Đáng tiền, recommend",
      "pros": [
        "Camera xuất sắc",
        "Pin tốt",
        "Hiệu năng ổn định"
      ],
      "cons": [
        "Giá hơi đắt",
        "To và nặng",
        "Không có sạc không dây"
      ],
      "date": "2025-07-10"
    }
  },
  {
    "id": "review_020",
    "text": "Review: Điện thoại tuyệt vời - Camera xuất sắc\nĐánh giá: 5/5\nNội dung: Nâng cấp từ Samsung 14 lên Samsung Galaxy A54 5G. Portrait mode và night mode ấn tượng Nhiệt độ kiểm soát tốt Pin hơi yếu khi dùng nhiều Nâng cấp đáng giá\nƯu điểm: Camera xuất sắc, Pin dài, Hiệu năng mạnh\nNhược điểm: Giá đắt, Hơi dày, Cáp sạc ngắn",
    "metadata": {
      "type": "review",
      "product_id": "phone_007",
      "rating": 5,
      "helpful_count": 90,
      "verified_purchase": true,
      "id": "review_020",
      "user_name": "Bùi Thị H",
      "title": "Điện thoại tuyệt vời - Camera xuất sắc",
      "content": "Nâng cấp từ Samsung 14 lên Samsung Galaxy A54 5G. Portrait mode và night mode ấn tượng Nhiệt độ kiểm soát tốt Pin hơi yếu khi dùng nhiều Nâng cấp đáng giá",
      "pros": [
        "Camera xuất sắc",
        "Pin dài",
        "Hiệu năng mạnh"
      ],
      "cons": [
        "Giá đắt",
        "Hơi dày",
        "Cáp sạc ngắn"
      ],
      "date": "2025-04-14"
    }
  },
  {
    "id": "review_021",
    "text": "Review: Laptop tuyệt vời cho văn phòng\nĐánh giá: 4/5\nNội dung: Mình dùng laptop này được 12 tháng cho văn phòng. Hiệu năng xử lý đa nhiệm mượt mà Màn hình hiển thị rất đẹp Pin hơi yếu khi gaming Touchpad responsive\nƯu điểm: Hiệu năng mạnh mẽ, Màn hình đẹp, Pin tốt\nNhược điểm: Hơi to, nóng khi gaming, Giá đắt",
    "metadata": {
      "type": "review",
      "product_id": "laptop_006",
      "rating": 4,
      "helpful_count": 99,
      "verified_purchase": true,
      "id": "review_021",
      "user_name": "Ngô Văn L",
      "title": "Laptop tuyệt vời cho văn phòng",
      "content": "Mình dùng laptop này được 12 tháng cho văn phòng. Hiệu năng xử lý đa nhiệm mượt mà Màn hình hiển thị rất đẹp Pin hơi yếu khi gaming Touchpad responsive",
      "pros": [
        "Hiệu năng mạnh mẽ",
        "Màn hình đẹp",
        "Pin tốt"
      ],
      "cons": [
        "Hơi to",
        "nóng khi gaming",
        "Giá đắt"
      ],
      "date": "2025-07-25"
    }
  },
  {
    "id": "review_022",
    "text": "Review: Điện thoại ấn tượng - Camera ấn tượng\nĐánh giá: 3/5\nNội dung: Nâng cấp từ Samsung 12 lên Realme 11 Pro+. Camera chụp ảnh rất đẹp, màu sắc tự nhiên Chơi game nặng vẫn ổn định Wireless charging tiện Đáng tiền, recommend\nƯu điểm: Camera ấn tượng, Pin dài, Hiệu năng ổn định\nNhược điểm: Giá đắt, Hơi dày, Không có sạc không dây",
    "metadata": {
      "type": "review",
      "product_id": "phone_010",
      "rating": 3,
      "helpful_count": 97,
      "verified_purchase": false,
      "id": "review_022",
      "user_name": "Ngô Văn L",
      "title": "Điện thoại ấn tượng - Camera ấn tượng",
      "content": "Nâng cấp từ Samsung 12 lên Realme 11 Pro+. Camera chụp ảnh rất đẹp, màu sắc tự nhiên Chơi game nặng vẫn ổn định Wireless charging tiện Đáng tiền, recommend",
      "pros": [
        "Camera ấn tượng",
        "Pin dài",
        "Hiệu năng ổn định"
      ],
      "cons": [
        "Giá đắt",
        "Hơi dày",
        "Không có sạc không dây"
      ],
      "date": "2025-06-17"
    }
  },
  {
    "id": "review_023",
    "text": "Review: Điện thoại tuyệt vời - Camera ấn tượng\nĐánh giá: 5/5\nNội dung: Nâng cấp từ Xiaomi 12 lên Xiaomi 14. Zoom xa vẫn net, chụp đêm ổn Chơi game nặng vẫn ổn định Pin hơi yếu khi dùng nhiều Sẽ tiếp tục dùng brand này\nƯu điểm: Camera ấn tượng, Pin trâu, Hiệu năng mạnh\nNhược điểm: Giá hơi đắt, To và nặng, Không có sạc không dây",
    "metadata": {
      "type": "review",
      "product_id": "phone_003",
      "rating": 5,
      "helpful_count": 67,
      "verified_purchase": false,
      "id": "review_023",
      "user_name": "Đỗ Thị M",
      "title": "Điện thoại tuyệt vời - Camera ấn tượng",
      "content": "Nâng cấp từ Xiaomi 12 lên Xiaomi 14. Zoom xa vẫn net, chụp đêm ổn Chơi game nặng vẫn ổn định Pin hơi yếu khi dùng nhiều Sẽ tiếp tục dùng brand này",
      "pros": [
        "Camera ấn tượng",
        "Pin trâu",
        "Hiệu năng mạnh"
      ],
      "cons": [
        "Giá hơi đắt",
        "To và nặng",
        "Không có sạc không dây"
      ],
      "date": "2025-06-02"
    }
  },
  {
    "id": "review_024",
    "text": "Review: Điện thoại ấn tượng - Camera chất lượng\nĐánh giá: 5/5\nNội dung: Nâng cấp từ Xiaomi 13 lên Xiaomi 14. Camera chụp ảnh rất đẹp, màu sắc tự nhiên Đa nhiệm mượt, chuyển app nhanh Wireless charging tiện Đáng tiền, recommend\nƯu điểm: Camera chất lượng, Pin ổn, Hiệu năng ổn định\nNhược điểm: Giá đắt, Khó cầm một tay, Không có sạc không dây",
    "metadata": {
      "type": "review",
      "product_id": "phone_003",
      "rating": 5,
      "helpful_count": 63,
      "verified_purchase": true,
      "id": "review_024",
      "user_name": "Chu Thị S",
      "title": "Điện thoại ấn tượng - Camera chất lượng",
      "content": "Nâng cấp từ Xiaomi 13 lên Xiaomi 14. Camera chụp ảnh rất đẹp, màu sắc tự nhiên Đa nhiệm mượt, chuyển app nhanh Wireless charging tiện Đáng tiền, recommend",
      "pros": [
        "Camera chất lượng",
        "Pin ổn",
        "Hiệu năng ổn định"
      ],
      "cons": [
        "Giá đắt",
        "Khó cầm một tay",
        "Không có sạc không dây"
      ],
      "date": "2025-03-29"
    }
  },
  {
    "id": "review_025",
    "text": "Review: Điện thoại tốt - Camera đẹp\nĐánh giá: 5/5\nNội dung: Nâng cấp từ Samsung 14 lên Samsung Galaxy A54 5G. Video quay mượt, chống rung tốt Đa nhiệm mượt, chuyển app nhanh Wireless charging tiện Sẽ tiếp tục dùng brand này\nƯu điểm: Camera đẹp, Pin tốt, Hiệu năng mượt\nNhược điểm: Giá hơi đắt, To và nặng, Sạc chậm",
    "metadata": {
      "type": "review",
      "product_id": "phone_007",
      "rating": 5,
      "helpful_count": 97,
      "verified_purchase": true,
      "id": "review_025",
      "user_name": "Nguyễn Văn A",
      "title": "Điện thoại tốt - Camera đẹp",
      "content": "Nâng cấp từ Samsung 14 lên Samsung Galaxy A54 5G. Video quay mượt, chống rung tốt Đa nhiệm mượt, chuyển app nhanh Wireless charging tiện Sẽ tiếp tục dùng brand này",
      "pros": [
        "Camera đẹp",
        "Pin tốt",
        "Hiệu năng mượt"
      ],
      "cons": [
        "Giá hơi đắt",
        "To và nặng",
        "Sạc chậm"
      ],
      "date": "2025-08-16"
    }
  },
  {
    "id": "review_026",
    "text": "Review: Lenovo hài lòng - Màn hình đẹp\nĐánh giá: 5/5\nNội dung: Chuyển từ HP sang Lenovo. Cải thiện rõ rệt so với máy cũ Học tập và nghiên cứu Đáng tiền bỏ ra Đáng để đầu tư\nƯu điểm: Màn hình đẹp, Thiết kế sang trọng, Cổng kết nối đầy đủ\nNhược điểm: RAM không nâng cấp được, Không có card reader, Dễ bám vân tay",
    "metadata": {
      "type": "review",
      "product_id": "laptop_004",
      "rating": 5,
      "helpful_count": 19,
      "verified_purchase": false,
      "id": "review_026",
      "user_name": "Phan Văn P",
      "title": "Lenovo hài lòng - Màn hình đẹp",
      "content": "Chuyển từ HP sang Lenovo. Cải thiện rõ rệt so với máy cũ Học tập và nghiên cứu Đáng tiền bỏ ra Đáng để đầu tư",
      "pros": [
        "Màn hình đẹp",
        "Thiết kế sang trọng",
        "Cổng kết nối đầy đủ"
      ],
      "cons": [
        "RAM không nâng cấp được",
        "Không có card reader",
        "Dễ bám vân tay"
      ],
      "date": "2025-07-12"
    }
  },
  {
    "id": "review_027",
    "text": "Review: Điện thoại ấn tượng - Camera ấn tượng\nĐánh giá: 5/5\nNội dung: Nâng cấp từ iPhone 14 lên iPhone 15 Pro Max. Camera chụp ảnh rất đẹp, màu sắc tự nhiên Nhiệt độ kiểm soát tốt Pin dùng thoải mái cả ngày Tổng thể rất hài lòng\nƯu điểm: Camera ấn tượng, Pin trâu, Hiệu năng mạnh\nNhược điểm: Giá đắt, Hơi dày, Không có sạc không dây",
    "metadata": {
      "type": "review",
      "product_id": "phone_001",
      "rating": 5,
      "helpful_count": 60,
      "verified_purchase": true,
      "id": "review_027",
      "user_name": "Hoàng Văn E",
      "title": "Điện thoại ấn tượng - Camera ấn tượng",
      "content": "Nâng cấp từ iPhone 14 lên iPhone 15 Pro Max. Camera chụp ảnh rất đẹp, màu sắc tự nhiên Nhiệt độ kiểm soát tốt Pin dùng thoải mái cả ngày Tổng thể rất hài lòng",
      "pros": [
        "Camera ấn tượng",
        "Pin trâu",
        "Hiệu năng mạnh"
      ],
      "cons": [
        "Giá đắt",
        "Hơi dày",
        "Không có sạc không dây"
      ],
      "date": "2025-07-08"
    }
  },
  {
    "id": "review_028",
    "text": "Review: Điện thoại tuyệt vời - Camera đẹp\nĐánh giá: 5/5\nNội dung: Nâng cấp từ Samsung 13 lên Realme 11 Pro+. Video quay mượt, chống rung tốt Hiệu năng mượt mà, không lag Pin hơi yếu khi dùng nhiều Đáng tiền, recommend\nƯu điểm: Camera đẹp, Pin dài, Hiệu năng mạnh\nNhược điểm: Giá đắt, Hơi dày, Sạc chậm",
    "metadata": {
      "type": "review",
      "product_id": "phone_010",
      "rating": 5,
      "helpful_count": 99,
      "verified_purchase": true,
      "id": "review_028",
      "user_name": "Đỗ Thị M",
      "title": "Điện thoại tuyệt vời - Camera đẹp",
      "content": "Nâng cấp từ Samsung 13 lên Realme 11 Pro+. Video quay mượt, chống rung tốt Hiệu năng mượt mà, không lag Pin hơi yếu khi dùng nhiều Đáng tiền, recommend",
      "pros": [
        "Camera đẹp",
        "Pin dài",
        "Hiệu năng mạnh"
      ],
      "cons": [
        "Giá đắt",
        "Hơi dày",
        "Sạc chậm"
      ],
      "date": "2025-08-15"
    }
  },
  {
    "id": "review_029",
    "text": "Review: Laptop tuyệt vời cho văn phòng\nĐánh giá: 5/5\nNội dung: Mình dùng laptop này được 1 tháng cho văn phòng. Chạy các phần mềm nặng không lag Màn hình hiển thị rất đẹp Pin dùng được cả ngày làm việc Build quality chắc chắn\nƯu điểm: Hiệu năng tốt, Màn hình sắc nét, Pin ổn\nNhược điểm: Hơi to, ấm khi render, Giá đắt",
    "metadata": {
      "type": "review",
      "product_id": "laptop_003",
      "rating": 5,
      "helpful_count": 53,
      "verified_purchase": false,
      "id": "review_029",
      "user_name": "Đinh Thị U",
      "title": "Laptop tuyệt vời cho văn phòng",
      "content": "Mình dùng laptop này được 1 tháng cho văn phòng. Chạy các phần mềm nặng không lag Màn hình hiển thị rất đẹp Pin dùng được cả ngày làm việc Build quality chắc chắn",
      "pros": [
        "Hiệu năng tốt",
        "Màn hình sắc nét",
        "Pin ổn"
      ],
      "cons": [
        "Hơi to",
        "ấm khi render",
        "Giá đắt"
      ],
      "date": "2025-08-10"
    }
  },
  {
    "id": "review_030",
    "text": "Review: Điện thoại tốt - Camera tốt\nĐánh giá: 4/5\nNội dung: Nâng cấp từ iPhone 12 lên Xiaomi Redmi Note 13 Pro+ 5G. Video quay mượt, chống rung tốt Hiệu năng mượt mà, không lag Pin dùng thoải mái cả ngày Tổng thể rất hài lòng\nƯu điểm: Camera tốt, Pin dài, Hiệu năng ổn định\nNhược điểm: Giá hơi đắt, Hơi dày, Cáp sạc ngắn",
    "metadata": {
      "type": "review",
      "product_id": "phone_008",
      "rating": 4,
      "helpful_count": 72,
      "verified_purchase": false,
      "id": "review_030",
      "user_name": "Lý Thị K",
      "title": "Điện thoại tốt - Camera tốt",
      "content": "Nâng cấp từ iPhone 12 lên Xiaomi Redmi Note 13 Pro+ 5G. Video quay mượt, chống rung tốt Hiệu năng mượt mà, không lag Pin dùng thoải mái cả ngày Tổng thể rất hài lòng",
      "pros": [
        "Camera tốt",
        "Pin dài",
        "Hiệu năng ổn định"
      ],
      "cons": [
        "Giá hơi đắt",
        "Hơi dày",
        "Cáp sạc ngắn"
      ],
      "date": "2025-04-27"
    }
  },
  {
    "id": "review_031",
    "text": "Review: Laptop tuyệt vời cho thiết kế\nĐánh giá: 5/5\nNội dung: Mình dùng laptop này được 11 tháng cho thiết kế. Build code và compile rất nhanh Màn hình hiển thị rất đẹp Pin hơi yếu khi gaming Touchpad responsive\nƯu điểm: Hiệu năng mạnh mẽ, Màn hình tuyệt vời, Pin dài\nNhược điểm: Hơi to, ấm khi render, Giá cao",
    "metadata": {
      "type": "review",
      "product_id": "laptop_002",
      "rating": 5,
      "helpful_count": 70,
      "verified_purchase": true,
      "id": "review_031",
      "user_name": "Hồ Văn N",
      "title": "Laptop tuyệt vời cho thiết kế",
      "content": "Mình dùng laptop này được 11 tháng cho thiết kế. Build code và compile rất nhanh Màn hình hiển thị rất đẹp Pin hơi yếu khi gaming Touchpad responsive",
      "pros": [
        "Hiệu năng mạnh mẽ",
        "Màn hình tuyệt vời",
        "Pin dài"
      ],
      "cons": [
        "Hơi to",
        "ấm khi render",
        "Giá cao"
      ],
      "date": "2025-04-21"
    }
  },
  {
    "id": "review_032",
    "text": "Review: Dell hài lòng - Thiết kế đẹp\nĐánh giá: 5/5\nNội dung: Chuyển từ Dell sang Dell. Cải thiện rõ rệt so với máy cũ Học tập và nghiên cứu Đáng tiền bỏ ra Recommend cho ai cần máy tương tự\nƯu điểm: Thiết kế đẹp, Thiết kế cao cấp, Cổng kết nối đầy đủ\nNhược điểm: SSD hơi nhỏ, Không có cổng Ethernet, Webcam vị trí hơi thấp",
    "metadata": {
      "type": "review",
      "product_id": "laptop_001",
      "rating": 5,
      "helpful_count": 47,
      "verified_purchase": true,
      "id": "review_032",
      "user_name": "Chu Thị S",
      "title": "Dell hài lòng - Thiết kế đẹp",
      "content": "Chuyển từ Dell sang Dell. Cải thiện rõ rệt so với máy cũ Học tập và nghiên cứu Đáng tiền bỏ ra Recommend cho ai cần máy tương tự",
      "pros": [
        "Thiết kế đẹp",
        "Thiết kế cao cấp",
        "Cổng kết nối đầy đủ"
      ],
      "cons": [
        "SSD hơi nhỏ",
        "Không có cổng Ethernet",
        "Webcam vị trí hơi thấp"
      ],
      "date": "2025-08-01"
    }
  },
  {
    "id": "review_033",
    "text": "Review: Điện thoại tốt - Camera ấn tượng\nĐánh giá: 3/5\nNội dung: Nâng cấp từ Xiaomi 12 lên Samsung Galaxy A54 5G. Camera chụp ảnh rất đẹp, màu sắc tự nhiên Nhiệt độ kiểm soát tốt Wireless charging tiện Đáng tiền, recommend\nƯu điểm: Camera ấn tượng, Pin tốt, Hiệu năng cao\nNhược điểm: Giá hơi đắt, Hơi dày, Không có sạc không dây",
    "metadata": {
      "type": "review",
      "product_id": "phone_007",
      "rating": 3,
      "helpful_count": 14,
      "verified_purchase": true,
      "id": "review_033",
      "user_name": "Tô Văn R",
      "title": "Điện thoại tốt - Camera ấn tượng",
      "content": "Nâng cấp từ Xiaomi 12 lên Samsung Galaxy A54 5G. Camera chụp ảnh rất đẹp, màu sắc tự nhiên Nhiệt độ kiểm soát tốt Wireless charging tiện Đáng tiền, recommend",
      "pros": [
        "Camera ấn tượng",
        "Pin tốt",
        "Hiệu năng cao"
      ],
      "cons": [
        "Giá hơi đắt",
        "Hơi dày",
        "Không có sạc không dây"
      ],
      "date": "2025-03-01"
    }
  },
  {
    "id": "review_034",
    "text": "Review: Điện thoại ấn tượng - Camera xuất sắc\nĐánh giá: 5/5\nNội dung: Nâng cấp từ Xiaomi 13 lên Realme 11 Pro+. Video quay mượt, chống rung tốt Đa nhiệm mượt, chuyển app nhanh Pin dùng thoải mái cả ngày Sẽ tiếp tục dùng brand này\nƯu điểm: Camera xuất sắc, Pin tốt, Hiệu năng mượt\nNhược điểm: Giá hơi đắt, Hơi dày, Sạc chậm",
    "metadata": {
      "type": "review",
      "product_id": "phone_010",
      "rating": 5,
      "helpful_count": 89,
      "verified_purchase": true,
      "id": "review_034",
      "user_name": "Lý Thị K",
      "title": "Điện thoại ấn tượng - Camera xuất sắc",
      "content": "Nâng cấp từ Xiaomi 13 lên Realme 11 Pro+. Video quay mượt, chống rung tốt Đa nhiệm mượt, chuyển app nhanh Pin dùng thoải mái cả ngày Sẽ tiếp tục dùng brand này",
      "pros": [
        "Camera xuất sắc",
        "Pin tốt",
        "Hiệu năng mượt"
      ],
      "cons": [
        "Giá hơi đắt",
        "Hơi dày",
        "Sạc chậm"
      ],
      "date": "2025-07-19"
    }
  },
  {
    "id": "review_035",
    "text": "Review: Dell ấn tượng - Màn hình đẹp\nĐánh giá: 5/5\nNội dung: Chuyển từ Acer sang Dell. Cải thiện rõ rệt so với máy cũ Gaming và giải trí Đáng tiền bỏ ra Đáng để đầu tư\nƯu điểm: Màn hình đẹp, Thiết kế tinh tế, Bàn phím có đèn nền\nNhược điểm: SSD hơi nhỏ, Không có card reader, Webcam vị trí hơi thấp",
    "metadata": {
      "type": "review",
      "product_id": "laptop_001",
      "rating": 5,
      "helpful_count": 9,
      "verified_purchase": false,
      "id": "review_035",
      "user_name": "Bùi Thị H",
      "title": "Dell ấn tượng - Màn hình đẹp",
      "content": "Chuyển từ Acer sang Dell. Cải thiện rõ rệt so với máy cũ Gaming và giải trí Đáng tiền bỏ ra Đáng để đầu tư",
      "pros": [
        "Màn hình đẹp",
        "Thiết kế tinh tế",
        "Bàn phím có đèn nền"
      ],
      "cons": [
        "SSD hơi nhỏ",
        "Không có card reader",
        "Webcam vị trí hơi thấp"
      ],
      "date": "2025-08-07"
    }
  },
  {
    "id": "review_036",
    "text": "Review: Điện thoại ấn tượng - Camera ấn tượng\nĐánh giá: 4/5\nNội dung: Nâng cấp từ Xiaomi 13 lên Samsung Galaxy S24 Ultra. Camera chụp ảnh rất đẹp, màu sắc tự nhiên Nhiệt độ kiểm soát tốt Pin dùng thoải mái cả ngày Đáng tiền, recommend\nƯu điểm: Camera ấn tượng, Pin dài, Hiệu năng ổn định\nNhược điểm: Giá cao, Khó cầm một tay, Không có sạc không dây",
    "metadata": {
      "type": "review",
      "product_id": "phone_002",
      "rating": 4,
      "helpful_count": 31,
      "verified_purchase": true,
      "id": "review_036",
      "user_name": "Mai Thị Q",
      "title": "Điện thoại ấn tượng - Camera ấn tượng",
      "content": "Nâng cấp từ Xiaomi 13 lên Samsung Galaxy S24 Ultra. Camera chụp ảnh rất đẹp, màu sắc tự nhiên Nhiệt độ kiểm soát tốt Pin dùng thoải mái cả ngày Đáng tiền, recommend",
      "pros": [
        "Camera ấn tượng",
        "Pin dài",
        "Hiệu năng ổn định"
      ],
      "cons": [
        "Giá cao",
        "Khó cầm một tay",
        "Không có sạc không dây"
      ],
      "date": "2025-04-09"
    }
  },
  {
    "id": "review_037",
    "text": "Review: Laptop tuyệt vời cho văn phòng\nĐánh giá: 5/5\nNội dung: Mình dùng laptop này được 11 tháng cho văn phòng. Build code và compile rất nhanh Độ sáng tốt, làm việc ngoài trời OK Pin dùng được cả ngày làm việc Touchpad responsive\nƯu điểm: Hiệu năng mạnh mẽ, Màn hình đẹp, Pin trâu\nNhược điểm: Hơi dày, ấm khi render, Giá cao",
    "metadata": {
      "type": "review",
      "product_id": "laptop_003",
      "rating": 5,
      "helpful_count": 81,
      "verified_purchase": false,
      "id": "review_037",
      "user_name": "Trần Thị B",
      "title": "Laptop tuyệt vời cho văn phòng",
      "content": "Mình dùng laptop này được 11 tháng cho văn phòng. Build code và compile rất nhanh Độ sáng tốt, làm việc ngoài trời OK Pin dùng được cả ngày làm việc Touchpad responsive",
      "pros": [
        "Hiệu năng mạnh mẽ",
        "Màn hình đẹp",
        "Pin trâu"
      ],
      "cons": [
        "Hơi dày",
        "ấm khi render",
        "Giá cao"
      ],
      "date": "2025-02-27"
    }
  },
  {
    "id": "review_038",
    "text": "Review: Laptop tuyệt vời cho gaming\nĐánh giá: 3/5\nNội dung: Mình dùng laptop này được 7 tháng cho gaming. Gaming ở setting cao vẫn mượt Độ sáng tốt, làm việc ngoài trời OK Sạc nhanh, tiện lợi Build quality chắc chắn\nƯu điểm: Hiệu năng ổn định, Màn hình đẹp, Pin dài\nNhược điểm: Hơi to, nóng khi gaming, Giá không rẻ",
    "metadata": {
      "type": "review",
      "product_id": "laptop_003",
      "rating": 3,
      "helpful_count": 7,
      "verified_purchase": false,
      "id": "review_038",
      "user_name": "Phan Văn P",
      "title": "Laptop tuyệt vời cho gaming",
      "content": "Mình dùng laptop này được 7 tháng cho gaming. Gaming ở setting cao vẫn mượt Độ sáng tốt, làm việc ngoài trời OK Sạc nhanh, tiện lợi Build quality chắc chắn",
      "pros": [
        "Hiệu năng ổn định",
        "Màn hình đẹp",
        "Pin dài"
      ],
      "cons": [
        "Hơi to",
        "nóng khi gaming",
        "Giá không rẻ"
      ],
      "date": "2025-02-25"
    }
  },
  {
    "id": "review_039",
    "text": "Review: Dell hài lòng - Màn hình đẹp\nĐánh giá: 5/5\nNội dung: Chuyển từ Dell sang Dell. Trải nghiệm tốt hơn hẳn Gaming và giải trí Rất hài lòng với hiệu năng Sẽ mua lại brand này\nƯu điểm: Màn hình đẹp, Thiết kế đẹp, Cổng kết nối đầy đủ\nNhược điểm: SSD hơi nhỏ, Không có card reader, Dễ bám vân tay",
    "metadata": {
      "type": "review",
      "product_id": "laptop_001",
      "rating": 5,
      "helpful_count": 37,
      "verified_purchase": true,
      "id": "review_039",
      "user_name": "Đặng Văn G",
      "title": "Dell hài lòng - Màn hình đẹp",
      "content": "Chuyển từ Dell sang Dell. Trải nghiệm tốt hơn hẳn Gaming và giải trí Rất hài lòng với hiệu năng Sẽ mua lại brand này",
      "pros": [
        "Màn hình đẹp",
        "Thiết kế đẹp",
        "Cổng kết nối đầy đủ"
      ],
      "cons": [
        "SSD hơi nhỏ",
        "Không có card reader",
        "Dễ bám vân tay"
      ],
      "date": "2025-07-06"
    }
  },
  {
    "id": "review_040",
    "text": "Review: Điện thoại tốt - Camera chất lượng\nĐánh giá: 5/5\nNội dung: Nâng cấp từ Xiaomi 13 lên Samsung Galaxy A54 5G. Camera chụp ảnh rất đẹp, màu sắc tự nhiên Nhiệt độ kiểm soát tốt Wireless charging tiện Tổng thể rất hài lòng\nƯu điểm: Camera chất lượng, Pin dài, Hiệu năng cao\nNhược điểm: Giá cao, Khó cầm một tay, Cáp sạc ngắn",
    "metadata": {
      "type": "review",
      "product_id": "phone_007",
      "rating": 5,
      "helpful_count": 97,
      "verified_purchase": true,
      "id": "review_040",
      "user_name": "Hoàng Văn E",
      "title": "Điện thoại tốt - Camera chất lượng",
      "content": "Nâng cấp từ Xiaomi 13 lên Samsung Galaxy A54 5G. Camera chụp ảnh rất đẹp, màu sắc tự nhiên Nhiệt độ kiểm soát tốt Wireless charging tiện Tổng thể rất hài lòng",
      "pros": [
        "Camera chất lượng",
        "Pin dài",
        "Hiệu năng cao"
      ],
      "cons": [
        "Giá cao",
        "Khó cầm một tay",
        "Cáp sạc ngắn"
      ],
      "date": "2025-04-02"
    }
  },
  {
    "id": "review_041",
    "text": "Review: Điện thoại tuyệt vời - Camera đẹp\nĐánh giá: 5/5\nNội dung: Nâng cấp từ iPhone 14 lên OnePlus 12. Camera chụp ảnh rất đẹp, màu sắc tự nhiên Chơi game nặng vẫn ổn định Wireless charging tiện Đáng tiền, recommend\nƯu điểm: Camera đẹp, Pin trâu, Hiệu năng ổn định\nNhược điểm: Giá hơi đắt, Khó cầm một tay, Cáp sạc ngắn",
    "metadata": {
      "type": "review",
      "product_id": "phone_005",
      "rating": 5,
      "helpful_count": 65,
      "verified_purchase": true,
      "id": "review_041",
      "user_name": "Lê Văn C",
      "title": "Điện thoại tuyệt vời - Camera đẹp",
      "content": "Nâng cấp từ iPhone 14 lên OnePlus 12. Camera chụp ảnh rất đẹp, màu sắc tự nhiên Chơi game nặng vẫn ổn định Wireless charging tiện Đáng tiền, recommend",
      "pros": [
        "Camera đẹp",
        "Pin trâu",
        "Hiệu năng ổn định"
      ],
      "cons": [
        "Giá hơi đắt",
        "Khó cầm một tay",
        "Cáp sạc ngắn"
      ],
      "date": "2025-06-03"
    }
  },
  {
    "id": "review_042",
    "text": "Review: Laptop tuyệt vời cho gaming\nĐánh giá: 5/5\nNội dung: Mình dùng laptop này được 5 tháng cho gaming. Chạy các phần mềm nặng không lag Góc nhìn rộng, không bị lóa Thời lượng pin khá ổn Bàn phím gõ thoải mái\nƯu điểm: Hiệu năng mạnh mẽ, Màn hình tuyệt vời, Pin dài\nNhược điểm: Hơi to, ấm khi render, Giá cao",
    "metadata": {
      "type": "review",
      "product_id": "laptop_004",
      "rating": 5,
      "helpful_count": 50,
      "verified_purchase": true,
      "id": "review_042",
      "user_name": "Đỗ Thị M",
      "title": "Laptop tuyệt vời cho gaming",
      "content": "Mình dùng laptop này được 5 tháng cho gaming. Chạy các phần mềm nặng không lag Góc nhìn rộng, không bị lóa Thời lượng pin khá ổn Bàn phím gõ thoải mái",
      "pros": [
        "Hiệu năng mạnh mẽ",
        "Màn hình tuyệt vời",
        "Pin dài"
      ],
      "cons": [
        "Hơi to",
        "ấm khi render",
        "Giá cao"
      ],
      "date": "2025-05-14"
    }
  },
  {
    "id": "review_043",
    "text": "Review: Điện thoại tốt - Camera xuất sắc\nĐánh giá: 5/5\nNội dung: Nâng cấp từ Xiaomi 14 lên Realme 11 Pro+. Zoom xa vẫn net, chụp đêm ổn Đa nhiệm mượt, chuyển app nhanh Wireless charging tiện Đáng tiền, recommend\nƯu điểm: Camera xuất sắc, Pin tốt, Hiệu năng mượt\nNhược điểm: Giá đắt, Hơi dày, Sạc chậm",
    "metadata": {
      "type": "review",
      "product_id": "phone_010",
      "rating": 5,
      "helpful_count": 33,
      "verified_purchase": true,
      "id": "review_043",
      "user_name": "Ngô Văn L",
      "title": "Điện thoại tốt - Camera xuất sắc",
      "content": "Nâng cấp từ Xiaomi 14 lên Realme 11 Pro+. Zoom xa vẫn net, chụp đêm ổn Đa nhiệm mượt, chuyển app nhanh Wireless charging tiện Đáng tiền, recommend",
      "pros": [
        "Camera xuất sắc",
        "Pin tốt",
        "Hiệu năng mượt"
      ],
      "cons": [
        "Giá đắt",
        "Hơi dày",
        "Sạc chậm"
      ],
      "date": "2025-06-18"
    }
  },
  {
    "id": "review_044",
    "text": "Review: Laptop tuyệt vời cho gaming\nĐánh giá: 5/5\nNội dung: Mình dùng laptop này được 6 tháng cho gaming. Build code và compile rất nhanh Độ sáng tốt, làm việc ngoài trời OK Pin hơi yếu khi gaming Thiết kế đẹp, sang trọng\nƯu điểm: Hiệu năng mạnh mẽ, Màn hình chất lượng, Pin tốt\nNhược điểm: Hơi nặng, nóng khi gaming, Giá không rẻ",
    "metadata": {
      "type": "review",
      "product_id": "laptop_002",
      "rating": 5,
      "helpful_count": 87,
      "verified_purchase": false,
      "id": "review_044",
      "user_name": "Ngô Văn L",
      "title": "Laptop tuyệt vời cho gaming",
      "content": "Mình dùng laptop này được 6 tháng cho gaming. Build code và compile rất nhanh Độ sáng tốt, làm việc ngoài trời OK Pin hơi yếu khi gaming Thiết kế đẹp, sang trọng",
      "pros": [
        "Hiệu năng mạnh mẽ",
        "Màn hình chất lượng",
        "Pin tốt"
      ],
      "cons": [
        "Hơi nặng",
        "nóng khi gaming",
        "Giá không rẻ"
      ],
      "date": "2025-02-18"
    }
  },
  {
    "id": "review_045",
    "text": "Review: Điện thoại xuất sắc - Camera ấn tượng\nĐánh giá: 5/5\nNội dung: Nâng cấp từ Samsung 14 lên iPhone 15. Camera chụp ảnh rất đẹp, màu sắc tự nhiên Hiệu năng mượt mà, không lag Pin dùng thoải mái cả ngày Nâng cấp đáng giá\nƯu điểm: Camera ấn tượng, Pin trâu, Hiệu năng mượt\nNhược điểm: Giá hơi đắt, To và nặng, Sạc chậm",
    "metadata": {
      "type": "review",
      "product_id": "phone_006",
      "rating": 5,
      "helpful_count": 9,
      "verified_purchase": true,
      "id": "review_045",
      "user_name": "Lưu Văn T",
      "title": "Điện thoại xuất sắc - Camera ấn tượng",
      "content": "Nâng cấp từ Samsung 14 lên iPhone 15. Camera chụp ảnh rất đẹp, màu sắc tự nhiên Hiệu năng mượt mà, không lag Pin dùng thoải mái cả ngày Nâng cấp đáng giá",
      "pros": [
        "Camera ấn tượng",
        "Pin trâu",
        "Hiệu năng mượt"
      ],
      "cons": [
        "Giá hơi đắt",
        "To và nặng",
        "Sạc chậm"
      ],
      "date": "2025-08-12"
    }
  },
  {
    "id": "review_046",
    "text": "Review: Điện thoại tuyệt vời - Camera ấn tượng\nĐánh giá: 5/5\nNội dung: Nâng cấp từ Samsung 11 lên Xiaomi Redmi Note 13 Pro+ 5G. Portrait mode và night mode ấn tượng Hiệu năng mượt mà, không lag Pin dùng thoải mái cả ngày Nâng cấp đáng giá\nƯu điểm: Camera ấn tượng, Pin dài, Hiệu năng mượt\nNhược điểm: Giá hơi đắt, Hơi dày, Cáp sạc ngắn",
    "metadata": {
      "type": "review",
      "product_id": "phone_008",
      "rating": 5,
      "helpful_count": 20,
      "verified_purchase": true,
      "id": "review_046",
      "user_name": "Hồ Văn N",
      "title": "Điện thoại tuyệt vời - Camera ấn tượng",
      "content": "Nâng cấp từ Samsung 11 lên Xiaomi Redmi Note 13 Pro+ 5G. Portrait mode và night mode ấn tượng Hiệu năng mượt mà, không lag Pin dùng thoải mái cả ngày Nâng cấp đáng giá",
      "pros": [
        "Camera ấn tượng",
        "Pin dài",
        "Hiệu năng mượt"
      ],
      "cons": [
        "Giá hơi đắt",
        "Hơi dày",
        "Cáp sạc ngắn"
      ],
      "date": "2025-08-05"
    }
  },
  {
    "id": "review_047",
    "text": "Review: Điện thoại hài lòng - Camera tốt\nĐánh giá: 5/5\nNội dung: Nâng cấp từ Xiaomi 13 lên OPPO Reno11 5G. Portrait mode và night mode ấn tượng Nhiệt độ kiểm soát tốt Pin hơi yếu khi dùng nhiều Sẽ tiếp tục dùng brand này\nƯu điểm: Camera tốt, Pin ổn, Hiệu năng cao\nNhược điểm: Giá hơi đắt, Hơi dày, Sạc chậm",
    "metadata": {
      "type": "review",
      "product_id": "phone_009",
      "rating": 5,
      "helpful_count": 72,
      "verified_purchase": false,
      "id": "review_047",
      "user_name": "Hồ Văn N",
      "title": "Điện thoại hài lòng - Camera tốt",
      "content": "Nâng cấp từ Xiaomi 13 lên OPPO Reno11 5G. Portrait mode và night mode ấn tượng Nhiệt độ kiểm soát tốt Pin hơi yếu khi dùng nhiều Sẽ tiếp tục dùng brand này",
      "pros": [
        "Camera tốt",
        "Pin ổn",
        "Hiệu năng cao"
      ],
      "cons": [
        "Giá hơi đắt",
        "Hơi dày",
        "Sạc chậm"
      ],
      "date": "2025-07-21"
    }
  },
  {
    "id": "review_048",
    "text": "Review: Điện thoại ấn tượng - Camera xuất sắc\nĐánh giá: 5/5\nNội dung: Nâng cấp từ Samsung 11 lên Realme 11 Pro+. Zoom xa vẫn net, chụp đêm ổn Chơi game nặng vẫn ổn định Sạc nhanh, tiện lợi Đáng tiền, recommend\nƯu điểm: Camera xuất sắc, Pin tốt, Hiệu năng ổn định\nNhược điểm: Giá đắt, Khó cầm một tay, Sạc chậm",
    "metadata": {
      "type": "review",
      "product_id": "phone_010",
      "rating": 5,
      "helpful_count": 10,
      "verified_purchase": true,
      "id": "review_048",
      "user_name": "Trần Thị B",
      "title": "Điện thoại ấn tượng - Camera xuất sắc",
      "content": "Nâng cấp từ Samsung 11 lên Realme 11 Pro+. Zoom xa vẫn net, chụp đêm ổn Chơi game nặng vẫn ổn định Sạc nhanh, tiện lợi Đáng tiền, recommend",
      "pros": [
        "Camera xuất sắc",
        "Pin tốt",
        "Hiệu năng ổn định"
      ],
      "cons": [
        "Giá đắt",
        "Khó cầm một tay",
        "Sạc chậm"
      ],
      "date": "2025-05-22"
    }
  },
  {
    "id": "review_049",
    "text": "Review: ASUS ấn tượng - Hiệu năng cao\nĐánh giá: 5/5\nNội dung: Chuyển từ Acer sang ASUS. Ban đầu hơi khó quen nhưng giờ thì ổn Học tập và nghiên cứu Rất hài lòng với hiệu năng Sẽ mua lại brand này\nƯu điểm: Hiệu năng cao, Thiết kế tinh tế, Cổng kết nối đầy đủ\nNhược điểm: Không có DVD drive, Không có card reader, Webcam vị trí hơi thấp",
    "metadata": {
      "type": "review",
      "product_id": "laptop_003",
      "rating": 5,
      "helpful_count": 67,
      "verified_purchase": true,
      "id": "review_049",
      "user_name": "Lý Thị K",
      "title": "ASUS ấn tượng - Hiệu năng cao",
      "content": "Chuyển từ Acer sang ASUS. Ban đầu hơi khó quen nhưng giờ thì ổn Học tập và nghiên cứu Rất hài lòng với hiệu năng Sẽ mua lại brand này",
      "pros": [
        "Hiệu năng cao",
        "Thiết kế tinh tế",
        "Cổng kết nối đầy đủ"
      ],
      "cons": [
        "Không có DVD drive",
        "Không có card reader",
        "Webcam vị trí hơi thấp"
      ],
      "date": "2025-06-09"
    }
  },
  {
    "id": "review_050",
    "text": "Review: Điện thoại tuyệt vời - Camera đẹp\nĐánh giá: 5/5\nNội dung: Nâng cấp từ iPhone 12 lên Xiaomi Redmi Note 13 Pro+ 5G. Portrait mode và night mode ấn tượng Chơi game nặng vẫn ổn định Wireless charging tiện Nâng cấp đáng giá\nƯu điểm: Camera đẹp, Pin dài, Hiệu năng cao\nNhược điểm: Giá đắt, Hơi dày, Sạc chậm",
    "metadata": {
      "type": "review",
      "product_id": "phone_008",
      "rating": 5,
      "helpful_count": 62,
      "verified_purchase": true,
      "id": "review_050",
      "user_name": "Vũ Thị F",
      "title": "Điện thoại tuyệt vời - Camera đẹp",
      "content": "Nâng cấp từ iPhone 12 lên Xiaomi Redmi Note 13 Pro+ 5G. Portrait mode và night mode ấn tượng Chơi game nặng vẫn ổn định Wireless charging tiện Nâng cấp đáng giá",
      "pros": [
        "Camera đẹp",
        "Pin dài",
        "Hiệu năng cao"
      ],
      "cons": [
        "Giá đắt",
        "Hơi dày",
        "Sạc chậm"
      ],
      "date": "2025-03-25"
    }
  }
]